Workbook
Name 会社名: [1]顧客リスト!$C$2:$N$2

Sheet 見積・請求書→

Sheet トヨタ紡織→
A1: 2024年 | C1: エンジニアリングサービス部 見積書・請求書発行管理台帳 | H1: 見積書(税抜金額) | M1: 請求書(税抜金額) | R1: 出張費請求書(税抜金額) | V1: 業務委託契約書
A2: 企業名： | C2: トヨタ紡織(株)
A3: タスク | B3: No | C3: 部署名 | D3: 見積/請求番号 | E3: 発注番号 | F3: 業務計画書No | G3: 案件名 | H3: 見積金額 | I3: 見積月 | J3: 発行日 | K3: 発行者 | L3: 枝番 | M3: 請求金額 | N3: 請求月 | O3: 発行日 | P3: 発行者 | Q3: 番号 | R3: 金額 | S3: 請求月 | T3: 発行日 | U3: 発行者 | V3: 収入印紙 | W3: 返送日 | X3: 送付先 | Y3: 発行者 | Z3: 備考

Sheet A1
A1: 2025年 | C1: エンジニアリングサービス部 見積書・請求書発行管理台帳 | H1: 見積書(税抜金額)
A2: 企業名： | C2: トヨタ紡織(株)
A3: タスク | B3: No | C3: 部署名 | D3: 見積/請求番号 | E3: 発注番号 | F3: 業務計画書No | G3: 案件名 | H3: 見積金額 | I3: 見積月 | J3: 発行日 | K3: 発行者 | L3: 備考
A4: 完了 | B4: 1 | C4: 第1シート設計部 | D4: 16100016 | E4: A13-R22-010 | F4: - | G4: DASデータまとめ | I4: 1月 | J4: 44903 | K4: 鈴木
A5: 完了 | B5: 2 | C5: 第1シート設計部 | D5: 16100017 | E5: A13-R22-011 | F5: - | G5: DASデータまとめ | I5: 2月 | J5: 44937 | K5: 鈴木
A6: 完了 | B6: 3 | C6: 第1シート設計部 | D6: 16100018 | E6: A13-R22-014 | F6: - | G6: DASデータまとめ | I6: 3月 | J6: 44966 | K6: 鈴木
A7: 完了 | B7: 4 | C7: 第1シート設計部 | D7: 16100019 | E7: A13-R22-016 | F7: - | G7: DASデータまとめ | I7: 4月 | J7: 44999 | K7: 鈴木
A8: 完了 | B8: 5 | C8: 第1シート設計部 | D8: 16100020 | F8: - | G8: DASデータまとめ | I8: 5月 | J8: 45023 | K8: 鈴木
A9: 完了 | B9: 6 | C9: 第1シート設計部 | D9: 16100021 | F9: - | G9: DASデータまとめ | I9: 6月 | J9: 45063 | K9: 鈴木
A10: 完了 | B10: 7 | C10: 第1シート設計部 | D10: 16100022 | F10: - | G10: DASデータまとめ | I10: 7月 | J10: 45085 | K10: 鈴木
A11: 完了 | B11: 8 | C11: 第1シート設計部 | D11: 16100023 | F11: - | G11: DASデータまとめ | I11: 8月 | J11: 45112 | K11: 鈴木
A12: 完了 | B12: 9 | C12: 第1シート設計部 | D12: 16100024 | F12: - | G12: DASデータまとめ | I12: 9月 | J12: 45148 | K12: 鈴木
A13: 完了 | B13: 10 | C13: 第1シート設計部 | D13: 16100025 | F13: - | G13: DASデータまとめ | I13: 10月 | J13: 45183 | K13: 齊藤
A14: 完了 | B14: 11 | C14: 第1シート設計部 | D14: 16100026 | F14: - | G14: DASデータまとめ | I14: 11月 | J14: 45210 | K14: 齊藤
A15: 完了 | B15: 12 | C15: 第1シート設計部 | D15: 16100027 | F15: - | G15: DASデータまとめ | I15: 12月 | J15: 45243 | K15: 齊藤
A16: 進行中 | B16: 13 | C16: 第1シート設計部 | D16: 16100028 | F16: - | G16: DASデータまとめ | I16: 1月 | J16: 45266 | K16: 齊藤
B17: 14 | C17: 第1シート設計部 | D17: 16100029 | F17: - | G17: DASデータまとめ | I17: 2月 | J17: 45309 | K17: 齊藤
B18: 15 | C18: 第1シート設計部 | D18: 16100030 | F18: - | G18: DASデータまとめ | I18: 3月 | J18: 45328 | K18: 齊藤
B19: 16 | C19: 第1シート設計部 | D19: 16100031 | F19: - | G19: DASデータまとめ | I19: 4月 | J19: 45364 | K19: 齊藤
B20: 17 | C20: 第1シート設計部 | D20: 16100032 | F20: - | G20: DASデータまとめ | I20: 5月 | J20: 45390 | K20: 齊藤
B21: 18 | C21: 第1シート設計部 | D21: 16100033 | F21: - | G21: DASデータまとめ | I21: 6月 | J21: 45422 | K21: 齊藤
B22: 19 | C22: 第1シート設計部 | D22: 16100034 | F22: - | G22: DASデータまとめ | I22: 7月 | J22: 45453 | K22: 齊藤
B23: 20 | C23: 第1シート設計部 | D23: 16100035 | F23: - | G23: DASデータまとめ | I23: 8月 | J23: 45481 | K23: 齊藤
B24: 21 | C24: 第1シート設計部 | D24: 16100036 | F24: - | G24: DASデータまとめ | I24: 9月 | J24: 45510 | K24: 齊藤
B25: 22 | C25: 第1シート設計部 | D25: 16100037 | F25: - | G25: DASデータまとめ | I25: 10月 | J25: 45544 | K25: 久目形
B26: 23 | C26: 第1シート設計部 | D26: 16100038 | F26: - | G26: DASデータまとめ | I26: 11月 | J26: 45583 | K26: 久目形
B27: 24 | C27: 第1シート設計部 | D27: 16100039 | F27: - | G27: DASデータまとめ | I27: 12月 | J27: 45604 | K27: 久目形
B28: 25 | C28: 第1シート設計部 | D28: 16100040 | F28: - | G28: DASデータまとめ | I28: 1月 | J28: 45997 | K28: 久目形
B29: 26 | C29: 第1シート設計部 | D29: 16100041 | F29: - | G29: DASデータまとめ | I29: 2月 | J29: 45672 | K29: 久目形
B30: 27 | D30: 16100042
B31: 28 | C31: 第1シート設計部 | D31: 16100043 | F31: - | G31: DASデータまとめ | I31: 3月 | J31: 45699 | K31: 久目形
B32: 29 | C32: 第1シート設計部 | D32: 16100044 | F32: - | G32: DASデータまとめ | I32: 4月 | J32: 45735 | K32: 久目形
B33: 30 | C33: 第1シート設計部 | D33: 16100045 | F33: - | G33: DASデータまとめ | I33: ５月 | J33: 45761 | K33: 丸山
B34: 31 | C34: 第1シート設計部 | D34: 16100046 | F34: - | G34: DASデータまとめ | I34: 6月 | J34: ’25/5/13 | K34: 丸山
B35: 32 | C35: 第1シート設計部 | D35: 16100047 | F35: - | G35: DASデータまとめ | I35: 7月 | J35: ’25/6/9 | K35: 久目形
B36: 33 | C36: 第1シート設計部 | D36: 16100048 | F36: - | G36: DASデータまとめ | I36: 8月 | J36: ’25/7/4 | K36: 久目形
B37: 34 | C37: 第1シート設計部 | D37: 16100049 | F37: - | G37: DASデータまとめ | I37: 9月 | J37: ’25/8/6 | K37: 久目形
B38: 35 | C38: 第1シート設計部 | D38: 16100050 | F38: - | G38: DASデータまとめ | I38: 10月 | J38: ’25/9/8 | K38: 久目形
B39: 36 | C39: 第1シート設計部 | D39: 16100051 | F39: - | G39: DASデータまとめ | I39: 11月 | J39: ’25/10/6 | K39: 久目形
B40: 37 | C40: 第1シート設計部 | D40: 16100052 | F40: - | G40: DASデータまとめ | I40: 12月 | J40: ’25/11/10 | K40: 久目形
B41: 38 | C41: 第1シート設計部 | D41: 16100053 | F41: - | G41: DASデータまとめ | I41: 1月 | J41: 45996 | K41: 久目形
B42: 39 | D42: 16100054
B43: 40 | D43: 16100055
B44: 41 | D44: 16100056
B45: 42 | D45: 16100057
B46: 43 | D46: 16100058
B47: 44 | D47: 16100059
B48: 45 | D48: 16100060
B49: 46 | D49: 16100061
B50: 47 | D50: 16100062
B51: 48 | D51: 16100063
B52: 49 | D52: 16100064
B53: 50 | D53: 16100065
... B55: 52 | D55: 16100067

Sheet A11
A1: 2024年 | C1: エンジニアリングサービス部 見積書・請求書発行管理台帳 | H1: 見積書(税抜金額)
A2: 企業名： | C2: トヨタ紡織(株)
A3: タスク | B3: No | C3: 部署名 | D3: 見積/請求番号 | E3: 発注番号 | F3: 業務計画書No | G3: 案件名 | H3: 見積金額 | I3: 見積月 | J3: 発行日 | K3: 発行者 | L3: 備考
A4: 完了 | B4: 1 | C4: 第1シート設計部第11シート設計室 | D4: 16113002 | F4: 9591 | G4: 320D | I4: 6月 | J4: 45078 | K4: 鈴木
A5: 完了 | B5: 2 | C5: 第1シート設計部第11シート設計室 | D5: 16113003 | F5: 9787 | G5: 320D | I5: 7月 | J5: 45103 | K5: 鈴木
A6: 進行中 | B6: 3 | C6: 第1シート設計部第11シート設計室 | D6: 16113004 | F6: 10172 | G6: 320D | I6: 8月 | J6: 45128 | K6: 鈴木
B7: 4 | D7: 16113005
B8: 5 | D8: 16113006
B9: 6 | D9: 16113007
B10: 7 | D10: 16113008
B11: 8 | D11: 16113009
B12: 9 | D12: 16113010
B13: 10 | D13: 16113011
B14: 11 | D14: 16113012
B15: 12 | D15: 16113013
B16: 13 | D16: 16113014

Sheet A12
A1: 2024年 | C1: エンジニアリングサービス部 見積書・請求書発行管理台帳 | H1: 見積書(税抜金額)
A2: 企業名： | C2: トヨタ紡織(株)
A3: タスク | B3: No | C3: 部署名 | D3: 見積/請求番号 | E3: 発注番号 | F3: 業務計画書No | G3: 案件名 | H3: 見積金額 | I3: 見積月 | J3: 発行日 | K3: 発行者 | L3: 備考
A4: 完了 | B4: 1 | C4: 第1シート設計部第12シート設計室 | D4: 16108162 | E4: 802-2212-0031-000 | F4: ITK08249 | G4: 330D | I4: 1月 | J4: 44923 | K4: 鈴木
A5: 完了 | B5: 2 | C5: 第1シート設計部第12シート設計室 | D5: 16108163 | E5: 802-2212-0032-000 | F5: ITK08248 | G5: 440D | I5: 1月 | J5: 44923 | K5: 鈴木
A6: 完了 | B6: 3 | C6: 第1シート設計部第12シート設計室 | D6: 16108164 | E6: 802-2212-0104-000 | F6: ITK08116 | G6: 460B | I6: 1月 | J6: 44923 | K6: 鈴木
A7: 完了 | B7: 4 | C7: 第1シート設計部第12シート設計室 | D7: 16108165 | E7: 802-2301-0027-000 | F7: 8515 | G7: 330D | I7: 2月 | J7: 44960 | K7: 鈴木
A8: 完了 | B8: 5 | C8: 第1シート設計部第12シート設計室 | D8: 16108166 | E8: 802-2301-0026-000 | F8: 8516 | G8: 440D | I8: 2月 | J8: 44965 | K8: 鈴木
A9: 完了 | B9: 6 | C9: 第1シート設計部第12シート設計室 | D9: 16108167 | E9: 802-2301-0021-000 | F9: 8564 | G9: 460B | I9: 2月 | J9: 44965 | K9: 鈴木
A10: 完了 | B10: 7 | C10: 第1シート設計部第12シート設計室 | D10: 16108168 | E10: 802-2301-0023-000 | F10: 8557 | G10: 440D追加 | I10: 2月 | J10: 44965 | K10: 鈴木
A11: 完了 | B11: 8 | C11: 第1シート設計部第12シート設計室 | D11: 16108169 | F11: 8750 | G11: 330D | I11: 3月 | J11: 44994 | K11: 鈴木
A12: 完了 | B12: 9 | C12: 第1シート設計部第12シート設計室 | D12: 16108170 | F12: 8751 | G12: 440D | I12: 3月 | J12: 44994 | K12: 鈴木
A13: 完了 | B13: 10 | C13: 第1シート設計部第12シート設計室 | D13: 16108171 | F13: 8807 | G13: 460B | I13: 3月 | J13: 44994 | K13: 鈴木
A14: 完了 | B14: 11 | C14: 第1シート設計部第12シート設計室 | D14: 16108172 | F14: 9021 | G14: 440D | I14: 4月 | J14: 45016 | K14: 鈴木
A15: 完了 | B15: 12 | C15: 第1シート設計部第12シート設計室 | D15: 16108173 | F15: 9133 | G15: B626(440D) | I15: 4月 | J15: 45019 | K15: 鈴木
A16: 完了 | B16: 13 | C16: 第1シート設計部第12シート設計室 | D16: 16108174 | F16: 9327 | G16: 440D | I16: 5月 | J16: 45044 | K16: 鈴木
A17: 完了 | B17: 14 | C17: 第1シート設計部第12シート設計室 | D17: 16108175 | F17: 9544 | G17: 440D | I17: 6月 | J17: 45078 | K17: 鈴木
A18: 完了 | B18: 15 | C18: 第1シート設計部第12シート設計室 | D18: 16108176 | F18: 9651 | G18: 440D | I18: 7月 | J18: 45105 | K18: 鈴木
A19: 完了 | B19: 16 | C19: 第1シート設計部第12シート設計室 | D19: 16108177 | F19: 10065 | G19: 440D 追加 | I19: 7月 | J19: 45119 | K19: 鈴木
A20: 完了 | B20: 17 | C20: 第1シート設計部第12シート設計室 | D20: 16108178 | F20: 10053 | G20: 440D | I20: 8月 | J20: 45128 | K20: 鈴木
A21: 完了 | B21: 18 | C21: 第1シート設計部第12シート設計室 | D21: 16108179 | F21: 10361 | G21: 440D | I21: 9月 | J21: 45148 | K21: 鈴木
A22: 完了 | B22: 19 | C22: 第1シート設計部第12シート設計室 | D22: 16108180 | F22: 10711 | G22: 440D | I22: 10月 | J22: 45198 | K22: 齊藤
... A24: 完了 | B24: 21 | C24: 第1シート設計部第12シート設計室 | D24: 16108182 | F24: 11332 | G24: 440D | I24: 12月 | J24: 45252 | K24: 齊藤
B25: 22 | C25: 第1シート設計部第12シート設計室 | D25: 16108183 | F25: ITK11621 | G25: 440D | I25: 1月 | J25: 45279 | K25: 齊藤
B26: 23 | C26: 第1シート設計部第12シート設計室 | D26: 16108184 | F26: 11871 | G26: 440D | I26: 2月 | J26: 45310 | K26: 齊藤
B27: 24 | C27: 第1シート設計部第12シート設計室 | D27: 16108185 | F27: 12017 | G27: 440D | I27: 3月 | J27: 45337 | K27: 齊藤
B28: 25 | C28: 第1シート設計部第12シート設計室 | D28: 16108186 | F28: ITK12247 | G28: 440D | I28: 4月 | J28: 45377 | K28: 齊藤
B29: 26 | C29: 第1シート設計部第12シート設計室 | D29: 16108187 | F29: ITK12248 | G29: 330D | I29: 4月 | J29: 45377 | K29: 齊藤
B30: 27 | C30: 第1シート設計部第12シート設計室 | D30: 16108188 | F30: ITK12620 | G30: 440Ｄ | I30: 5月 | J30: 45401 | K30: 齊藤
B31: 28 | C31: 第1シート設計部第12シート設計室 | D31: 16108189 | F31: ITK12621 | G31: 330D | I31: 5月 | J31: 45401 | K31: 齊藤
B32: 29 | C32: 第1シート設計部第12シート設計室 | D32: 16108190 | F32: ITK12871 | G32: 440Ｄ | I32: 6月 | J32: 45433 | K32: 齊藤
B33: 30 | C33: 第1シート設計部第12シート設計室 | D33: 16108191 | F33: ITK12858 | G33: 330D | I33: 6月 | J33: 45435 | K33: 齊藤
B34: 31 | C34: 第1シート設計部第12シート設計室 | D34: 16108192 | F34: 13198 | G34: 330D | I34: 7月 | J34: 45467 | K34: 齊藤
B35: 32 | C35: 第1シート設計部第12シート設計室 | D35: 16108193 | F35: 13199 | G35: 440Ｄ | I35: 7月 | J35: 45467 | K35: 齊藤
B36: 33 | C36: 第1シート設計部第12シート設計室 | D36: 16108194 | F36: 13581 | G36: 440Ｄ | I36: 8月 | J36: '24/7/16 | K36: 齊藤
B37: 34 | C37: 第1シート設計部第12シート設計室 | D37: 16108195 | F37: 13574 | G37: 330D | I37: 8月 | J37: '24/7/16 | K37: 齊藤
B38: 35 | C38: 第1シート設計部第12シート設計室 | D38: 16108196 | F38: 13773 | G38: 330D | I38: 9月 | J38: '24/8/21 | K38: 齊藤
B39: 36 | C39: 第1シート設計部第12シート設計室 | D39: 16108197 | F39: 13774 | G39: 440Ｄ | I39: 9月 | J39: '24/8/21 | K39: 齊藤
B40: 37 | C40: 第1シート設計部第12シート設計室 | D40: 16108198 | F40: 14089 | G40: 330D | I40: 10月 | J40: '24/10/3 | K40: 久目形
B41: 38 | C41: 第1シート設計部第12シート設計室 | D41: 16108199 | F41: 14088 | G41: 440Ｄ | I41: 10月 | J41: '24/10/3 | K41: 久目形
B42: 39 | C42: 第1シート設計部第12シート設計室 | D42: 16108200 | F42: 14366 | G42: 330D | I42: 11月 | J42: '24/11/1 | K42: 久目形
B43: 40 | C43: 第1シート設計部第12シート設計室 | D43: 16108201 | F43: 14365 | G43: 440Ｄ | I43: 11月 | J43: '24/11/1 | K43: 久目形
B44: 41 | C44: 第1シート設計部第12シート設計室 | D44: 16108202 | F44: 14684 | G44: 330D | I44: 12月 | J44: '24/11/29 | K44: 久目形
B45: 42 | C45: 第1シート設計部第12シート設計室 | D45: 16108203 | F45: 14685 | G45: 440Ｄ | I45: 12月 | J45: '24/11/29 | K45: 久目形
B46: 43 | C46: 第1シート設計部第12シート設計室 | D46: 16108204 | F46: 14834 | G46: 330D | I46: 1月 | J46: 45645 | K46: 久目形
B47: 44 | C47: 第1シート設計部第12シート設計室 | D47: 16108205 | F47: 14835 | G47: 440Ｄ | I47: 1月 | J47: 45645 | K47: 久目形
B48: 45 | C48: 第1シート設計部第12シート設計室 | D48: 16108206 | F48: 15101 | G48: 330D | I48: 2月 | J48: 202/2/29 | K48: 久目形
B49: 46 | C49: 第1シート設計部第12シート設計室 | D49: 16108207 | F49: 15102 | G49: 440Ｄ | I49: 2月 | J49: 202/2/29 | K49: 久目形
B50: 47 | C50: 第1シート設計部第12シート設計室 | D50: 16108208 | F50: 15240 | G50: 330D | I50: 3月 | J50: 2025/2/26 | K50: 久目形
B51: 48 | C51: 第1シート設計部第12シート設計室 | D51: 16108209 | F51: 15253 | G51: 440Ｄ | I51: 3月 | J51: 2025/2/26 | K51: 久目形
B52: 49 | C52: 第1シート設計部第12シート設計室 | D52: 16108210 | F52: ITK15653 | G52: 440Ｄ | I52: 4月 | J52: 45750 | K52: 丸山
B53: 50 | C53: 第1シート設計部第12シート設計室 | D53: 16108211 | F53: ITK15723 | G53: 440Ｄ | I53: 5月 | J53: 45784 | K53: 丸山
B54: 51 | C54: 第1シート設計部第12シート設計室 | D54: 16108212 | F54: 16144 | G54: 440Ｄ | I54: 7月 | J54: ’25/6/10 | K54: 久目形
B55: 52 | C55: 第1シート設計部第12シート設計室 | D55: 16108213 | F55: 16386 | G55: 440Ｄ | I55: 7月 | J55: 45835 | K55: 久目形
B56: 53 | C56: 第1シート設計部第12シート設計室 | D56: 16108214 | F56: 16696 | G56: 440Ｄ | I56: 8月 | J56: ’25/7/21 | K56: 久目形
B57: 54 | C57: 第1シート設計部第12シート設計室 | D57: 16108215 | F57: 16927 | G57: 440Ｄ | I57: 9月 | J57: 45889 | K57: 久目形
B58: 55 | C58: 第1シート設計部第12シート設計室 | D58: 16108216 | F58: 17200 | G58: 440D | I58: 10月 | J58: 45916 | K58: 久目形
B59: 56 | C59: 第1シート設計部第12シート設計室 | D59: 16108217 | F59: 17450 | G59: 440D | I59: 11月 | J59: 45946 | K59: 久目形
B60: 57 | C60: 第1シート設計部第12シート設計室 | D60: 16108218 | F60: 17761 | G60: 440D | I60: 12月 | J60: 45975 | K60: 久目形
B61: 58 | C61: 第1シート設計部第12シート設計室 | D61: 16108219 | F61: 17986 | G61: 440D | I61: １月 | J61: 46008 | K61: 久目形
B62: 59 | D62: 16108220
B63: 60 | D63: 16108221
B64: 61 | D64: 16108222
B65: 62 | D65: 16108223
B66: 63 | D66: 16108224

Sheet A13
A1: 2023年 | C1: エンジニアリングサービス部 見積書・請求書発行管理台帳 | H1: 見積書(税抜金額)
A2: 企業名： | C2: トヨタ紡織(株)
A3: タスク | B3: No | C3: 部署名 | D3: 見積/請求番号 | E3: 発注番号 | F3: 業務計画書No | G3: 案件名 | H3: 見積金額 | I3: 見積月 | J3: 発行日 | K3: 発行者 | L3: 備考
A4: 完了 | B4: 1 | C4: 第1シート設計部第13シート設計室 | D4: 16101111 | E4: 802-2212-0157-000 | F4: ITK08044 | G4: 759W | H4: 391300 | I4: 1月 | J4: 44923 | K4: 鈴木
A5: 完了 | B5: 2 | C5: 第1シート設計部第13シート設計室 | D5: 16101112 | E5: 802-2212-0092-000 | F5: ITK08147 | G5: 400BX | H5: 774000 | I5: 1月 | J5: 44923 | K5: 鈴木
A6: 完了 | B6: 3 | C6: 第1シート設計部第13シート設計室 | D6: 16101113 | E6: 802-2212-0089-000 | F6: ITK08151 | G6: 738W(400B)_VA | H6: 323000 | I6: 1月 | J6: 44923 | K6: 鈴木
A7: 完了 | B7: 4 | C7: 第1シート設計部第13シート設計室 | D7: 16101114 | E7: 802-2212-0091-000 | F7: ITK08148 | G7: 345D | H7: 119000 | I7: 1月 | J7: 44923 | K7: 鈴木
A8: 完了 | B8: 5 | C8: 第1シート設計部第13シート設計室 | D8: 16101115 | E8: 802-2212-0090-000 | F8: ITK08149 | G8: 346D | H8: 655000 | I8: 1月 | J8: 44923 | K8: 鈴木
A9: 完了 | B9: 6 | C9: 第1シート設計部第13シート設計室 | D9: 16101116 | E9: 802-2301-0063-000 | F9: 8444 | G9: 759W 号口 | H9: 240800 | I9: 2月 | J9: 44959 | K9: 鈴木
A10: 完了 | B10: 7 | C10: 第1シート設計部第13シート設計室 | D10: 16101117 | E10: 802-2301-0066-000 | F10: 8436 | G10: 400BX | H10: 774000 | I10: 2月 | J10: 44960 | K10: 鈴木
A11: 完了 | B11: 8 | C11: 第1シート設計部第13シート設計室 | D11: 16101118 | E11: 802-2301-0059-000 | F11: 8449 | G11: 400B VA | H11: 512000 | I11: 2月 | J11: 44960 | K11: 鈴木
A12: 完了 | B12: 9 | C12: 第1シート設計部第13シート設計室 | D12: 16101119 | E12: 802-2301-0065-000 | F12: 8437 | G12: 345D | H12: 807000 | I12: 2月 | J12: 44960 | K12: 鈴木
A13: 完了 | B13: 10 | C13: 第1シート設計部第13シート設計室 | D13: 16101120 | E13: 802-2302-0091-000 | F13: 8651 | G13: 759W 号口 | H13: 365500 | I13: 3月 | J13: 44984 | K13: 鈴木
A14: 完了 | B14: 11 | C14: 第1シート設計部第13シート設計室 | D14: 16101121 | F14: 8766 | G14: 400BX | H14: 774000 | I14: 3月 | J14: 44994 | K14: 鈴木
A15: 完了 | B15: 12 | C15: 第1シート設計部第13シート設計室 | D15: 16101122 | F15: 8765 | G15: 400B VA | H15: 525000 | I15: 3月 | J15: 44994 | K15: 鈴木

Sheet A2
A1: 2023年 | C1: エンジニアリングサービス部 見積書・請求書発行管理台帳 | H1: 見積書(税抜金額)
A2: 企業名： | C2: トヨタ紡織(株)
A3: タスク | B3: No | C3: 部署名 | D3: 見積/請求番号 | E3: 発注番号 | F3: 業務計画書No | G3: 案件名 | H3: 見積金額 | I3: 見積月 | J3: 発行日 | K3: 発行者 | L3: 備考
C4: 第2シート設計部 | D4: 16106002

Sheet A3
A1: 2024年 | C1: エンジニアリングサービス部 見積書・請求書発行管理台帳 | H1: 見積書(税抜金額)
A2: 企業名： | C2: トヨタ紡織(株)
A3: タスク | B3: No | C3: 部署名 | D3: 見積/請求番号 | E3: 発注番号 | F3: 業務計画書No | G3: 案件名 | H3: 見積金額 | I3: 見積月 | J3: 発行日 | K3: 発行者 | L3: 備考
A4: 完了 | B4: 1 | C4: 第3シート設計部 | D4: 16107028 | E4: A31-R7454 | F4: - | G4: 無償修理低減解析 | I4: 1月 | J4: 44903 | K4: 鈴木
A5: 完了 | B5: 2 | C5: 第3シート設計部第32シート設計室 | D5: 16107033 | E5: 802-2212-0191-000 | F5: ITK08002 | G5: 277D | I5: 1月 | J5: 44923 | K5: 鈴木
A6: 完了 | B6: 3 | C6: 第3シート設計部第32シート設計室 | D6: 16107034 | E6: 802-2212-0190-000 | F6: ITK08004 | G6: 492D | I6: 1月 | J6: 44923 | K6: 鈴木
A7: 完了 | B7: 4 | C7: 第3シート設計部第32シート設計室 | D7: 16107035 | E7: 802-2212-0187-000 | F7: ITK08009 | G7: 493D | I7: 1月 | J7: 44923 | K7: 鈴木
A8: 完了 | B8: 5 | C8: 第3シート設計部第32シート設計室 | D8: 16107036 | E8: 802-2212-0192-000 | F8: ITK08001 | G8: 825B | I8: 1月 | J8: 44923 | K8: 鈴木
A9: 完了 | B9: 6 | C9: 第3シート設計部第32シート設計室 | D9: 16107037 | E9: 802-2212-0052-000 | F9: ITK08209 | G9: 018D | I9: 1月 | J9: 44923 | K9: 鈴木
A10: 完了 | B10: 7 | C10: 第3シート設計部 | D10: 16107038 | E10: A31-R7455 | F10: - | G10: 無償修理低減解析 | I10: 2月 | J10: 44937 | K10: 鈴木
A11: 完了 | B11: 8 | C11: 第3シート設計部第32シート設計室 | D11: 16107039 | E11: 802-2301-0139-000 | F11: 8295 | G11: 277D | I11: 2月 | J11: 44965 | K11: 鈴木
A12: 完了 | B12: 9 | C12: 第3シート設計部第32シート設計室 | D12: 16107040 | E12: 802-2301-0111-000 | F12: 8366 | G12: 492D | I12: 2月 | J12: 44965 | K12: 鈴木
A13: 完了 | B13: 10 | C13: 第3シート設計部第32シート設計室 | D13: 16107041 | E13: 802-2301-0107-000 | F13: 8370 | G13: 493D | I13: 2月 | J13: 44965 | K13: 鈴木
A14: 完了 | B14: 11 | C14: 第3シート設計部第32シート設計室 | D14: 16107042 | E14: 802-2301-0141-000 | F14: 8293 | G14: 825B | I14: 2月 | J14: 44965 | K14: 鈴木
A15: 完了 | B15: 12 | C15: 第3シート設計部第32シート設計室 | D15: 16107043 | E15: 802-2301-0140-000 | F15: 8294 | G15: 018D | I15: 2月 | J15: 44965 | K15: 鈴木
A16: 完了 | B16: 13 | C16: 第3シート設計部第32シート設計室 | D16: 16107044 | E16: 802-2302-0117-000 | F16: 8606 | G16: 277D | I16: 3月 | J16: 44984 | K16: 鈴木
A17: 完了 | B17: 14 | C17: 第3シート設計部第32シート設計室 | D17: 16107045 | F17: 8608 | G17: 492D | I17: 3月 | J17: 44986 | K17: 鈴木
A18: 完了 | B18: 15 | C18: 第3シート設計部第32シート設計室 | D18: 16107046 | F18: 8610 | G18: 493D | I18: 3月 | J18: 44986 | K18: 鈴木
A19: 完了 | B19: 16 | C19: 第3シート設計部第32シート設計室 | D19: 16107047 | E19: 802-2302-0119-000 | F19: 8604 | G19: 825B | I19: 3月 | J19: 44984 | K19: 鈴木
A20: 完了 | B20: 17 | C20: 第3シート設計部第32シート設計室 | D20: 16107048 | E20: 802-2302-0118-000 | F20: 8605 | G20: 018D | I20: 3月 | J20: 44984 | K20: 鈴木
A21: 完了 | B21: 18 | C21: 第3シート設計部 | D21: 16107049 | F21: - | G21: 無償修理低減解析 | I21: 3月 | J21: 44966 | K21: 鈴木
A22: 完了 | B22: 19 | C22: 第3シート設計部 | D22: 16107050 | F22: - | G22: 無償修理低減解析 | I22: 4月 | J22: 44999 | K22: 鈴木
A23: 完了 | B23: 20 | C23: 第3シート設計部 | D23: 16107051 | F23: - | G23: 無償修理低減解析 | I23: 5月 | J23: 45023 | K23: 鈴木
A24: 完了 | B24: 21 | C24: 第3シート設計部 | D24: 16107052 | F24: - | G24: 無償修理低減解析 | I24: 6月 | J24: 45063 | K24: 鈴木
A25: 完了 | B25: 22 | C25: 第3シート設計部 | D25: 16107053 | F25: - | G25: 無償修理低減解析 | I25: 7月 | J25: 45085 | K25: 鈴木
A26: 完了 | B26: 23 | C26: 第3シート設計部 | D26: 16107054 | F26: - | G26: 無償修理低減解析 | I26: 8月 | J26: 45112 | K26: 鈴木
A27: 完了 | B27: 24 | C27: 第3シート設計部 | D27: 16107055 | F27: - | G27: 無償修理低減解析 | I27: 9月 | J27: 45148 | K27: 鈴木
A28: 完了 | B28: 25 | C28: 第3シート設計部 | D28: 16107056 | F28: - | G28: 無償修理低減解析 | I28: 10月 | J28: 45183 | K28: 齊藤
A29: 完了 | B29: 26 | C29: 第3シート設計部 | D29: 16107057 | F29: - | G29: 無償修理低減解析 | I29: 11月 | J29: 45210 | K29: 齊藤
A30: 完了 | B30: 27 | C30: 第3シート設計部 | D30: 16107058 | F30: - | G30: 無償修理低減解析 | I30: 12月 | J30: 45243 | K30: 齊藤
B31: 28 | C31: 第3シート設計部 | D31: 16107059 | F31: - | G31: 無償修理低減解析 | I31: 1月 | J31: 45266 | K31: 齊藤
B32: 29 | C32: 第3シート設計部 | D32: 16107060 | F32: ITK11502 | G32: 650D | I32: 1月 | J32: 45275 | K32: 齊藤
B33: 30 | C33: 第3シート設計部 | D33: 16107061 | F33: - | G33: 無償修理低減解析 | I33: 2月 | J33: 45309 | K33: 齊藤
B34: 31 | C34: 第3シート設計部 | D34: 16107062 | F34: 11801 | G34: 650D | I34: 2月 | J34: 45309 | K34: 齊藤
B35: 32 | C35: 第3シート設計部 | D35: 16107063 | F35: - | G35: 無償修理低減解析 | I35: 3月 | J35: 45328 | K35: 齊藤
B36: 33 | C36: 第3シート設計部 | D36: 16107064 | F36: 12166 | G36: 650D | I36: 3月 | J36: 45341 | K36: 齊藤
B37: 34 | C37: 第3シート設計部 | D37: 16107065 | F37: - | G37: 無償修理低減解析 | I37: 4月 | J37: 45364 | K37: 齊藤
B38: 35 | C38: 第3シート設計部 | D38: 16107066 | F38: ITK12303 | G38: 650D | I38: 4月 | J38: 45377 | K38: 齊藤
B39: 36 | C39: 第3シート設計部 | D39: 16107067 | F39: ITK12409 | G39: 410D | I39: 4月 | J39: 45377 | K39: 齊藤
B40: 37 | C40: 第3シート設計部 | D40: 16107068 | F40: ITK12423 | G40: 450D | I40: 4月 | J40: 45377 | K40: 齊藤
B41: 38 | C41: 第3シート設計部 | D41: 16107069 | F41: ITK12424 | G41: 410D（H/R標準化） | I41: 4月 | J41: 45377 | K41: 齊藤
B42: 39 | C42: 第3シート設計部 | D42: 16107070 | F42: - | G42: 無償修理低減解析 | I42: 5月 | J42: 45390 | K42: 齊藤
B43: 40 | C43: 第3シート設計部 | D43: 16107071 | F43: ITK12701 | G43: 410D（H/R標準化） | I43: 5月 | J43: 45401 | K43: 齊藤
B44: 41 | C44: 第3シート設計部 | D44: 16107072 | F44: ITK12723 | G44: 650D | I44: 5月 | J44: 45401 | K44: 齊藤
B45: 42 | C45: 第3シート設計部 | D45: 16107073 | F45: - | G45: 無償修理低減解析 | I45: 6月 | J45: 45422 | K45: 齊藤
B46: 43 | C46: 第3シート設計部 | D46: 16107074 | F46: ITK12951 | G46: 410D（H/R標準化） | I46: 6月 | J46: 45433 | K46: 齊藤
B47: 44 | C47: 第3シート設計部 | D47: 16107075 | F47: ITK12977 | G47: 650D | I47: 6月 | J47: 45433 | K47: 齊藤
B48: 45 | C48: 第3シート設計部 | D48: 16107076 | F48: - | G48: 無償修理低減解析 | I48: 7月 | J48: 45453 | K48: 齊藤
B49: 46 | C49: 第3シート設計部 | D49: 16107077 | F49: 13158 | G49: 410D（H/R標準化） | I49: 7月 | J49: 45467 | K49: 齊藤
B50: 47 | C50: 第3シート設計部 | D50: 16107078 | F50: 13260 | G50: 650D | I50: 7月 | J50: 45467 | K50: 齊藤
B51: 48 | C51: 第3シート設計部 | D51: 16107079 | F51: - | G51: 無償修理低減解析 | I51: ８月 | J51: 45481 | K51: 齊藤
B52: 49 | C52: 第3シート設計部 | D52: 16107080 | F52: 13397 | G52: 410D（H/R標準化） | I52: 8月 | J52: '24/7/22 | K52: 齊藤
B53: 50 | C53: 第3シート設計部 | D53: 16107081 | F53: 13587 | G53: 650D | I53: 8月 | J53: '24/7/22 | K53: 齊藤
B54: 51 | C54: 第3シート設計部 | D54: 16107082 | F54: - | G54: 無償修理低減解析 | I54: 9月 | J54: 45510 | K54: 齊藤
B55: 52 | C55: 第3シート設計部 | D55: 16107083 | F55: 13688 | G55: 410D（H/R標準化） | I55: 9月 | J55: '24/8/21 | K55: 齊藤
B56: 53 | C56: 第3シート設計部 | D56: 16107084 | F56: 13788 | G56: 650D | I56: 9月 | J56: '24/9/2 | K56: 齊藤
B57: 54 | C57: 第3シート設計部 | D57: 16107085 | F57: - | G57: 無償修理低減解析 | I57: 10月 | J57: 45544 | K57: 齊藤
B58: 55 | C58: 第3シート設計部 | D58: 16107086 | F58: 14050 | G58: 650D | I58: 10月 | J58: '24/10/3 | K58: 久目形
B59: 56 | C59: 第3シート設計部 | D59: 16107087 | F59: 13964 | G59: 410D（H/R標準化） | I59: 10月 | J59: '24/10/3 | K59: 久目形
B60: 57 | C60: 第3シート設計部 | D60: 16107088 | F60: - | G60: 無償修理低減解析 | I60: 11月 | J60: 45583 | K60: 久目形
B61: 58 | C61: 第3シート設計部 | D61: 16107089 | F61: 14314 | G61: 410D（H/R標準化） | I61: 11月 | J61: '24/11/1 | K61: 久目形
B62: 59 | C62: 第3シート設計部 | D62: 16107090 | F62: 14331 | G62: 650D | I62: 11月 | J62: '24/11/1 | K62: 久目形
B63: 60 | C63: 第3シート設計部 | D63: 16107091 | F63: - | G63: 無償修理低減解析 | I63: 12月 | J63: 45604 | K63: 久目形
B64: 61 | C64: 第3シート設計部 | D64: 16107092 | F64: 14571 | G64: 650D | I64: 12月 | J64: '24/11/26 | K64: 久目形
B65: 62 | C65: 第3シート設計部 | D65: 16107093 | F65: 14548 | G65: 410D（H/R標準化） | I65: 12月 | J65: '24/11/27 | K65: 久目形
B66: 63 | C66: 第3シート設計部 | D66: 16107094 | F66: - | G66: 無償修理低減解析 | I66: 1月 | J66: 45632 | K66: 久目形
B67: 64 | C67: 第3シート設計部 | D67: 16107095 | F67: 14643 | G67: 650D | I67: 1月 | J67: 45645 | K67: 久目形
B68: 65 | C68: 第3シート設計部 | D68: 16107096 | F68: 14642 | G68: 410D（H/R標準化） | I68: 1月 | J68: 45645 | K68: 久目形
B69: 66 | C69: 第3シート設計部 | D69: 16107097 | F69: - | G69: 無償修理低減解析 | I69: 2月 | J69: 45672 | K69: 久目形
B70: 67 | C70: 第3シート設計部 | D70: 16107098 | F70: 15125 | G70: 650D | I70: 2月 | J70: 202/2/29 | K70: 久目形
B71: 68 | C71: 第3シート設計部 | D71: 16107099 | F71: 14937 | G71: 410D（H/R標準化） | I71: 2月 | J71: 202/2/29 | K71: 久目形
B72: 69 | C72: 第3シート設計部 | D72: 16107100 | F72: - | G72: 無償修理低減解析 | I72: 3月 | J72: 45699 | K72: 久目形
B73: 70 | C73: 第3シート設計部 | D73: 16107101 | F73: 15393 | G73: 650D | I73: 3月 | J73: 2025/2/26 | K73: 久目形
B74: 71 | C74: 第3シート設計部 | D74: 16107102 | F74: 15321 | G74: 410D（H/R標準化） | I74: 3月 | J74: 2025/2/26 | K74: 久目形
B75: 72 | C75: 第3シート設計部 | D75: 16107103 | F75: - | G75: 無償修理低減解析 | I75: 4月 | J75: 45735 | K75: 久目形
B76: 73 | C76: 第3シート設計部 | D76: 16107104 | F76: ITK15631 | G76: 410D（H/R標準化） | I76: 4月 | J76: 45744 | K76: 丸山
B77: 74 | C77: 第3シート設計部 | D77: 16107105 | F77: ITK15630 | G77: 650D | I77: 4月 | J77: 45744 | K77: 丸山
B78: 75 | C78: 第3シート設計部 | D78: 16107106 | F78: - | G78: 無償修理低減解析 | I78: 5月 | J78: 45761 | K78: 丸山
B79: 76 | C79: 第3シート設計部 | D79: 16107107 | F79: ITK15874 | G79: 410D（H/R標準化） | I79: 5月 | J79: 45784 | K79: 丸山
B80: 77 | C80: 第3シート設計部 | D80: 16107108 | F80: ITK15873 | G80: 650D | I80: 5月 | J80: 45784 | K80: 丸山
B81: 78 | C81: 第3シート設計部 | D81: 16107109 | F81: - | G81: 無償修理低減解析 | I81: 6月 | J81: 45790 | K81: 丸山
B82: 79 | C82: 第3シート設計部 | D82: 16107110 | F82: 16170 | G82: 410D（H/R標準化） | I82: 6月 | J82: 45805 | K82: 丸山
B83: 80 | C83: 第3シート設計部 | D83: 16107111 | F83: 16171 | G83: 650D | I83: 6月 | J83: 45805 | K83: 丸山
B84: 81 | C84: 第3シート設計部 | D84: 16107112 | F84: - | G84: 無償修理低減解析 | I84: 7月 | J84: 45817 | K84: 久目形
B85: 82 | C85: 第3シート設計部 | D85: 16107113 | F85: 16432 | G85: 410D（H/R標準化） | I85: 7月 | J85: 45835 | K85: 久目形
B86: 83 | C86: 第3シート設計部 | D86: 16107114 | F86: 16433 | G86: 650D | I86: 7月 | J86: 45835 | K86: 久目形
B87: 84 | C87: 第3シート設計部 | D87: 16107115 | F87: - | G87: 無償修理低減解析 | I87: 8月 | J87: ’25/7/4 | K87: 久目形
B88: 85 | C88: 第3シート設計部 | D88: 16107116 | F88: 16778 | G88: 650D | I88: 8月 | J88: ’25/7/21 | K88: 久目形
B89: 86 | C89: 第3シート設計部 | D89: 16107117 | F89: 16777 | G89: 410D（H/R標準化） | I89: 8月 | J89: ’25/7/21 | K89: 久目形
B90: 87 | C90: 第3シート設計部 | D90: 16107118 | F90: - | G90: 無償修理低減解析 | I90: 9月 | J90: 25/8/18 | K90: 久目形
B91: 88 | C91: 第3シート設計部 | D91: 16107119 | F91: 16950 | G91: 410D（H/R標準化） | I91: 9月 | J91: 45889 | K91: 久目形
B92: 89 | C92: 第3シート設計部 | D92: 16107120 | F92: 16949 | G92: 650D | I92: 9月 | J92: 45889 | K92: 久目形
B93: 90 | C93: 第3シート設計部 | D93: 16107121 | F93: - | G93: 無償修理低減解析 | I93: 10月 | J93: ’25/9/8 | K93: 久目形
B94: 91 | C94: 第3シート設計部 | D94: 16107122 | F94: 17143 | G94: 410D（H/R標準化） | I94: 10月 | J94: 45916 | K94: 久目形
B95: 92 | C95: 第3シート設計部 | D95: 16107123 | F95: 17285 | G95: 650D | I95: 10月 | J95: 45916 | K95: 久目形
B96: 93 | C96: 第3シート設計部 | D96: 16107124 | F96: - | G96: 無償修理低減解析 | I96: 11月 | J96: ’25/10/13 | K96: 久目形
B97: 94 | C97: 第3シート設計部 | D97: 16107125 | F97: 17522 | G97: 410D（H/R標準化） | I97: 11月 | J97: 45946 | K97: 久目形
B98: 95 | C98: 第3シート設計部 | D98: 16107126 | F98: 17526 | G98: 650D | I98: 11月 | J98: 45946 | K98: 久目形
B99: 96 | C99: 第3シート設計部 | D99: 16107127 | F99: - | G99: 無償修理低減解析 | I99: 12月 | J99: ’25/11/10 | K99: 久目形
B100: 97 | C100: 第3シート設計部 | D100: 16107128 | F100: 17889 | G100: 410D（H/R標準化） | I100: 12月 | J100: 45975 | K100: 久目形
...

Sheet A4
A1: 2024年 | C1: エンジニアリングサービス部 見積書・請求書発行管理台帳 | H1: 見積書(税抜金額)
A2: 企業名： | C2: トヨタ紡織(株)
A3: タスク | B3: No | C3: 部署名 | D3: 見積/請求番号 | E3: 発注番号 | F3: 業務計画書No | G3: 案件名 | H3: 見積金額 | I3: 見積月 | J3: 発行日 | K3: 発行者 | L3: 備考
B4: 1 | C4: 第4シート設計部 | D4: 16123001 | E4: A31-R7454 | F4: ITK12712 | G4: QA08 TB3 | I4: 5月 | J4: 45401 | K4: 齊藤
B5: 2 | C5: 第4シート設計部 | D5: 16123002 | E5: 802-2212-0191-000 | F5: ITK12730 | G5: 410D TB3 | I5: 5月 | J5: 45401 | K5: 齊藤
B6: 3 | C6: 第4シート設計部 | D6: 16123003 | E6: 802-2212-0190-000 | F6: ITK12731 | G6: 450D TB3 | I6: 5月 | J6: 45401 | K6: 齊藤
B7: 4 | C7: 第4シート設計部 | D7: 16123004 | E7: 802-2212-0187-000 | F7: ITK12887 | G7: 410D TB3 | I7: 6月 | J7: 45433 | K7: 齊藤
B8: 5 | C8: 第4シート設計部 | D8: 16123005 | E8: 802-2212-0192-000 | F8: ITK12889 | G8: 450D TB3 | I8: 6月 | J8: 45433 | K8: 齊藤
B9: 6 | C9: 第4シート設計部 | D9: 16123006 | E9: 802-2212-0052-000 | F9: ITK12807 | G9: QA08 TB3 | I9: 6月 | J9: 45435 | K9: 齊藤
B10: 7 | C10: 第4シート設計部 | D10: 16123007 | E10: A31-R7455 | F10: 13144 | G10: 410D TB3 | I10: 7月 | J10: 45467 | K10: 齊藤
B11: 8 | C11: 第4シート設計部 | D11: 16123008 | E11: 802-2301-0139-000 | F11: 13146 | G11: QA08 TB3 | I11: 7月 | J11: 45467 | K11: 齊藤
B12: 9 | C12: 第4シート設計部 | D12: 16123009 | E12: 802-2301-0111-000 | F12: 13145 | G12: 450D TB3 | I12: 7月 | J12: 45467 | K12: 齊藤
B13: 10 | C13: 第4シート設計部 | D13: 16123010 | E13: 802-2301-0107-000 | F13: 13496 | G13: 450D TB3 | I13: 8月 | J13: '24/7/16 | K13: 齊藤
B14: 11 | C14: 第4シート設計部 | D14: 16123011 | E14: 802-2301-0141-000 | F14: 13495 | G14: 410D TB3 | I14: 8月 | J14: '24/7/18 | K14: 齊藤
B15: 12 | C15: 第4シート設計部 | D15: 16123012 | E15: 802-2301-0140-000 | F15: 13384 | G15: QA08 TB3 | I15: 8月 | J15: '24/7/22 | K15: 齊藤
B16: 13 | C16: 第4シート設計部 | D16: 16123013 | E16: 802-2302-0117-000 | F16: 13603 | G16: QA08 TB3 | I16: 9月 | J16: '24/8/21 | K16: 齊藤
B17: 14 | C17: 第4シート設計部 | D17: 16123014 | F17: 13763 | G17: 450D TB3 | I17: 9月 | J17: '24/8/21 | K17: 齊藤
B18: 15 | C18: 第4シート設計部 | D18: 16123015 | F18: 13762 | G18: 410D TB3 | I18: 9月 | J18: '24/8/21 | K18: 齊藤
B19: 16 | C19: 第4シート設計部 | D19: 16123016 | E19: 802-2302-0119-000 | F19: 13934 | G19: 450D TB3 | I19: 10月 | J19: '24/10/3 | K19: 久目形
B20: 17 | C20: 第4シート設計部 | D20: 16123017 | E20: 802-2302-0118-000 | F20: 13933 | G20: 410D TB3 | I20: 10月 | J20: '24/10/3 | K20: 久目形
B21: 18 | C21: 第4シート設計部 | D21: 16123018 | F21: 13890 | G21: QA08 TB3 | I21: 10月 | J21: '24/10/3 | K21: 久目形
B22: 19 | C22: 第4シート設計部 | D22: 16123019 | F22: 14245 | G22: 410D TB3 | I22: 11月 | J22: '24/11/1 | K22: 久目形
B23: 20 | C23: 第4シート設計部 | D23: 16123020 | F23: 14244 | G23: 450D TB3 | I23: 11月 | J23: '24/11/1 | K23: 久目形
B24: 21 | C24: 第4シート設計部 | D24: 16123021 | F24: 14196 | G24: QA08 TB3 | I24: 11月 | J24: '24/11/1 | K24: 久目形
B25: 22 | C25: 第4シート設計部 | D25: 16123022 | F25: 14421 | G25: QA08 TB3 | I25: 12月 | J25: '24/11/29 | K25: 久目形
B26: 23 | C26: 第4シート設計部 | D26: 16123023 | F26: 14432 | G26: 410D TB3 | I26: 12月 | J26: '24/11/29 | K26: 久目形
B27: 24 | C27: 第4シート設計部 | D27: 16123024 | F27: 14433 | G27: 450D TB3 | I27: 12月 | J27: '24/11/29 | K27: 久目形
B28: 25 | C28: 第4シート設計部 | D28: 16123025 | F28: 14681 | G28: QA08 TB3 | I28: 1月 | J28: 45645 | K28: 久目形
B29: 26 | C29: 第4シート設計部 | D29: 16123026 | F29: 14695 | G29: 410D TB3 | I29: 1月 | J29: 45645 | K29: 久目形
B30: 27 | C30: 第4シート設計部 | D30: 16123027 | F30: 14696 | G30: 450D TB3 | I30: 1月 | J30: 45645 | K30: 久目形
B31: 28 | C31: 第4シート設計部 | D31: 16123028 | F31: 14936 | G31: QA08 TB3 | I31: 2月 | J31: 202/2/29 | K31: 久目形
B32: 29 | C32: 第4シート設計部 | D32: 16123029 | F32: 14973 | G32: 410D TB3 | I32: 2月 | J32: 202/2/29 | K32: 久目形
B33: 30 | C33: 第4シート設計部 | D33: 16123030 | F33: 14974 | G33: 450D TB3 | I33: 2月 | J33: 202/2/29 | K33: 久目形
B34: 31 | C34: 第4シート設計部 | D34: 16123031 | F34: 15214 | G34: QA08 TB3 | I34: 3月 | J34: 2025/2/26 | K34: 久目形
B35: 32 | C35: 第4シート設計部 | D35: 16123032 | F35: 15254 | G35: 410D TB3 | I35: 3月 | J35: 2025/2/26 | K35: 久目形
B36: 33 | C36: 第4シート設計部 | D36: 16123033 | F36: 15255 | G36: 450D TB3 | I36: 3月 | J36: 2025/2/26 | K36: 久目形
B37: 34 | C37: 第4シート設計部 | D37: 16123034 | F37: ITK15483 | G37: 32AT TB3 | I37: 4月 | J37: 45744 | K37: 丸山
B38: 35 | C38: 第4シート設計部 | D38: 16123035 | F38: ITK15846 | G38: 32AT TB3 | I38: 5月 | J38: 45784 | K38: 丸山
B39: 36 | C39: 第4シート設計部 | D39: 16123036 | F39: 16076 | G39: 32AT TB3 | I39: 6月 | J39: 45805 | K39: 丸山
B40: 37 | C40: 第4シート設計部 | D40: 16123037 | F40: 16329 | G40: 32AT TB3 | I40: 7月 | J40: 45835 | K40: 久目形
B41: 38 | C41: 第4シート設計部 | D41: 16123038 | F41: 16782 | G41: 32AT TB3 | I41: 8月 | J41: 45863 | K41: 久目形
B42: 39 | C42: 第4シート設計部 | D42: 16123039 | F42: 16782 | G42: 32AT TB3 | I42: 8月 | J42: 45863 | K42: 久目形
B43: 40 | C43: 第4シート設計部 | D43: 16123040 | F43: 17024 | G43: TB3 | I43: 9月 | J43: 45889 | K43: 久目形
B44: 41 | C44: 第4シート設計部 | D44: 16123041 | F44: 17245 | G44: TB3 | I44: 10月 | J44: 45916 | K44: 久目形
B45: 42 | C45: 第4シート設計部 | D45: 16123042 | F45: 17245 | G45: TB3 | I45: 11月 | J45: 45946 | K45: 久目形
B46: 43 | C46: 第4シート設計部 | D46: 16123043 | F46: 17858 | G46: TB3 | I46: 12月 | J46: 45975 | K46: 久目形
B47: 44 | C47: 第4シート設計部 | D47: 16123044 | F47: 18127 | G47: TB3 | I47: １月 | J47: 46008 | K47: 久目形
B48: 45 | D48: 16123045
B49: 46 | D49: 16123046
B50: 47 | D50: 16123047
B51: 48 | D51: 16123048
B52: 49 | D52: 16123049
B53: 50 | D53: 16123050
B54: 51
B55: 52
B56: 53
B57: 54
B58: 55
B59: 56
B60: 57
B61: 58
B62: 59
B63: 60
B64: 61
B65: 62
... B87: 84

Sheet Fr骨格
A1: 2024年 | C1: エンジニアリングサービス部 見積書・請求書発行管理台帳 | H1: 見積書(税抜金額)
A2: 企業名： | C2: トヨタ紡織(株)
A3: タスク | B3: No | C3: 部署名 | D3: 見積/請求番号 | E3: 発注番号 | F3: 業務計画書No | G3: 案件名 | H3: 見積金額 | I3: 見積月 | J3: 発行日 | K3: 発行者 | L3: 備考
A4: 完了 | B4: 1 | C4: Frシート骨格設計部第2設計室 | D4: 16102047 | E4: 802-2212-0086-000 | F4: ITk08154 | G4: TNGA/SK7 FRシート骨格 | I4: 1月 | J4: 44923 | K4: 鈴木
A5: 完了 | B5: 2 | C5: Frシート骨格設計部第2設計室 | D5: 16102048 | E5: 802-2212-0085-000 | F5: ITK08160 | G5: SK7 FRシート骨格 | I5: 1月 | J5: 44923 | K5: 鈴木
A6: 完了 | B6: 3 | C6: Frシート骨格設計部第2設計室 | D6: 16102049 | E6: 802-2301-0002-000 | F6: 8443 | G6: 410D | I6: 1月 | J6: 44937 | K6: 鈴木
A7: 完了 | B7: 4 | C7: Frシート骨格設計部第2設計室 | D7: 16102050 | E7: 802-2301-0055-000 | F7: 8459 | G7: TNGA/SK7 FRシート骨格 | I7: 2月 | J7: 44960 | K7: 鈴木
A8: 完了 | B8: 5 | C8: Frシート骨格設計部第2設計室 | D8: 16102051 | E8: 802-2301-0044-000 | F8: 8476 | G8: SK7 FRシート骨格 | I8: 2月 | J8: 44960 | K8: 鈴木
A9: 完了 | B9: 6 | C9: Frシート骨格設計部第2設計室 | D9: 16102052 | E9: 802-2301-0041-000 | F9: 8479 | G9: 410D | I9: 2月 | J9: 44960 | K9: 鈴木
A10: 完了 | B10: 7 | C10: Frシート骨格設計部第2設計室 | D10: 16102053 | F10: 8655 | G10: TNGA/SK7 FRシート骨格 | I10: 3月 | J10: 44994 | K10: 鈴木
A11: 完了 | B11: 8 | C11: Frシート骨格設計部第2設計室 | D11: 16102054 | F11: 8690 | G11: SK7 FRシート骨格 | I11: 3月 | J11: 44994 | K11: 鈴木
A12: 完了 | B12: 9 | C12: Frシート骨格設計部第2設計室 | D12: 16102055 | F12: 8693 | G12: 502D | I12: 2月 | J12: 44994 | K12: 鈴木
A13: 完了 | B13: 10 | C13: Frシート骨格設計部第2設計室 | D13: 16102056 | F13: 8749 | G13: 502D | I13: 3月 | J13: 44994 | K13: 鈴木
A14: 完了 | B14: 11 | C14: Frシート骨格設計部第2設計室 | D14: 16102057 | F14: 8945 | G14: TNGA/SK7 FRシート骨格 | I14: 4月 | J14: 45023 | K14: 鈴木
A15: 完了 | B15: 12 | C15: Frシート骨格設計部第2設計室 | D15: 16102058 | F15: 9337 | G15: TNGA/SK7 FRシート骨格 | I15: 5月 | J15: 45044 | K15: 鈴木
A16: 完了 | B16: 13 | C16: Frシート骨格設計部第2設計室 | D16: 16102059 | F16: 9549 | G16: TNGA/SK7 FRシート骨格 | I16: 6月 | J16: 45078 | K16: 鈴木
A17: 完了 | B17: 14 | C17: Frシート骨格設計部第2設計室 | D17: 16102060 | F17: 9704 | G17: X1T5 次世代バックフレーム | I17: 6月 | J17: 45090 | K17: 鈴木
A18: 完了 | B18: 15 | C18: Frシート骨格設計部第2設計室 | D18: 16102061 | F18: 9792 | G18: TNGA/SK7 FRシート骨格 | I18: 7月 | J18: 45103 | K18: 鈴木
A19: 完了 | B19: 16 | C19: Frシート骨格設計部第2設計室 | D19: 16102062 | F19: 9732 | G19: X1T5 次世代バックフレーム | I19: 7月 | J19: 45103 | K19: 鈴木
A20: 完了 | B20: 17 | C20: Frシート骨格設計部第2設計室 | D20: 16102063 | F20: 10141 | G20: X1T5 次世代バックフレーム | I20: 8月 | J20: 45128 | K20: 鈴木
A21: 完了 | B21: 18 | C21: Frシート骨格設計部第2設計室 | D21: 16102064 | F21: 10150 | G21: TNGA/SK7 FRシート骨格 | I21: 8月 | J21: 45128 | K21: 鈴木
... A35: 完了 | B35: 32 | C35: Frシート骨格設計部第2設計室 | D35: 16102078 | F35: 11356 | G35: SUBARU 28BEV RFQ対応 | I35: 12月 | J35: 45257 | K35: 齊藤
A36: 完了 | B36: 33 | C36: Frシート骨格設計部第2設計室 | D36: 16102079 | F36: ITK11355 | G36: 581D Frシート骨格開発 | I36: 12月 | J36: 45264 | K36: 齊藤
B37: 34 | C37: Frシート骨格設計部第2設計室 | D37: 16102080 | F37: 11615 | G37: TNGA/SK7 FRシート骨格 | I37: １月 | J37: 45279 | K37: 齊藤
B38: 35 | C38: Frシート骨格設計部第2設計室 | D38: 16102081 | F38: ITK11614 | G38: 581D Frシート骨格開発 | I38: １月 | J38: 45279 | K38: 齊藤
B39: 36 | C39: Frシート骨格設計部第2設計室 | D39: 16102082 | F39: 11759 | G39: TNGA/SK7 FRシート骨格 | I39: 2月 | J39: 45310 | K39: 齊藤
B40: 37 | C40: Frシート骨格設計部第2設計室 | D40: 16102083 | F40: 11764 | G40: X1T8 他社販骨格開 | I40: 2月 | J40: 45310 | K40: 齊藤
B41: 38 | C41: Frシート骨格設計部第2設計室 | D41: 16102084 | F41: 11794 | G41: 581D Frシート骨格開発 | I41: 2月 | J41: 45310 | K41: 齊藤
B42: 39 | C42: Frシート骨格設計部第2設計室 | D42: 16102085 | F42: 11866 | G42: 500DFrシート骨格開発 | I42: 2月 | J42: 45310 | K42: 齊藤
B43: 40 | C43: Frシート骨格設計部第2設計室 | D43: 16102086 | F43: 11880 | G43: X1T5 次世代バックフレーム | I43: 2月 | J43: 45310 | K43: 齊藤
B44: 41 | C44: Frシート骨格設計部第2設計室 | D44: 16102087 | F44: 12052 | G44: TNGA/SK7 FRシート骨格 | I44: 3月 | J44: 45337 | K44: 齊藤
B45: 42 | C45: Frシート骨格設計部第2設計室 | D45: 16102088 | F45: 12090 | G45: 581D Frシート骨格開発 | I45: 3月 | J45: 45337 | K45: 齊藤
B46: 43 | C46: Frシート骨格設計部第2設計室 | D46: 16102089 | F46: 12061 | G46: X1T5 次世代バックフレーム | I46: 3月 | J46: 45337 | K46: 齊藤
B47: 44 | C47: Frシート骨格設計部第2設計室 | D47: 16102090 | F47: 12130 | G47: 500DFrシート骨格開発 | I47: 3月 | J47: 45337 | K47: 齊藤
B48: 45 | C48: Frシート骨格設計部第2設計室 | D48: 16102091 | F48: 12046 | G48: X1T8 他社販骨格開 | I48: 3月 | J48: 45345 | K48: 齊藤
B49: 46 | C49: Frシート骨格設計部骨格開発室 | D49: 16102092 | F49: ITK12318 | G49: STEP3薄型PWRクッションフレーム | I49: 4月 | J49: 45377 | K49: 齊藤
B50: 47 | C50: Frシート骨格設計部第2設計室 | D50: 16102093 | F50: ITK12443 | G50: TNGA/SK7 FRシート骨格 | I50: 4月 | J50: 45377 | K50: 齊藤
B51: 48 | C51: Frシート骨格設計部第1設計室 | D51: 16102094 | F51: ITK12468 | G51: 2.5巡目車種展 | I51: 4月 | J51: 45377 | K51: 齊藤
B52: 49 | C52: Frシート骨格設計部第2設計室 | D52: 16102095 | F52: ITK12689 | G52: TNGA/SK7 FRシート骨格 | I52: 5月 | J52: 45401 | K52: 齊藤
B53: 50 | C53: Frシート骨格設計部骨格開発室 | D53: 16102096 | F53: ITK12696 | G53: STEP3薄型PWRクッションフレーム | I53: 5月 | J53: 45401 | K53: 齊藤
B54: 51 | C54: Frシート骨格設計部第1設計室 | D54: 16102097 | F54: ITK12967 | G54: 2.5巡目車種展 | I54: 6月 | J54: 45433 | K54: 齊藤
B55: 52 | C55: Frシート骨格設計部第2設計室 | D55: 16102098 | F55: ITK12961 | G55: TNGA/SK7 FRシート骨格 | I55: 6月 | J55: 45433 | K55: 齊藤
B56: 53 | C56: Frシート骨格設計部骨格開発室 | D56: 16102099 | F56: ITK12956 | G56: STEP3薄型PWRクッションフレーム | I56: 6月 | J56: 45433 | K56: 齊藤
B57: 54 | C57: Frシート骨格設計部第2設計室 | D57: 16102100 | F57: 13176 | G57: TNGA/SK7 FRシート骨格 | I57: 7月 | J57: 45467 | K57: 齊藤
B58: 55 | C58: Frシート骨格設計部第1設計室 | D58: 16102101 | F58: 13200 | G58: 2.5巡目車種展 | I58: 7月 | J58: 45467 | K58: 齊藤
B59: 56 | C59: Frシート骨格設計部骨格開発室 | D59: 16102102 | F59: 13172 | G59: STEP3薄型PWRクッションフレーム | I59: 7月 | J59: 45467 | K59: 齊藤
B60: 57 | C60: Frシート骨格設計部第2設計室 | D60: 16102103 | F60: 13503 | G60: TNGA/SK7 FRシート骨格 | I60: 8月 | J60: '24/7/16 | K60: 齊藤
B61: 58 | C61: Frシート骨格設計部骨格開発室 | D61: 16102104 | F61: 133515 | G61: STEP3薄型PWRクッションフレーム | I61: 8月 | J61: '24/7/16 | K61: 齊藤
B62: 59 | C62: Frシート骨格設計部第1設計室 | D62: 16102105 | F62: 13469 | G62: 2.5巡目車種展 | I62: 8月 | J62: '24/7/18 | K62: 齊藤
B63: 60 | C63: Frシート骨格設計部骨格開発室 | D63: 16102106 | F63: 13735 | G63: STEP3薄型PWRクッションフレーム | I63: 9月 | J63: '24/8/21 | K63: 齊藤
B64: 61 | C64: Frシート骨格設計部第2設計室 | D64: 16102107 | F64: 13737 | G64: TNGA/SK7 FRシート骨格 | I64: 9月 | J64: '24/8/21 | K64: 齊藤
B65: 62 | C65: Frシート骨格設計部第1設計室 | D65: 16102108 | F65: 13734 | G65: 2.5巡目車種展 | I65: 9月 | J65: '24/8/21 | K65: 齊藤
B66: 63 | C66: Frシート骨格設計部第2設計室 | D66: 16102109 | F66: 13838 | G66: SUBARU後席エアバッグ対応 | I66: 9月 | J66: 24/9/11 | K66: 久目形
B67: 64 | C67: Frシート骨格設計部第2設計室 | D67: 16102110 | F67: 14018 | G67: TNGA/SK7 FRシート骨格 | I67: 10月 | J67: '24/10/3 | K67: 久目形
B68: 65 | C68: Frシート骨格設計部第2設計室 | D68: 16102111 | F68: 14016 | G68: 2.5巡目車種展 | I68: 10月 | J68: '24/10/3 | K68: 久目形
B69: 66 | C69: Frシート骨格設計部骨格開発室 | D69: 16102112 | F69: 14015 | G69: STEP3薄型PWRクッションフレーム | I69: 10月 | J69: '24/10/3 | K69: 久目形
B70: 67 | C70: Frシート骨格設計部第2設計室 | D70: 16102113 | F70: 13910 | G70: SUBARU後席エアバッグ対応 | I70: 10月 | J70: '24/10/3 | K70: 久目形
B71: 68 | C71: Frシート骨格設計部骨格開発室 | D71: 16102114 | F71: 14294 | G71: STEP3薄型PWRクッションフレーム | I71: 11月 | J71: '24/11/1 | K71: 久目形
... B78: 75 | C78: Frシート骨格設計部第2設計室 | D78: 16102121 | F78: 14518 | G78: SUBARU後席エアバッグ対応 | I78: 12月 | J78: '24/11/27 | K78: 久目形
B79: 76 | C79: Frシート骨格設計部第2設計室 | D79: 16102122 | F79: 14794 | G79: 2.5巡目車種展 | I79: 1月 | J79: 45645 | K79: 久目形
B80: 77 | C80: Frシート骨格設計部第2設計室 | D80: 16102123 | F80: 14739 | G80: STEP3薄型PWRクッションフレーム | I80: 1月 | J80: 45645 | K80: 久目形
B81: 78 | C81: Frシート骨格設計部第2設計室 | D81: 16102124 | F81: 14792 | G81: SUBARU後席エアバッグ対応 | I81: 1月 | J81: 45645 | K81: 久目形
B82: 79 | C82: Frシート骨格設計部第2設計室 | D82: 16102125 | F82: 14821 | G82: TNGA/SK7 FRシート骨格 | I82: 1月 | J82: 45645 | K82: 久目形
B83: 80 | C83: Frシート骨格設計部第2設計室 | D83: 16102126 | F83: 15111 | G83: TNGA/SK7 FRシート骨格 | I83: 2月 | J83: 202/2/29 | K83: 久目形
B84: 81 | C84: Frシート骨格設計部第2設計室 | D84: 16102127 | F84: 15088 | G84: STEP3薄型PWRクッションフレーム | I84: 2月 | J84: 202/2/29 | K84: 久目形
B85: 82 | C85: Frシート骨格設計部第2設計室 | D85: 16102128 | F85: 15087 | G85: 2.5巡目車種展 | I85: 2月 | J85: 202/2/29 | K85: 久目形
B86: 83 | C86: Frシート骨格設計部第2設計室 | D86: 16102129 | F86: 15335 | G86: TNGA/SK7 FRシート骨格 | I86: 3月 | J86: 2025/2/26 | K86: 久目形
B87: 84 | C87: Frシート骨格設計部第2設計室 | D87: 16102130 | F87: 15239 | G87: STEP3薄型PWRクッションフレーム | I87: 3月 | J87: 2025/2/26 | K87: 久目形
B88: 85 | C88: Frシート骨格設計部第2設計室 | D88: 16102131 | F88: 15315 | G88: 2.5巡目車種展 | I88: 3月 | J88: 2025/2/26 | K88: 久目形
B89: 86 | C89: Frシート骨格設計部第2設計室 | D89: 16102132 | F89: ITK15563 | G89: B780新プレステージ開発 | I89: 4月 | J89: 45744 | K89: 丸山
B90: 87 | C90: Frシート骨格設計部第2設計室 | D90: 16102133 | F90: ITK15562 | G90: X1TE新プレステージ開発 | I90: 4月 | J90: 45744 | K90: 丸山
B91: 88 | C91: Frシート骨格設計部第2設計室 | D91: 16102134 | F91: ITK15560 | G91: 900D受注活動 | I91: 4月 | J91: 45744 | K91: 丸山
B92: 89 | C92: Frシート骨格設計部第2設計室 | D92: 16102135 | F92: ITK15441 | G92: TNGA/SK7 FRシート骨格 | I92: 4月 | J92: 45744 | K92: 丸山
B93: 90 | C93: Frシート骨格設計部骨格開発室 | D93: 16102136 | F93: ITK15426 | G93: 低ハイト薄型クッションフレーム | I93: 4月 | J93: 45744 | K93: 丸山
B94: 91 | C94: Frシート骨格設計部第2設計室 | D94: 16102137 | F94: ITK15563 | G94: B780新プレステージ開発 | I94: 4月 | J94: 45762 | K94: 丸山 | L94: 金額変更にて再発行
B95: 92 | C95: Frシート骨格設計部第2設計室 | D95: 16102138 | F95: ITK15562 | G95: X1TE新プレステージ開発 | I95: 4月 | J95: 45762 | K95: 丸山 | L95: 金額変更にて再発行
B96: 93 | C96: Frシート骨格設計部第2設計室 | D96: 16102139 | F96: ITK15560 | G96: 900D受注活動 | I96: 4月 | J96: 45762 | K96: 丸山 | L96: 金額変更にて再発行
B97: 94 | C97: Frシート骨格設計部第2設計室 | D97: 16102140 | F97: ITK15441 | G97: TNGA/SK7 FRシート骨格 | I97: 4月 | J97: 45762 | K97: 丸山 | L97: 金額変更にて再発行
B98: 95 | C98: Frシート骨格設計部骨格開発室 | D98: 16102141 | F98: ITK15426 | G98: 低ハイト薄型クッションフレーム | I98: 4月 | J98: 45762 | K98: 丸山 | L98: 金額変更にて再発行
B99: 96 | C99: Frシート骨格設計部第2設計室 | D99: 16102142 | F99: ITK15798 | G99: TNGA/SK7 FRシート骨格 | I99: 5月 | J99: 45784 | K99: 丸山
B100: 97 | C100: Frシート骨格設計部第2設計室 | D100: 16102143 | F100: ITK15790 | G100: 900D受注活動 | I100: 5月 | J100: 45784 | K100: 丸山
B101: 98 | C101: Frシート骨格設計部骨格開発室 | D101: 16102144 | F101: ITK15732 | G101: 低ハイト薄型クッションフレーム | I101: 5月 | J101: 45784 | K101: 丸山
B102: 99 | C102: Frシート骨格設計部骨格開発室 | D102: 16102145 | F102: 16134 | G102: 低ハイト薄型クッションフレーム | I102: 6月 | J102: 45805 | K102: 丸山
B103: 100 | C103: Frシート骨格設計部第2設計室 | D103: 16102146 | F103: 16135 | G103: 900D受注活動 | I103: 6月 | J103: 45805 | K103: 丸山
B104: 101 | C104: Frシート骨格設計部第2設計室 | D104: 16102147 | F104: 16139 | G104: TNGA/SK7 FRシート骨格 | I104: 6月 | J104: 45805 | K104: 丸山
B105: 102 | C105: Frシート骨格設計部骨格開発室 | D105: 16102148 | F105: 16474 | G105: 低ハイト薄型クッションフレーム | I105: 7月 | J105: 45835 | K105: 久目形
B106: 103 | C106: Frシート骨格設計部第2設計室 | D106: 16102149 | F106: 16430 | G106: TNGA/SK7 FRシート骨格 | I106: 7月 | J106: 45835 | K106: 久目形
B107: 104 | C107: Frシート骨格設計部第2設計室 | D107: 16102150 | F107: 16501 | G107: 900D受注活動 | I107: 7月 | J107: 45835 | K107: 久目形
B108: 105 | C108: Frシート骨格設計部第2設計室 | D108: 16102151 | F108: 16633 | G108: 630D Fr骨格開発 | I108: 7月 | J108: 45847 | K108: 久目形
B109: 106 | C109: Frシート骨格設計部骨格開発室 | D109: 16102152 | F109: 16665 | G109: 低ハイト薄型クッションフレーム | I109: 8月 | J109: 45855 | K109: 久目形
B110: 107 | C110: Frシート骨格設計部第2設計室 | D110: 16102153 | F110: 16712 | G110: TNGA/SK7 FRシート骨格 | I110: 8月 | J110: 45855 | K110: 久目形
B111: 108 | C111: Frシート骨格設計部第2設計室 | D111: 16102154 | F111: 16720 | G111: 900D受注活動 | I111: 8月 | J111: 45855 | K111: 久目形
B112: 109 | C112: Frシート骨格設計部第2設計室 | D112: 16102155 | F112: 16716 | G112: 630D Fr骨格開発 | I112: 8月 | J112: 45855 | K112: 久目形
B113: 110 | C113: Frシート骨格設計部骨格開発室 | D113: 16102156 | F113: 16960 | G113: 低ハイト薄型クッションフレーム | I113: 9月 | J113: 45889 | K113: 久目形
... B120: 117 | C120: Frシート骨格設計部第2設計室 | D120: 16102163 | F120: 17328 | G120: 900D受注活動 | I120: 10月 | J120: 45916 | K120: 久目形
B121: 118 | C121: Frシート骨格設計部第2設計室 | D121: 16102164 | F121: 17328 | G121: 900D受注活動 | I121: 10月 | J121: 45951 | K121: 久目形 | L121: ※成果物増加により委託金額修正
B122: 119 | C122: Frシート骨格設計部骨格開発室 | D122: 16102165 | F122: 17634 | G122: 低ハイト薄型クッションフレーム | I122: 11月 | J122: 45952 | K122: 久目形
B123: 120 | C123: Frシート骨格設計部第2設計室 | D123: 16102166 | F123: 17643 | G123: 630D Fr骨格開発 | I123: 11月 | J123: 45952 | K123: 久目形
B124: 121 | C124: Frシート骨格設計部第2設計室 | D124: 16102167 | F124: 17637 | G124: TNGA/SK7 FRシート骨格 | I124: 11月 | J124: 45952 | K124: 久目形
B125: 122 | C125: Frシート骨格設計部第2設計室 | D125: 16102168 | F125: 17644 | G125: 900D受注活動 | I125: 11月 | J125: 45952 | K125: 久目形
...

Sheet Rr骨格
A1: 2024年 | C1: エンジニアリングサービス部 見積書・請求書発行管理台帳 | H1: 見積書(税抜金額)
A2: 企業名： | C2: トヨタ紡織(株)
A3: タスク | B3: No | C3: 部署名 | D3: 見積/請求番号 | E3: 発注番号 | F3: 業務計画書No | G3: 案件名 | H3: 見積金額 | I3: 見積月 | J3: 発行日 | K3: 発行者 | L3: 備考
A4: 完了 | B4: 1 | C4: Rrシート骨格設計部第1設計室 | D4: 16104060 | E4: 802-2212-0147-000 | F4: ITK08061 | G4: ミニバン統合骨格 | I4: 1月 | J4: 44923 | K4: 鈴木
A5: 完了 | B5: 2 | C5: Rrシート骨格設計部第2設計室 | D5: 16104061 | E5: 802-2212-0079-000 | F5: ITK08166 | G5: 440D | I5: 1月 | J5: 44923 | K5: 鈴木
A6: 完了 | B6: 3 | C6: Rrシート骨格設計部第1設計室 | D6: 16104062 | E6: 802-2301-0070-000 | F6: 8431 | G6: ミニバン統合骨格 | I6: 2月 | J6: 44965 | K6: 鈴木
A7: 完了 | B7: 4 | C7: Rrシート骨格設計部第2設計室 | D7: 16104063 | E7: 802-2301-0071-000 | F7: 8430 | G7: 440D | I7: 2月 | J7: 44965 | K7: 鈴木
A8: 完了 | B8: 5 | C8: Rrシート骨格設計部第2設計室 | D8: 16104064 | E8: 802-2302-0082-000 | F8: 8662 | G8: 440D | I8: 3月 | J8: 44986 | K8: 鈴木
A9: 完了 | B9: 6 | C9: Rrシート骨格設計部第1設計室 | D9: 16104065 | E9: 802-2302-0058-000 | F9: 8707 | G9: ミニバン統合骨格 | I9: 3月 | J9: 44986 | K9: 鈴木
A10: 完了 | B10: 7 | C10: Rrシート骨格設計部第2設計室 | D10: 16104066 | F10: 8851 | G10: SUBARU | I10: 3月 | J10: 44994 | K10: 鈴木
A11: 完了 | B11: 8 | C11: Rrシート骨格設計部第1設計室 | D11: 16104067 | F11: 8858 | G11: ミニバン統合骨格 | I11: 4月 | J11: 45016 | K11: 鈴木
A12: 完了 | B12: 9 | C12: Rrシート骨格設計部第1設計室 | D12: 16104068 | F12: 9173 | G12: ミニバン統合骨格 | I12: 5月 | J12: 45044 | K12: 鈴木
A13: 完了 | B13: 10 | C13: Rrシート骨格設計部第1設計室 | D13: 16104069 | F13: 9442 | G13: ミニバン統合骨格 | I13: 6月 | J13: 45078 | K13: 鈴木
A14: 完了 | B14: 11 | C14: Rrシート骨格設計部第1設計室 | D14: 16104070 | F14: 9732 | G14: ミニバン統合骨格 | I14: 7月 | J14: 45105 | K14: 鈴木
A15: 完了 | B15: 12 | C15: Rrシート骨格設計部第1設計室 | D15: 16104071 | F15: 10100 | G15: ミニバン統合骨格 | I15: 8月 | J15: 45128 | K15: 鈴木
A16: 完了 | B16: 13 | C16: Rrシート骨格設計部第2設計室 | D16: 16104072 | F16: 10243 | G16: QE36 SUBARU | I16: 8月 | J16: 45141 | K16: 鈴木
A17: 完了 | B17: 14 | C17: Rrシート骨格設計部第2設計室 | D17: 16104073 | F17: 10325 | G17: B658 SUBARU | I17: 8月 | J17: 45141 | K17: 鈴木
A18: 完了 | B18: 15 | C18: Rrシート骨格設計部第1設計室 | D18: 16104074 | F18: 10410 | G18: ミニバン統合骨格 | I18: 9月 | J18: 45148 | K18: 鈴木
A19: 完了 | B19: 16 | C19: Rrシート骨格設計部第2設計室 | D19: 16104075 | F19: 10404 | G19: QE36 SUBARU | I19: 9月 | J19: 45148 | K19: 鈴木
A20: 完了 | B20: 17 | C20: Rrシート骨格設計部第2設計室 | D20: 16104076 | F20: 10405 | G20: B658 SUBARU | I20: 9月 | J20: 45148 | K20: 鈴木
A21: 完了 | B21: 18 | C21: Rrシート骨格設計部第2設計室 | D21: 16104077 | F21: 10449 | G21: 410D | I21: 8月 | J21: 45160 | K21: 鈴木
A22: 完了 | B22: 19 | C22: Rrシート骨格設計部第2設計室 | D22: 16104078 | F22: ITK10742 | G22: 351D台座FRM開発 | I22: 9月 | J22: 45188 | K22: 齊藤
A23: 完了 | B23: 20 | C23: Rrシート骨格設計部第2設計室 | D23: 16104079 | F23: 10582 | G23: ミニバン統合骨格 | I23: 10月 | J23: 45198 | K23: 齊藤
A24: 完了 | B24: 21 | C24: Rrシート骨格設計部第2設計室 | D24: 16104080 | F24: 10565 | G24: QE36 SUBARU | I24: 10月 | J24: 45198 | K24: 齊藤
A25: 完了 | B25: 22 | C25: Rrシート骨格設計部第2設計室 | D25: 16104081 | F25: 10564 | G25: B658 SUBARU | I25: 10月 | J25: 45198 | K25: 齊藤
A26: 進行中 | B26: 23 | C26: Rrシート骨格設計部第2設計室 | D26: 16104082 | F26: 10990 | G26: QE36 SUBARU | I26: 11月 | J26: 45225 | K26: 齊藤
A27: 進行中 | B27: 24 | C27: Rrシート骨格設計部第2設計室 | D27: 16104083 | F27: 10984 | G27: ミニバン統合骨格 | I27: 11月 | J27: 45225 | K27: 齊藤
A28: 進行中 | B28: 25 | C28: Rrシート骨格設計部第2設計室 | D28: 16104084 | F28: 10982 | G28: B658 SUBARU | I28: 11月 | J28: 45225 | K28: 齊藤
B29: 26 | C29: Rrシート骨格設計部第2設計室 | D29: 16104085 | F29: 11330 | G29: 410D | I29: 11月 | J29: 45257 | K29: 齊藤
B30: 27 | C30: Rrシート骨格設計部第3設計室 | D30: 16104086 | F30: 11197 | G30: ミニバン統合骨格 | I30: 12月 | J30: 45250 | K30: 齊藤
B31: 28 | C31: Rrシート骨格設計部第4設計室 | D31: 16104087 | F31: 11192 | G31: B658 SUBARU | I31: 12月 | J31: 45250 | K31: 齊藤
B32: 29 | C32: Rrシート骨格設計部第5設計室 | D32: 16104088 | F32: 11191 | G32: QE36 SUBARU | I32: 12月 | J32: 45250 | K32: 齊藤
B33: 30 | C33: Rrシート骨格設計部第2設計室 | D33: 16104089 | F33: 11584 | G33: ミニバン統合骨格 | I33: 1月 | J33: 45279 | K33: 齊藤
B34: 31 | C34: Rrシート骨格設計部第2設計室 | D34: 16104090 | F34: 11581 | G34: B658 SUBARU | I34: 1月 | J34: 45279 | K34: 齊藤
B35: 32 | C35: Rrシート骨格設計部第2設計室 | D35: 16104091 | F35: 11580 | G35: QE36 SUBARU | I35: 1月 | J35: 45279 | K35: 齊藤
B36: 33 | C36: Rrシート骨格設計部第2設計室 | D36: 16104092 | F36: 11805 | G36: QE36 SUBARU | I36: 2月 | J36: 45309 | K36: 齊藤
B37: 34 | C37: Rrシート骨格設計部第2設計室 | D37: 16104093 | F37: 11806 | G37: B658 SUBARU | I37: 2月 | J37: 45309 | K37: 齊藤
B38: 35 | C38: Rrシート骨格設計部第2設計室 | D38: 16104094 | F38: 11807 | G38: ミニバン統合骨格 | I38: ２月 | J38: 45279 | K38: 齊藤
B39: 36 | C39: Rrシート骨格設計部第2設計室 | D39: 16104095 | F39: 12099 | G39: B658 SUBARU | I39: 3月 | J39: 45337 | K39: 齊藤
B40: 37 | C40: Rrシート骨格設計部第2設計室 | D40: 16104096 | F40: 12098 | G40: QE36 SUBARU | I40: 3月 | J40: 45337 | K40: 齊藤
B41: 38 | C41: Rrシート骨格設計部第2設計室 | D41: 16104097 | F41: 12100 | G41: ミニバン統合骨格 | I41: 3月 | J41: 45337 | K41: 齊藤
B42: 39 | C42: Rrシート骨格設計部第2設計室 | D42: 16104098 | F42: ITK12274 | G42: QE36 SUBARU | I42: 4月 | J42: 45377 | K42: 齊藤
B43: 40 | C43: Rrシート骨格設計部第2設計室 | D43: 16104099 | F43: ITK12539 | G43: QE36 SUBARU | I43: 5月 | J43: 45401 | K43: 齊藤
B44: 41 | C44: Rrシート骨格設計部第1設計室 | D44: 16104100 | F44: ITK12782 | G44: QE36 SUBARU | I44: 6月 | J44: 45435 | K44: 齊藤
B45: 42 | C45: Rrシート骨格設計部第1設計室 | D45: 16104101 | F45: 13081 | G45: QE36 SUBARU | I45: 7月 | J45: 45467 | K45: 齊藤
B46: 43 | C46: Rrシート骨格設計部第1設計室 | D46: 16104102 | F46: 13410 | G46: QE36 SUBARU | I46: 8月 | J46: '24/7/18 | K46: 齊藤
B47: 44 | C47: Rrシート骨格設計部第1設計室 | D47: 16104103 | F47: 14126 | G47: B747(695D) | I47: 10月-11月 | J47: '24/10/3 | K47: 久目形
B48: 45 | C48: Rrシート骨格設計部第1設計室 | D48: 16104104 | F48: 15139 | G48: QF02 | I48: 2月 | J48: 202/2/29 | K48: 久目形
B49: 46 | C49: Rrシート骨格設計部第1設計室 | D49: 16104105 | F49: 15209 | G49: QF02 | I49: 3月 | J49: 2025/2/26 | K49: 久目形
B50: 47 | C50: Rrシート骨格設計部第1設計室 | D50: 16104106 | F50: ITK15570 | G50: QF02 | I50: 4月 | J50: 45744 | K50: 丸山
B51: 48 | C51: Rrシート骨格設計部第1設計室 | D51: 16104107 | F51: ITK15535 | G51: 749D(B781) | I51: 4月 | J51: 45744 | K51: 丸山
B52: 49 | C52: Rrシート骨格設計部第1設計室 | D52: 16104108 | F52: ITK15822 | G52: QF02 | I52: 5月 | J52: 45784 | K52: 丸山
B53: 50 | C53: Rrシート骨格設計部第1設計室 | D53: 16104109 | F53: ITK15823 | G53: X1TE新プレステージ開発 | I53: 5月 | J53: 45784 | K53: 丸山
B54: 51 | C54: Rrシート骨格設計部第1設計室 | D54: 16104110 | F54: ITK15821 | G54: B780新プレステージ開発 | I54: 5月 | J54: 45784 | K54: 丸山
B55: 52 | C55: Rrシート骨格設計部第1設計室 | D55: 16104111 | F55: 16196 | G55: X1TE新プレステージ開発 | I55: 6月 | J55: 45798 | K55: 丸山
B56: 53 | C56: Rrシート骨格設計部第1設計室 | D56: 16104112 | F56: 16197 | G56: B780新プレステージ開発 | I56: 6月 | J56: 45798 | K56: 丸山
B57: 54 | C57: Rrシート骨格設計部第1設計室 | D57: 16104113 | F57: 16045 | G57: QF02 | I57: 6月 | J57: 45805 | K57: 丸山
B58: 55 | C58: Rrシート骨格設計部第1設計室 | D58: 16104114 | F58: 16507 | G58: X1TE新プレステージ開発 | I58: 7月 | J58: 45835 | K58: 久目形
B59: 56 | C59: Rrシート骨格設計部第1設計室 | D59: 16104115 | F59: 16455 | G59: QF02 | I59: 7月 | J59: 45835 | K59: 久目形
B60: 57 | C60: Rrシート骨格設計部第1設計室 | D60: 16104116 | F60: 16456 | G60: B780新プレステージ開発 | I60: 7月 | J60: 45835 | K60: 久目形
B61: 58 | C61: Rrシート骨格設計部第1設計室 | D61: 16104117 | F61: 16724 | G61: X1TE新プレステージ開発 | I61: 8月 | J61: 45855 | K61: 久目形
B62: 59 | C62: Rrシート骨格設計部第1設計室 | D62: 16104118 | F62: 16725 | G62: B780新プレステージ開発 | I62: 8月 | J62: 45855 | K62: 久目形
B63: 60 | C63: Rrシート骨格設計部第1設計室 | D63: 16104119 | F63: 16638 | G63: 737D Rr2シートフレーム開発 | I63: 8月 | J63: ’25/7/21 | K63: 久目形
B64: 61 | C64: Rrシート骨格設計部第1設計室 | D64: 16104120 | F64: 16942 | G64: 737D Rr2シートフレーム開発 | I64: 9月 | J64: 45889 | K64: 久目形
B65: 62 | C65: Rrシート骨格設計部第1設計室 | D65: 16104121 | F65: 17035 | G65: B780新プレステージ開発 | I65: 9月 | J65: 45889 | K65: 久目形
B66: 63 | C66: Rrシート骨格設計部第1設計室 | D66: 16104122 | F66: 17034 | G66: X1TE新プレステージ開発 | I66: 9月 | J66: 45889 | K66: 久目形
B67: 64 | C67: Rrシート骨格設計部第1設計室 | D67: 16104123 | F67: 17360 | G67: X1TE新プレステージ開発 | I67: 10月 | J67: 45918 | K67: 久目形
B68: 65 | C68: Rrシート骨格設計部第1設計室 | D68: 16104124 | F68: 17359 | G68: B780新プレステージ開発 | I68: 10月 | J68: 45918 | K68: 久目形
B69: 66 | C69: Rrシート骨格設計部第1設計室 | D69: 16104125 | F69: 17221 | G69: 737D Rr2シートフレーム開発 | I69: 10月 | J69: 45918 | K69: 久目形 | L69: 客先ミス：廃止（元々受注はなかった）
B70: 67 | C70: Rrシート骨格設計部第1設計室 | D70: 16104126 | F70: 17412 | G70: サイドバックロックタイプ XN02 | I70: 10月 | J70: 45929 | K70: 久目形
B71: 68 | C71: Rrシート骨格設計部第1設計室 | D71: 16104127 | F71: 17566 | G71: X1TE新プレステージ開発 | I71: 11月 | J71: 45951 | K71: 久目形
B72: 69 | C72: Rrシート骨格設計部第1設計室 | D72: 16104128 | F72: 17565 | G72: B780新プレステージ開発 | I72: 11月 | J72: 45951 | K72: 久目形
B73: 64 | C73: Rrシート骨格設計部第1設計室 | D73: 16104129 | F73: 17567 | G73: サイドバックロックタイプ XN02 | I73: 11月 | J73: 45951 | K73: 久目形
C74: Rrシート骨格設計部第1設計室 | D74: 16104130 | F74: 17838 | G74: X1TE新プレステージ開発 | I74: 12月 | J74: 45975 | K74: 久目形
C75: Rrシート骨格設計部第1設計室 | D75: 16104131 | F75: 17892 | G75: サイドバックロックタイプ XN02 | I75: 12月 | J75: 45978 | K75: 久目形
C76: Rrシート骨格設計部第1設計室 | D76: 16104132 | F76: 17965 | G76: B780新プレステージ開発 | I76: 12月 | J76: 45986 | K76: 久目形
C77: Rrシート骨格設計部第1設計室 | D77: 16104133 | F77: 18140 | G77: X1TE新プレステージ開発 | I77: １月 | J77: 46008 | K77: 久目形
C78: Rrシート骨格設計部第1設計室 | D78: 16104134 | F78: 18218 | G78: サイドバックロックタイプ XN02 | I78: １月 | J78: 46008 | K78: 久目形
C79: Rrシート骨格設計部第1設計室 | D79: 16104135 | F79: 18141 | G79: B780新プレステージ開発 | I79: １月 | J79: 46008 | K79: 久目形
D80: 16104136
D81: 16104137
D82: 16104138
D83: 16104139
D84: 16104140

Sheet GS
A1: 2024年 | C1: エンジニアリングサービス部 見積書・請求書発行管理台帳 | H1: 見積書(税抜金額)
A2: 企業名： | C2: トヨタ紡織(株)
A3: タスク | B3: No | C3: 部署名 | D3: 見積/請求番号 | E3: 発注番号 | F3: 業務計画書No | G3: 案件名 | H3: 見積金額 | I3: 見積月 | J3: 発行日 | K3: 発行者 | L3: 備考
A4: 完了 | B4: 1 | C4: グローバルシート設計室 | D4: 16119078 | E4: 802-2212-0158-000 | F4: ITK08043 | G4: D92A/D54B | I4: 1月 | J4: 44923 | K4: 鈴木
A5: 完了 | B5: 2 | C5: グローバルシート設計室 | D5: 16119079 | E5: 802-2212-0062-000 | F5: ITK08195 | G5: B-SUV 2列 | I5: 1月 | J5: 44923 | K5: 鈴木
A6: 完了 | B6: 3 | C6: グローバルシート設計室 | D6: 16119080 | E6: 802-2212-0199-000 | F6: ITK07918 | G6: B-SUV Fr開発 MY(追加) | I6: 1月 | J6: 44923 | K6: 鈴木
A7: 完了 | B7: 4 | C7: グローバルシート設計室 | D7: 16119081 | E7: 802-2212-0057-000 | F7: ITK08201 | G7: B-SUV Fr開発 MY | I7: 1月 | J7: 44923 | K7: 鈴木
A8: 完了 | B8: 5 | C8: グローバルシート設計室 | D8: 16119082 | E8: 802-2212-0193-000 | F8: ITK08000 | G8: 3列 B-EV | I8: 1月 | J8: 44923 | K8: 鈴木
A9: 完了 | B9: 6 | C9: グローバルシート設計室 | D9: 16119083 | E9: 802-2212-0081-000 | F9: 8164 | G9: 320D | I9: 1月 | J9: 44923 | K9: 鈴木
A10: 完了 | B10: 7 | C10: グローバルシート設計室 | D10: 16119084 | E10: 802-2212-0166-000 | F10: 8034 | G10: 612W | I10: 1月 | J10: 44923 | K10: 鈴木
A11: 完了 | B11: 8 | C11: グローバルシート設計室 | D11: 16119085 | E11: 802-2212-0163-000 | F11: 8037 | G11: D74A | I11: 1月 | J11: 44923 | K11: 鈴木
A12: 完了 | B12: 9 | C12: グローバルシート設計室 | D12: 16119086 | E12: 802-2212-0167-000 | F12: 8033 | G12: D25B | I12: 1月 | J12: 44923 | K12: 鈴木
A13: 完了 | B13: 10 | C13: グローバルシート設計室 | D13: 16119087 | E13: 802-2212-0131-000 | F13: 8078 | G13: YY8 | I13: 1月 | J13: 44923 | K13: 鈴木
A14: 完了 | B14: 11 | C14: グローバルシート設計室 | D14: 16119088 | E14: 802-2212-0019-000 | F14: 8298 | G14: D03B Fr開発 | I14: 1月 | J14: 44923 | K14: 鈴木
A15: 完了 | B15: 12 | C15: グローバルシート設計室 | D15: 16119089 | E15: 802-2212-0128-000 | F15: 8081 | G15: D90B | I15: 1月 | J15: 44923 | K15: 鈴木
A16: 完了 | B16: 13 | C16: グローバルシート設計室 | D16: 16119090 | E16: 802-2301-0109-000 | F16: 8368 | G16: D92A/D54B | I16: 2月 | J16: 44965 | K16: 鈴木
A17: 完了 | B17: 14 | C17: グローバルシート設計室 | D17: 16119091 | E17: 802-2301-0130-000 | F17: 8321 | G17: 3列 B-EV | I17: 2月 | J17: 44965 | K17: 鈴木
A18: 完了 | B18: 15 | C18: グローバルシート設計室 | D18: 16119092 | E18: 802-2301-0142-000 | F18: 8291 | G18: 320D | I18: 2月 | J18: 44965 | K18: 鈴木
A19: 完了 | B19: 16 | C19: グローバルシート設計室 | D19: 16119093 | E19: 802-2301-0103-000 | F19: 8382 | G19: 612W | I19: 2月 | J19: 44965 | K19: 鈴木
A20: 完了 | B20: 17 | C20: グローバルシート設計室 | D20: 16119094 | E20: 802-2301-0105-000 | F20: 8380 | G20: D74A | I20: 2月 | J20: 44965 | K20: 鈴木
... A25: 完了 | B25: 22 | C25: グローバルシート設計室 | D25: 16119099 | E25: 802-2301-0028-000 | F25: 8512 | G25: B-SUV Fr開発 MY | I25: 2月 | J25: 44960 | K25: 鈴木
A26: 完了 | B26: 23 | C26: グローバルシート設計室 | D26: 16119100 | F26: 8599 | G26: D92A/D54B | I26: 3月 | J26: 44994 | K26: 鈴木
A27: 完了 | B27: 24 | C27: グローバルシート設計室 | D27: 16119101 | F27: 8634 | G27: 3列 B-EV | I27: 3月 | J27: 44994 | K27: 鈴木
A28: 完了 | B28: 25 | C28: グローバルシート設計室 | D28: 16119102 | F28: 8635 | G28: 320D | I28: 3月 | J28: 44994 | K28: 鈴木
A29: 完了 | B29: 26 | C29: グローバルシート設計室 | D29: 16119103 | F29: 8648 | G29: D74A | I29: 3月 | J29: 44994 | K29: 鈴木
A30: 完了 | B30: 27 | C30: グローバルシート設計室 | D30: 16119104 | F30: 8664 | G30: D90B | I30: 3月 | J30: 44994 | K30: 鈴木
A31: 完了 | B31: 28 | C31: グローバルシート設計室 | D31: 16119105 | E31: 802-2302-0068-000 | F31: 8687 | G31: 612W | I31: 3月 | J31: 44984 | K31: 鈴木
A32: 完了 | B32: 29 | C32: グローバルシート設計室 | D32: 16119106 | E32: 802-2302-0059-000 | F32: 8706 | G32: D25B | I32: 3月 | J32: 44984 | K32: 鈴木
A33: 完了 | B33: 30 | C33: グローバルシート設計室 | D33: 16119107 | F33: 8719 | G33: YY8 | I33: 3月 | J33: 44994 | K33: 鈴木
A34: 完了 | B34: 31 | C34: グローバルシート設計室 | D34: 16119108 | F34: 857 | G34: B-SUV 2列 | I34: 3月 | J34: 44994 | K34: 鈴木
A35: 完了 | B35: 32 | C35: グローバルシート設計室 | D35: 16119109 | F35: 856 | G35: B-SUV Fr開発 MY | I35: 3月 | J35: 44994 | K35: 鈴木
A36: 完了 | B36: 33 | C36: グローバルシート設計室 | D36: 16119110 | F36: 8863 | G36: D92A/D54B | I36: 4月 | J36: 45016 | K36: 鈴木
A37: 完了 | B37: 34 | C37: グローバルシート設計室 | D37: 16119111 | F37: 8827 | G37: B-SUV 2列 | I37: 4月 | J37: 45016 | K37: 鈴木
A38: 完了 | B38: 35 | C38: グローバルシート設計室 | D38: 16119112 | F38: 8951 | G38: 320D | I38: 4月 | J38: 45016 | K38: 鈴木
A39: 完了 | B39: 36 | C39: グローバルシート設計室 | D39: 16119113 | F39: 8843 | G39: 612W | I39: 4月 | J39: 45016 | K39: 鈴木
A40: 完了 | B40: 37 | C40: グローバルシート設計室 | D40: 16119114 | F40: 8881 | G40: D90B | I40: 4月 | J40: 45016 | K40: 鈴木
A41: 完了 | B41: 38 | C41: グローバルシート設計室 | D41: 16119115 | F41: 8844 | G41: D42H | I41: 4月 | J41: 45016 | K41: 鈴木
A42: 完了 | B42: 39 | C42: グローバルシート設計室 | D42: 16119116 | F42: 8845 | G42: 524D(612W) | I42: 4月 | J42: 45016 | K42: 鈴木
A43: 完了 | B43: 40 | C43: グローバルシート設計室 | D43: 16119117 | F43: 8841 | G43: D38H | I43: 4月 | J43: 45016 | K43: 鈴木
A44: 完了 | B44: 41 | C44: グローバルシート設計室 | D44: 16119118 | F44: 9335 | G44: D92A/D54B | I44: 5月 | J44: 45044 | K44: 鈴木
... A93: 進行中 | B93: 90 | C93: グローバルシート設計室 | D93: 16119167 | F93: 10950 | G93: B-SUV 2列 | I93: 11月 | J93: 45225 | K93: 齊藤
B94: 91 | C94: グローバルシート設計室 | D94: 16119168 | F94: 11183 | G94: B-SUV 2列 | I94: 12月 | J94: 45250 | K94: 齊藤
B95: 92 | C95: グローバルシート設計室 | D95: 16119169 | F95: 11320 | G95: 524D(612W) | I95: 12月 | J95: 45250 | K95: 齊藤
B96: 93 | C96: グローバルシート設計室 | D96: 16119170 | F96: 11319 | G96: 612W | I96: 12月 | J96: 45250 | K96: 齊藤
B97: 94 | C97: グローバルシート設計室 | D97: 16119171 | F97: 11317 | G97: D42H | I97: 12月 | J97: 45250 | K97: 齊藤
B98: 95 | C98: グローバルシート設計室 | D98: 16119172 | F98: 11316 | G98: D38H | I98: 12月 | J98: 45250 | K98: 齊藤
B99: 96 | C99: グローバルシート設計室 | D99: 16119173 | F99: 11315 | G99: D90B | I99: 12月 | J99: 45250 | K99: 齊藤
B100: 97 | C100: グローバルシート設計室 | D100: 16119174 | F100: 11304 | G100: D92A/D54B | I100: 12月 | J100: 45250 | K100: 齊藤
B101: 98 | C101: グローバルシート設計室 | D101: 16119175 | F101: ITK11539 | G101: 524D(612W) | I101: 1月 | J101: 45275 | K101: 齊藤
B102: 99 | C102: グローバルシート設計室 | D102: 16119176 | F102: ITK11528 | G102: 612W | I102: 1月 | J102: 45275 | K102: 齊藤
B103: 100 | C103: グローバルシート設計室 | D103: 16119177 | F103: ITK11533 | G103: D90B | I103: 1月 | J103: 45275 | K103: 齊藤
B104: 101 | C104: グローバルシート設計室 | D104: 16119178 | F104: ITK11532 | G104: B-SUV 2列 | I104: 1月 | J104: 45275 | K104: 齊藤
B105: 102 | C105: グローバルシート設計室 | D105: 16119179 | F105: ITK11559 | G105: D92A/D54B | I105: 1月 | J105: 45275 | K105: 齊藤
B106: 103 | C106: グローバルシート設計室 | D106: 16119180 | F106: 11851 | G106: 612W | I106: ２月 | J106: 45310 | K106: 齊藤
B107: 104 | C107: グローバルシート設計室 | D107: 16119181 | F107: 11852 | G107: 524D(612W) | I107: ２月 | J107: 45310 | K107: 齊藤
B108: 105 | C108: グローバルシート設計室 | D108: 16119182 | F108: 11878 | G108: B-SUV 2列 | I108: ２月 | J108: 45310 | K108: 齊藤
B109: 106 | C109: グローバルシート設計室 | D109: 16119183 | F109: 11879 | G109: D90B | I109: ２月 | J109: 45310 | K109: 齊藤
B110: 107 | C110: グローバルシート設計室 | D110: 16119184 | F110: 11883 | G110: D92A/D54B | I110: ２月 | J110: 45310 | K110: 齊藤
B111: 108 | C111: グローバルシート設計室 | D111: 16119185 | F111: 12081 | G111: D92A/D54B | I111: 3月 | J111: 45337 | K111: 齊藤
B112: 109 | C112: グローバルシート設計室 | D112: 16119186 | F112: 12114 | G112: 612W | I112: 3月 | J112: 45337 | K112: 齊藤
B113: 110 | C113: グローバルシート設計室 | D113: 16119187 | F113: 12089 | G113: 524D(612W) | I113: 3月 | J113: 45337 | K113: 齊藤
B114: 111 | C114: グローバルシート設計室 | D114: 16119188 | F114: 12159 | G114: D90B | I114: 3月 | J114: 45337 | K114: 齊藤
B115: 112 | C115: グローバルシート設計室 | D115: 16119189 | F115: 12160 | G115: B-SUV 2列 | I115: 3月 | J115: 45337 | K115: 齊藤
B116: 113 | C116: グローバルシート設計室 | D116: 16119190 | F116: ITK12510 | G116: 524D(612W) | I116: 4月 | J116: 45380 | K116: 齊藤
B117: 114 | C117: グローバルシート設計室 | D117: 16119191 | F117: ITK12511 | G117: B-SUV 2列 | I117: 4月 | J117: 45380 | K117: 齊藤
B118: 115 | C118: グローバルシート設計室 | D118: 16119192 | F118: ITK12537 | G118: D92A号口 | I118: 4月 | J118: '24/4/6 | K118: 齊藤
B119: 116 | C119: グローバルシート設計室 | D119: 16119193 | F119: ITK12536 | G119: D90B | I119: 4月 | J119: '24/4/6 | K119: 齊藤
B120: 117 | C120: グローバルシート設計室 | D120: 16119194 | F120: ITK12533 | G120: 612W号口 | I120: 4月 | J120: '24/4/11 | K120: 齊藤
B121: 118 | C121: グローバルシート設計室 | D121: 16119195 | F121: ITK12527 | G121: D38H | I121: 4月 | J121: '24/4/11 | K121: 齊藤
B122: 119 | C122: グローバルシート設計部 | D122: 16119196 | F122: ITK12632 | G122: D90B | I122: 5月 | J122: '24/4/19 | K122: 齊藤
B123: 120 | C123: グローバルシート設計部 | D123: 16119197 | F123: ITK12635 | G123: B-SUV 2列 | I123: 5月 | J123: '24/4/19 | K123: 齊藤
B124: 121 | C124: グローバルシート設計部 | D124: 16119198 | F124: ITK12636 | G124: D38H | I124: 5月 | J124: '24/4/19 | K124: 齊藤
B125: 122 | C125: グローバルシート設計部 | D125: 16119199 | F125: ITK12637 | G125: 524D(612W) | I125: 5月 | J125: '24/4/19 | K125: 齊藤
B126: 123 | C126: グローバルシート設計部 | D126: 16119200 | F126: ITK12638 | G126: 612W号口 | I126: 5月 | J126: '24/4/19 | K126: 齊藤
B127: 124 | C127: グローバルシート設計部 | D127: 16119201 | F127: ITK12654 | G127: D92A号口 | I127: 5月 | J127: '24/4/19 | K127: 齊藤
B128: 125 | C128: グローバルシート設計部 | D128: 16119202 | F128: ITK12855 | G128: D90B | I128: 6月 | J128: '24/5/23 | K128: 齊藤
B129: 126 | C129: グローバルシート設計部 | D129: 16119203 | F129: ITK12827 | G129: B-SUV 2列 | I129: 6月 | J129: '24/5/23 | K129: 齊藤
... B133: 130 | C133: グローバルシート設計部 | D133: 16119207 | F133: ITK12822 | G133: D38H | I133: 6月 | J133: '24/5/23 | K133: 齊藤
B134: 131 | C134: グローバルシート設計部 | D134: 16119208 | F134: 13086 | G134: D92A号口 | I134: 7月 | J134: '24/6/24 | K134: 齊藤
B135: 132 | C135: グローバルシート設計部 | D135: 16119209 | F135: 13089 | G135: D38H | I135: 7月 | J135: '24/6/24 | K135: 齊藤
B136: 133 | C136: グローバルシート設計部 | D136: 16119210 | F136: 13126 | G136: D90B | I136: 7月 | J136: '24/6/24 | K136: 齊藤
B137: 134 | C137: グローバルシート設計部 | D137: 16119211 | F137: 13088 | G137: 524D(612W) | I137: 7月 | J137: '24/6/24 | K137: 齊藤
B138: 135 | C138: グローバルシート設計部 | D138: 16119212 | F138: 13087 | G138: 612W号口 | I138: 7月 | J138: '24/6/24 | K138: 齊藤
B139: 136 | C139: グローバルシート設計部 | D139: 16119213 | F139: 13242 | G139: B-SUV 2列 | I139: 7月 | J139: '24/6/24 | K139: 齊藤
B140: 137 | C140: グローバルシート設計部 | D140: 16119214 | F140: 13567 | G140: B-SUV 2列 | I140: 8月 | J140: '24/7/16 | K140: 齊藤
B141: 138 | C141: グローバルシート設計部 | D141: 16119215 | F141: 13502 | G141: D90B | I141: 8月 | J141: '24/7/16 | K141: 齊藤
B142: 139 | C142: グローバルシート設計部 | D142: 16119216 | F142: 13500 | G142: D92A号口 | I142: 8月 | J142: '24/7/16 | K142: 齊藤
B143: 140 | C143: グローバルシート設計部 | D143: 16119217 | F143: 13499 | G143: 612W号口 | I143: 8月 | J143: '24/7/16 | K143: 齊藤
B144: 141 | C144: グローバルシート設計部 | D144: 16119218 | F144: 13498 | G144: 524D(612W) | I144: 8月 | J144: '24/7/16 | K144: 齊藤
B145: 142 | C145: グローバルシート設計部 | D145: 16119219 | F145: 13497 | G145: D38H | I145: 8月 | J145: '24/7/16 | K145: 齊藤
... B169: 166 | C169: グローバルシート設計部 | D169: 16119243 | F169: 14463 | G169: D90B | I169: 12月 | J169: '24/11/29 | K169: 久目形
B170: 167 | C170: グローバルシート設計部 | D170: 16119244 | F170: 14778 | G170: 612W号口 | I170: 1月 | J170: 45645 | K170: 久目形
B171: 168 | C171: グローバルシート設計部 | D171: 16119245 | F171: 14758 | G171: D90B | I171: 1月 | J171: 45645 | K171: 久目形
B172: 169 | C172: グローバルシート設計部 | D172: 16119246 | F172: 14769 | G172: D92A号口 | I172: 1月 | J172: 45645 | K172: 久目形
B173: 170 | C173: グローバルシート設計部 | D173: 16119247 | F173: 14768 | G173: D38H | I173: 1月 | J173: 45645 | K173: 久目形
B174: 171 | C174: グローバルシート設計部 | D174: 16119248 | F174: 14767 | G174: 524D(612W) | I174: 1月 | J174: 45645 | K174: 久目形
B175: 172 | C175: グローバルシート設計部 | D175: 16119249 | F175: 14730 | G175: B-SUV 2列 | I175: 1月 | J175: 45645 | K175: 久目形
B176: 173 | C176: グローバルシート設計部 | D176: 16119250 | F176: 15033 | G176: 612W号口 | I176: 2月 | J176: 202/2/29 | K176: 久目形
B177: 174 | C177: グローバルシート設計部 | D177: 16119251 | F177: 15073 | G177: D90B | I177: 2月 | J177: 202/2/29 | K177: 久目形
B178: 175 | C178: グローバルシート設計部 | D178: 16119252 | F178: 15030 | G178: D92A号口 | I178: 2月 | J178: 202/2/29 | K178: 久目形
...

Sheet BX→ｼｰﾄﾃﾞﾊﾞｲｽ
A1: 2024年 | C1: エンジニアリングサービス部 見積書・請求書発行管理台帳 | H1: 見積書(税抜金額)
A2: 企業名： | C2: トヨタ紡織(株)
A3: タスク | B3: No | C3: 部署名 | D3: 見積/請求番号 | E3: 発注番号 | F3: 業務計画書No | G3: 案件名 | H3: 見積金額 | I3: 見積月 | J3: 発行日 | K3: 発行者 | L3: 備考
A4: 完了 | B4: 1 | C4: シート機能品設計部第2設計室 | D4: 16117014 | E4: BX-22-012 | F4: - | G4: DASデータまとめ | I4: 1月 | J4: 44903 | K4: 鈴木
A5: 完了 | B5: 2 | C5: シート機能品設計部第2設計室 | D5: 16117015 | E5: BX-22-013 | F5: - | G5: DASデータまとめ | I5: 2月 | J5: 44937 | K5: 鈴木
A6: 完了 | B6: 3 | C6: シート機能品設計部第2設計室 | D6: 16117016 | F6: - | G6: DASデータまとめ | I6: 3月 | J6: 44966 | K6: 鈴木
A7: 完了 | B7: 4 | C7: シートデバイス設計部 | D7: 16117017 | F7: - | G7: DASデータまとめ | I7: 4月 | J7: 44999 | K7: 鈴木
A8: 完了 | B8: 5 | C8: シートデバイス設計部 | D8: 16117018 | F8: - | G8: DASデータまとめ | I8: 5月 | J8: 45023 | K8: 鈴木
A9: 完了 | B9: 6 | C9: シートデバイス設計部 | D9: 16117019 | F9: - | G9: DASデータまとめ | I9: 6月 | J9: 45063 | K9: 鈴木
A10: 完了 | B10: 7 | C10: シートデバイス設計部 | D10: 16117020 | F10: - | G10: DASデータまとめ | I10: 7月 | J10: 45085 | K10: 鈴木
A11: 完了 | B11: 8 | C11: シートデバイス設計部 | D11: 16117021 | F11: - | G11: DASデータまとめ | I11: 8月 | J11: 45112 | K11: 鈴木
A12: 完了 | B12: 9 | C12: シートデバイス設計部 | D12: 16117022 | F12: - | G12: DASデータまとめ | I12: 9月 | J12: 45148 | K12: 鈴木
A13: 完了 | B13: 10 | C13: シートデバイス設計部 | D13: 16117023 | F13: - | G13: DASデータまとめ | I13: 10月 | J13: 45183 | K13: 齊藤
A14: 進行中 | B14: 11 | C14: シートデバイス設計部 | D14: 16117024 | F14: - | G14: DASデータまとめ | I14: 11月 | J14: 45210 | K14: 齊藤
A15: 見積着手 | B15: 12 | C15: シートデバイス設計部 | D15: 16117025 | F15: - | G15: DASデータまとめ | I15: 12月 | J15: 45243 | K15: 齊藤
B16: 13 | C16: シートデバイス設計部 | D16: 16117026 | F16: - | G16: DASデータまとめ | I16: 1月 | J16: 45266 | K16: 齊藤
B17: 14 | C17: シートデバイス設計部 | D17: 16117027 | F17: - | G17: DASデータまとめ | I17: 2月 | J17: 44944 | K17: 齊藤
B18: 15 | C18: シートデバイス設計部 | D18: 16117028 | F18: - | G18: DASデータまとめ | I18: 3月 | J18: 44963 | K18: 齊藤
B19: 16 | C19: シートデバイス設計部 | D19: 16117029 | F19: - | G19: DASデータまとめ | I19: 4月 | J19: 44998 | K19: 齊藤
B20: 17 | C20: シートデバイス設計部 | D20: 16117030 | F20: - | G20: DASデータまとめ | I20: 5月 | J20: 45024 | K20: 齊藤
B21: 18 | C21: デバイス開発領域 | D21: 16117031 | F21: - | G21: DASデータまとめ | I21: 6月 | J21: 45056 | K21: 齊藤
B22: 19 | C22: デバイス開発領域 | D22: 16117032 | F22: - | G22: DASデータまとめ | I22: 7月 | J22: 45087 | K22: 齊藤
B23: 20 | C23: デバイス開発領域 | D23: 16117033 | F23: - | G23: DASデータまとめ | I23: ８月 | J23: 45115 | K23: 齊藤
B24: 21 | C24: デバイス開発領域 | D24: 16117034 | F24: - | G24: DASデータまとめ | I24: 9月 | J24: 45510 | K24: 齊藤
B25: 22 | C25: デバイス開発領域 | D25: 16117035 | F25: - | G25: DASデータまとめ | I25: 10月 | J25: 45544 | K25: 久目形
B26: 23 | C26: デバイス開発領域 | D26: 16117036 | F26: - | G26: DASデータまとめ | I26: 11月 | J26: 45583 | K26: 久目形
B27: 24 | C27: デバイス開発領域 | D27: 16117037 | F27: - | G27: DASデータまとめ | I27: 12月 | J27: 45604 | K27: 久目形
... B34: 31 | C34: デバイス開発領域 | D34: 16117044 | F34: - | G34: DASデータまとめ | I34: 7月 | J34: 45817 | K34: 久目形
B35: 32 | C35: デバイス開発領域 | D35: 16117045 | F35: - | G35: DASデータまとめ | I35: 8月 | J35: ’25/7/4 | K35: 久目形
B36: 33 | C36: デバイス開発領域 | D36: 16117046 | F36: - | G36: DASデータまとめ | I36: 9月 | J36: ’25/8/6 | K36: 久目形
B37: 34 | C37: デバイス開発領域 | D37: 16117047 | F37: - | G37: DASデータまとめ | I37: 10月 | J37: ’25/9/8 | K37: 久目形
B38: 35 | C38: デバイス開発領域 | D38: 16117048 | F38: - | G38: DASデータまとめ | I38: 11月 | J38: ’25/10/13 | K38: 久目形
B39: 36 | C39: デバイス開発領域 | D39: 16117049 | F39: - | G39: DASデータまとめ | I39: 12月 | J39: ’25/11/10 | K39: 久目形
B40: 37 | C40: デバイス開発領域 | D40: 16117050 | F40: - | G40: DASデータまとめ | I40: 1月 | J40: 45996 | K40: 久目形
B41: 38 | D41: 16117051
B42: 39 | D42: 16117052
B43: 40 | D43: 16117053
B44: 41 | D44: 16117054
B45: 42 | D45: 16117055
B46: 43 | D46: 16117056
B47: 44 | D47: 16117057
B48: 45 | D48: 16117058
B49: 46 | D49: 16117059
B50: 47 | D50: 16117060

Sheet ND
A1: 2024年 | C1: エンジニアリングサービス部 見積書・請求書発行管理台帳 | H1: 見積書(税抜金額)
A2: 企業名： | C2: トヨタ紡織(株)
A3: タスク | B3: No | C3: 部署名 | D3: 見積/請求番号 | E3: 発注番号 | F3: 業務計画書No | G3: 案件名 | H3: 見積金額 | I3: 見積月 | J3: 発行日 | K3: 発行者 | L3: 備考
A4: 完了 | B4: 1 | C4: ドアトリム設計部第1ドアトリム設計室 | D4: 16116026 | E4: 401-2212-0002-000 | F4: ITK08120 | G4: 700W他_号口管理 | I4: 1月 | J4: 44914 | K4: 鈴木
A5: 完了 | B5: 2 | C5: ドアトリム設計部第2ドアトリム設計室 | D5: 16116027 | E5: 404-2212-0012-000 | F5: ITK08207 | G5: D90B | I5: 1月 | J5: 44921 | K5: 鈴木
A6: 完了 | B6: 3 | C6: ドアトリム設計部第2ドアトリム設計室 | D6: 16116028 | E6: 404-2212-0011-000 | F6: ITK08206 | G6: 478D | I6: 1月 | J6: 44921 | K6: 鈴木
A7: 完了 | B7: 4 | C7: ドアトリム設計部第2ドアトリム設計室 | D7: 16116029 | E7: 404-2301-0009-000 | F7: 8451 | G7: D90B | I7: 2月 | J7: 44945 | K7: 鈴木
A8: 完了 | B8: 5 | C8: ドアトリム設計部第2ドアトリム設計室 | D8: 16116030 | E8: 404-2301-0008-000 | F8: 8487 | G8: 478D | I8: 2月 | J8: 44945 | K8: 鈴木
A9: 完了 | B9: 6 | C9: ドアトリム設計部第1ドアトリム設計室 | D9: 16116031 | E9: 401-2301-0001-000 | F9: 8524 | G9: 700W他_号口管理 | I9: 2月 | J9: 44950 | K9: 鈴木
A10: 完了 | B10: 7 | C10: ドアトリム設計部第1ドアトリム設計室 | D10: 16116032 | E10: 401-2302-0001-000 | F10: 8770 | G10: 700W他_号口管理 | I10: 3月 | J10: 44974 | K10: 鈴木
A11: 完了 | B11: 8 | C11: ドアトリム設計部第2ドアトリム設計室 | D11: 16116033 | E11: 404-2303-0002-000 | F11: 8814 | G11: D90B | I11: 3月 | J11: 44995 | K11: 鈴木
A12: 完了 | B12: 9 | C12: ドアトリム設計部第1ドアトリム設計室 | D12: 16116034 | F12: 9007 | G12: 700W他_号口管理 | I12: 4月 | J12: 45007 | K12: 鈴木
A13: 完了 | B13: 10 | C13: ドアトリム設計部先行設計室 | D13: 16116035 | F13: 9109 | G13: 競争力BMC | I13: 4月 | J13: 45016 | K13: 鈴木
A14: 完了 | B14: 11 | C14: ドアトリム設計部第1ドアトリム設計室 | D14: 16116036 | F14: 9178 | G14: 700W他_号口管理 | I14: 5月 | J14: 45027 | K14: 鈴木
A15: 完了 | B15: 12 | C15: ドアトリム設計部先行設計室 | D15: 16116037 | F15: 9176 | G15: 競争力BMC | I15: 5月 | J15: 45028 | K15: 鈴木
A16: 完了 | B16: 13 | C16: ドアトリム設計部第1ドアトリム設計室 | D16: 16116038 | F16: 9432 | G16: 700W他_号口管理 | I16: 6月 | J16: 45078 | K16: 鈴木
A17: 完了 | B17: 14 | C17: ドアトリム設計部先行設計室 | D17: 16116039 | F17: 9408 | G17: 競争力BMC | I17: 6月 | J17: 45078 | K17: 鈴木
A18: 完了 | B18: 15 | C18: ドアトリム設計部第1ドアトリム設計室 | D18: 16116040 | F18: 9841 | G18: 700W他_号口管理 | I18: 7月 | J18: 45099 | K18: 鈴木
A19: 完了 | B19: 16 | C19: ドアトリム設計部先行設計室 | D19: 16116041 | F19: 9842 | G19: 競争力BMC | I19: 7月 | J19: 45097 | K19: 鈴木
A20: 完了 | B20: 17 | C20: ドアトリム設計部先行設計室 | D20: 16116042 | F20: 10060 | G20: 競争力BMC | I20: 8月 | J20: 45121 | K20: 鈴木
A21: 完了 | B21: 18 | C21: ドアトリム設計部第1ドアトリム設計室 | D21: 16116043 | F21: 10069 | G21: 700W他_号口管理 | I21: 8月 | J21: 45119 | K21: 鈴木
A22: 完了 | B22: 19 | C22: ドアトリム設計部第1ドアトリム設計室 | D22: 16116044 | F22: 10283 | G22: 700W他_号口管理 | I22: 9月 | J22: 45138 | K22: 鈴木
A23: 完了 | B23: 20 | C23: ドアトリム設計部先行設計室 | D23: 16116045 | F23: 10310 | G23: 競争力BMC | I23: 9月 | J23: 45140 | K23: 鈴木
... A26: 進行中 | B26: 23 | C26: ドアトリム設計部第1ドアトリム設計室 | D26: 16116048 | F26: 10863 | G26: 700W他_号口管理 | I26: 11月 | J26: 45202 | K26: 齊藤
A27: 進行中 | B27: 24 | C27: ドアトリム設計部先行設計室 | D27: 16116049 | F27: ITK10868 | G27: 競争力BMC | I27: 11月 | J27: 45210 | K27: 齊藤
A28: 見積完了 | B28: 25 | C28: ドアトリム設計部第1ドアトリム設計室 | D28: 16116050 | F28: 11107 | G28: 700W他_号口管理 | I28: 12月 | J28: 45234 | K28: 齊藤
B29: 26 | C29: ドアトリム設計部先行設計室 | D29: 16116051 | F29: 11296 | G29: 競争力BMC | I29: 12月 | J29: 45250 | K29: 齊藤
B30: 27 | C30: ドアトリム設計部 | D30: 16116052 | F30: 11343 | G30: SHC部品開発 | I30: 11月 | J30: 45252 | K30: 齊藤
B31: 28 | C31: ドアトリム設計部 | D31: 16116053 | F31: 11367 | G31: SHC部品開発委託 | I31: 12月 | J31: 45267 | K31: 齊藤
B32: 29 | C32: ドアトリム設計部第1ドアトリム設計室 | D32: 16116054 | F32: 11433 | G32: 700W他_号口管理 | I32: 1月 | J32: 45267 | K32: 齊藤
B33: 30 | C33: ドアトリム設計部先行設計室 | D33: 16116055 | F33: 11607 | G33: 競争力BMC | I33: 1月 | J33: 45279 | K33: 齊藤
B34: 31 | C34: ドアトリム設計部先行設計室 | D34: 16116056 | F34: 11607 | G34: 競争力BMC | I34: 2月 | J34: 45303 | K34: 齊藤
B35: 32 | C35: ドアトリム設計部第1ドアトリム設計室 | D35: 16116057 | F35: 11882 | G35: 700W他_号口管理 | I35: 2月 | J35: 45306 | K35: 齊藤
B36: 33 | C36: ドアトリム設計部 | D36: 16116058 | F36: 11960 | G36: SHC部品開発委託 | I36: 2月 | J36: 45323 | K36: 齊藤
B37: 34 | C37: ドアトリム設計部第1ドアトリム設計室 | D37: 16116059 | F37: 120044 | G37: 700W他_号口管理 | I37: 3月 | J37: 45334 | K37: 齊藤
B38: 35 | C38: ドアトリム設計部先行設計室 | D38: 16116060 | F38: 12034 | G38: 競争力BMC | I38: 3月 | J38: 45334 | K38: 齊藤
B39: 36 | C39: ドアトリム設計部 | D39: 16116061 | F39: 12203 | G39: SHC部品開発委託 | I39: 3月 | J39: 45358 | K39: 齊藤
B40: 37 | C40: ドアトリム設計部先行設計室 | D40: 16116062 | F40: ITK12307 | G40: 競争力BMC | I40: 4月 | J40: 45377 | K40: 齊藤
B41: 38 | C41: ドアトリム設計部 | D41: 16116063 | F41: ITK12486 | G41: 700W他_号口管理 | I41: 4月 | J41: 45379 | K41: 齊藤
B42: 39 | C42: ドアトリム設計部 | D42: 16116064 | F42: ITK12598 | G42: 700W他_号口管理 | I42: 5月 | J42: 45397 | K42: 齊藤
B43: 40 | C43: ドアトリム設計部 | D43: 16116065 | F43: ITK12662 | G43: 競争力BMC | I43: 5月 | J43: 45407 | K43: 齊藤
B44: 41 | C44: ドアトリム設計部 | D44: 16116066 | F44: ITK12771 | G44: 700W他_号口管理 | I44: 6月 | J44: 45432 | K44: 齊藤
B45: 42 | C45: ドアトリム設計部 | D45: 16116067 | F45: ITK12828 | G45: 競争力BMC | I45: 6月 | J45: 45432 | K45: 齊藤
B46: 43 | C46: ドアトリム設計部先行設計室 | D46: 16116068 | F46: ITK12992 | G46: 190Dサービスホールカバー | I46: 6月 | J46: 45441 | K46: 齊藤
B47: 44 | C47: ドアトリム設計部 | D47: 16116069 | F47: 13051 | G47: 700W他_号口管理 | I47: 7月 | J47: 45461 | K47: 齊藤
B48: 45 | C48: ドアトリム設計部先行設計室 | D48: 16116070 | F48: 13286 | G48: 190Dサービスホールカバー | I48: 7月 | J48: 45470 | K48: 齊藤
B49: 46 | C49: ドアトリム設計部 | D49: 16116071 | F49: 13287 | G49: 競争力BMC | I49: 7月 | J49: 45470 | K49: 齊藤
B50: 47 | C50: ドアトリム設計部 | D50: 16116072 | F50: 13363 | G50: 700W他_号口管理 | I50: 8月 | J50: 45489 | K50: 齊藤
B51: 48 | C51: ドアトリム設計部先行設計室 | D51: 16116073 | F51: 13414 | G51: 190Dサービスホールカバー | I51: 8月 | J51: 45489 | K51: 齊藤
B52: 49 | C52: ドアトリム設計部 | D52: 16116074 | F52: 13415 | G52: 競争力BMC | I52: 8月 | J52: 45500 | K52: 齊藤
B53: 50 | C53: ドアトリム設計部 | D53: 16116075 | F53: 13772 | G53: 競争力BMC | I53: 9月 | J53: '24/8/21 | K53: 齊藤
B54: 51 | C54: ドアトリム設計部 | D54: 16116076 | F54: 13670 | G54: 700W他_号口管理 | I54: 9月 | J54: '24/8/21 | K54: 齊藤
B55: 52 | C55: ドアトリム設計部 | D55: 16116077 | F55: 14030 | G55: 競争力BMC | I55: 10月 | J55: '24/9/20 | K55: 久目形
B56: 53 | C56: ドアトリム設計部 | D56: 16116078 | F56: 13884 | G56: 700W他_号口管理 | I56: 10月 | J56: '24/9/20 | K56: 久目形
B57: 54 | C57: ドアトリム設計部 | D57: 16116079 | F57: 14240 | G57: 競争力BMC | I57: 11月 | J57: '24/10/23 | K57: 久目形
B58: 55 | C58: ドアトリム設計部 | D58: 16116080 | F58: 14205 | G58: 700W他_号口管理 | I58: 11月 | J58: '24/10/23 | K58: 久目形
B59: 56 | C59: ドアトリム設計部 | D59: 16116081 | F59: 14425 | G59: 700W他_号口管理 | I59: 12月 | J59: '24/11/26 | K59: 久目形
B60: 57 | C60: ドアトリム設計部 | D60: 16116082 | F60: 14657 | G60: 競争力BMC | I60: 12月 | J60: '24/11/29 | K60: 久目形
B61: 58 | C61: ドアトリム設計部 | D61: 16116083 | F61: 14728 | G61: 700W他_号口管理 | I61: 1月 | J61: 45645 | K61: 久目形
B62: 59 | C62: ドアトリム設計部 | D62: 16116084 | F62: 14889 | G62: 競争力BMC | I62: 1月 | J62: 45645 | K62: 久目形
B63: 60 | C63: ドアトリム設計部 | D63: 16116085 | F63: 15026 | G63: 競争力BMC | I63: 2月 | J63: 2025/1/29 | K63: 久目形
B64: 61 | C64: ドアトリム設計部 | D64: 16116086 | F64: 15122 | G64: 700W他_号口管理 | I64: 2月 | J64: 2025/1/29 | K64: 久目形
B65: 62 | C65: ドアトリム設計部 | D65: 16116087 | F65: 15217 | G65: 700W他_号口管理 | I65: 3月 | J65: 2025/2/19 | K65: 久目形
B66: 63 | C66: ドアトリム設計部 | D66: 16116088 | F66: 15173 | G66: 競争力BMC | I66: 3月 | J66: 2025/2/19 | K66: 久目形
B67: 64 | C67: ドアトリム設計部 | D67: 16116089 | F67: ITK15495 | G67: 700W他_号口管理 | I67: 4月 | J67: 45743 | K67: 丸山
B68: 65 | C68: ドアトリム設計部 | D68: 16116090 | F68: ITK15645 | G68: 競争力BMC | I68: 4月 | J68: 45743 | K68: 丸山
B69: 66 | C69: ドアトリム設計部 | D69: 16116091 | F69: 15714 | G69: 700W他_号口管理 | I69: 5月 | J69: 45763 | K69: 丸山
B70: 67 | C70: ドアトリム設計部 | D70: 16116092 | F70: 15715 | G70: 競争力BMC | I70: 5月 | J70: 45763 | K70: 丸山
B71: 68 | C71: ドアトリム設計部 | D71: 16116093 | F71: ITK16141 | G71: 700W他_号口管理 | I71: 6月 | J71: 45791 | K71: 丸山
B72: 69 | C72: ドアトリム設計部 | D72: 16116094 | F72: ITK16004 | G72: 競争力BMC | I72: 6月 | J72: 45791 | K72: 丸山
B73: 70 | C73: ドアトリム設計部 | D73: 16116095 | F73: 16301 | G73: 700W他_号口管理 | I73: 7月 | J73: 45834 | K73: 久目形
B74: 71 | C74: ドアトリム設計部 | D74: 16116096 | F74: 16277 | G74: 競争力BMC | I74: 7月 | J74: 45834 | K74: 久目形
B75: 72 | C75: ドアトリム設計部 | D75: 16116097 | F75: 16619 | G75: 700W他_号口管理 | I75: 8月 | J75: 45861 | K75: 久目形
B76: 73 | C76: ドアトリム設計部 | D76: 16116098 | F76: 16620 | G76: 競争力BMC | I76: 8月 | J76: 45861 | K76: 久目形
B77: 74 | C77: ドアトリム設計部 | D77: 16116099 | F77: 17048 | G77: 700W他_号口管理 | I77: 9月 | J77: 45889 | K77: 久目形
B78: 75 | C78: ドアトリム設計部 | D78: 16116100 | F78: 17047 | G78: 競争力BMC | I78: 9月 | J78: 45889 | K78: 久目形
B79: 76 | C79: ドアトリム設計部 | D79: 16116101 | F79: 17170 | G79: 700W他_号口管理 | I79: 10月 | J79: 45916 | K79: 久目形
B80: 77 | C80: ドアトリム設計部 | D80: 16116102 | F80: 17173 | G80: 競争力BMC | I80: 10月 | J80: 45916 | K80: 久目形
B81: 78 | C81: ドアトリム設計部 | D81: 16116103 | F81: 17440 | G81: 700W他_号口管理 | I81: 11月 | J81: 45946 | K81: 久目形
B82: 79 | C82: ドアトリム設計部 | D82: 16116104 | F82: 17434 | G82: 競争力BMC | I82: 11月 | J82: 45946 | K82: 久目形
B83: 80 | C83: ドアトリム設計部 | D83: 16116105 | F83: 17782 | G83: 700W他_号口管理 | I83: 12月 | J83: 45975 | K83: 久目形
B84: 81 | C84: ドアトリム設計部 | D84: 16116106 | F84: 17803 | G84: 競争力BMC | I84: 12月 | J84: 45975 | K84: 久目形
B85: 82 | C85: ドアトリム設計部 | D85: 16116107 | F85: 18126 | G85: 700W他_号口管理 | I85: １月 | J85: 46008 | K85: 久目形
B86: 83 | D86: 16116108

Sheet ACT
A1: 2024年 | C1: エンジニアリングサービス部 見積書・請求書発行管理台帳 | H1: 見積書(税抜金額)
A2: 企業名： | C2: トヨタ紡織(株)
A3: タスク | B3: No | C3: 部署名 | D3: 見積/請求番号 | E3: 発注番号 | F3: 業務計画書No | G3: 案件名 | H3: 見積金額 | I3: 見積月 | J3: 発行日 | K3: 発行者 | L3: 備考
A4: 完了 | B4: 1 | C4: ACT事業室 | D4: 16118008 | E4: 802-2212-0096-000 | F4: 8141 | G4: 航空機シート | I4: 1月 | J4: 44923 | K4: 鈴木
A5: 完了 | B5: 2 | C5: ACT事業室 | D5: 16118009 | E5: 802-2301-0094-000 | F5: 8398 | G5: 航空機シート | I5: 2月 | J5: 44965 | K5: 鈴木
A6: 完了 | B6: 3 | C6: ACT事業室 | D6: 16118010 | F6: 8735 | G6: 航空機シート | I6: 3月 | J6: 44994 | K6: 鈴木
A7: 完了 | B7: 4 | C7: ACT事業室 | D7: 16118011 | F7: 9031 | G7: 航空機シート | I7: 4月 | J7: 45016 | K7: 鈴木
A8: 完了 | B8: 5 | C8: ACT事業室 | D8: 16118012 | F8: 9352 | G8: 航空機シート | I8: 5月 | J8: 45044 | K8: 鈴木
A9: 完了 | B9: 6 | C9: ACT事業室 | D9: 16118013 | F9: 9520 | G9: 航空機シート | I9: 6月 | J9: 45078 | K9: 鈴木
A10: 完了 | B10: 7 | C10: ACT事業室 | D10: 16118014 | F10: 9880 | G10: 航空機シート | I10: 7月 | J10: 45103 | K10: 鈴木
A11: 完了 | B11: 8 | C11: ACT事業室 | D11: 16118015 | F11: 10208 | G11: 航空機シート | I11: 8月 | J11: 45128 | K11: 鈴木
A12: 完了 | B12: 9 | C12: ACT事業室 | D12: 16118016 | F12: 10439 | G12: 航空機シート | I12: 9月 | J12: 45160 | K12: 鈴木
A13: 完了 | B13: 10 | C13: ACT事業室 | D13: 16118017 | F13: 10611 | G13: 航空機シート | I13: 10月 | J13: 45198 | K13: 齊藤
A14: 進行中 | B14: 11 | C14: ACT事業室 | D14: 16118018 | F14: 11000 | G14: 航空機シート | I14: 11月 | J14: 45225 | K14: 齊藤
B15: 12 | C15: ACT事業室 | D15: 16118019 | F15: 11322 | G15: 航空機シート | I15: 12月 | J15: 45221 | K15: 齊藤
B16: 13 | C16: ACT事業室 | D16: 16118020 | F16: ITK11574 | G16: 航空機シート | I16: 1月 | J16: 45275 | K16: 齊藤
B17: 14 | C17: ACT事業室 | D17: 16118021 | F17: 11818 | G17: 航空機シート | I17: 2月 | J17: 45310 | K17: 齊藤 | L17: 金額変更により取り消し（No,16）
B18: 15 | C18: ACT事業室 | D18: 16118022 | F18: 12146 | G18: 航空機シート | I18: 3月 | J18: 45337 | K18: 齊藤
B19: 16 | C19: ACT事業室 | D19: 16118023 | F19: 11818 | G19: 航空機シート | I19: 2月 | J19: 45341 | K19: 齊藤 | L19: No,14の再見積もり（工数変更による金額変更）
B20: 17 | C20: ACT事業室 | D20: 16118024 | F20: ITK12428 | G20: 航空機シート | I20: 4月 | J20: 45377 | K20: 齊藤
B21: 18 | C21: ACT事業部 | D21: 16118025 | F21: ITK12682 | G21: 航空機シート | I21: 5月 | J21: 45401 | K21: 齊藤
B22: 19 | C22: ACT事業部 | D22: 16118026 | F22: ITK12931 | G22: 航空機シート | I22: 6月 | J22: 45433 | K22: 齊藤
B23: 20 | C23: ACT事業部 | D23: 16118027 | F23: 13259 | G23: 航空機シート | I23: 7月 | J23: 45467 | K23: 齊藤
B24: 21 | C24: ACT事業部 | D24: 16118028 | F24: 13561 | G24: 航空機シート | I24: 8月 | J24: '24/7/16 | K24: 齊藤
B25: 22 | C25: ACT事業部 | D25: 16118029 | F25: 13835 | G25: 航空機シート | I25: 9月 | J25: '24/9/2 | K25: 齊藤
B26: 23 | C26: ACT事業部 | D26: 16118030 | F26: 14067 | G26: 航空機シート | I26: 10月 | J26: '24/10/3 | K26: 久目形
B27: 24 | C27: ACT事業部 | D27: 16118032 | F27: 14359 | G27: 航空機シート | I27: 11月 | J27: '24/11/1 | K27: 久目形
B28: 25 | C28: ACT事業部 | D28: 16118033 | F28: 14582 | G28: 航空機シート | I28: 12月 | J28: '24/11/26 | K28: 久目形
B29: 26 | C29: ACT事業部 | D29: 16118034 | F29: 14896 | G29: 航空機シート | I29: 1月 | J29: 45645 | K29: 久目形
B30: 27 | C30: ACT事業部 | D30: 16118035 | F30: 15156 | G30: 航空機シート | I30: 2月 | J30: 2025/1/29 | K30: 久目形
B31: 28 | C31: ACT事業部 | D31: 16118036 | F31: 15392 | G31: 航空機シート | I31: 3月 | J31: 2025/2/26 | K31: 久目形
B32: 29 | D32: 16118037
B33: 30 | D33: 16118038
B34: 31 | D34: 16118039
B35: 32 | D35: 16118040
B36: 33 | D36: 16118041
B37: 34 | D37: 16118042
B38: 35 | D38: 16118043
B39: 36 | D39: 16118044
B40: 37 | D40: 16118045
B41: 38 | D41: 16118046
B42: 39 | D42: 16118047
B43: 40 | D43: 16118048
... B120: 117 | D120: 16118125

Sheet NT
A1: 2024年 | C1: エンジニアリングサービス部 見積書・請求書発行管理台帳 | H1: 見積書(税抜金額)
A2: 企業名： | C2: トヨタ紡織(株)
A3: タスク | B3: No | C3: 部署名 | D3: 見積/請求番号 | E3: 発注番号 | F3: 業務計画書No | G3: 案件名 | H3: 見積金額 | I3: 見積月 | J3: 発行日 | K3: 発行者 | L3: 備考
A4: 完了 | B4: 1 | C4: 内外装トリム設計部第３トリム設計室 | D4: 16112041 | E4: A93-2212-0009-000 | F4: ITK08246 | G4: 200D | I4: 1月 | J4: 44916 | K4: 鈴木
A5: 完了 | B5: 2 | C5: 内外装トリム設計部第３トリム設計室 | D5: 16112042 | E5: A93-2212-0013-000 | F5: ITK08244 | G5: 設計支援 | I5: 1月 | J5: 44916 | K5: 鈴木
A6: 完了 | B6: 3 | C6: 内外装トリム設計部第３トリム設計室 | D6: 16112043 | E6: A93-2301-0001-000 | F6: 8501 | G6: 263D | I6: 1月 | J6: 44944 | K6: 鈴木
A7: 完了 | B7: 4 | C7: 内外装トリム設計部第３トリム設計室 | D7: 16112044 | E7: A93-2301-0006-000 | F7: 8530 | G7: 200D | I7: 2月 | J7: 44950 | K7: 鈴木
A8: 完了 | B8: 5 | C8: 内外装トリム設計部第３トリム設計室 | D8: 16112045 | E8: A93-2301-0009-000 | F8: 8531 | G8: 設計支援 | I8: 2月 | J8: 44950 | K8: 鈴木
A9: 完了 | B9: 6 | C9: 内外装トリム設計部第３トリム設計室 | D9: 16112046 | E9: A93-2302-0012-000 | F9: 8774 | G9: 設計支援 | I9: 3月 | J9: 44977 | K9: 鈴木
A10: 完了 | B10: 7 | C10: 内外装トリム設計部第３トリム設計室 | D10: 16112047 | E10: A93-2302-0008-000 | F10: 8788 | G10: 200D | I10: 3月 | J10: 44992 | K10: 鈴木
A11: 完了 | B11: 8 | C11: 内外装トリム設計部第３トリム設計室 | D11: 16112048 | F11: 9066 | G11: 設計支援 | I11: 4月 | J11: 45016 | K11: 鈴木
A12: 完了 | B12: 9 | C12: 内外装トリム設計部第３トリム設計室 | D12: 16112049 | F12: 9358 | G12: 設計支援 | I12: 5月 | J12: 45040 | K12: 鈴木
A13: 完了 | B13: 10 | C13: 内外装トリム設計部第３トリム設計室 | D13: 16112050 | F13: 9607 | G13: 設計支援 | I13: 6月 | J13: 45071 | K13: 鈴木
A14: 完了 | B14: 11 | C14: 内外装トリム設計部第３トリム設計室 | D14: 16112051 | F14: 9904 | G14: 設計支援 | I14: 7月 | J14: 45099 | K14: 鈴木
A15: 完了 | B15: 12 | C15: 内外装トリム設計部第３トリム設計室 | D15: 16112052 | F15: 10182 | G15: 設計支援 | I15: 8月 | J15: 45126 | K15: 鈴木
A16: 完了 | B16: 13 | C16: 内外装トリム設計部第３トリム設計室 | D16: 16112053 | F16: 10462 | G16: 設計支援 | I16: 9月 | J16: 45167 | K16: 鈴木
A17: 完了 | B17: 14 | C17: 内外装トリム設計部第３トリム設計室 | D17: 16112054 | F17: 10769 | G17: 設計支援 | I17: 10月 | J17: 45196 | K17: 齊藤
A18: 完了 | B18: 15 | C18: 内外装トリム設計部第３トリム設計室 | D18: 16112055 | F18: 11061 | G18: 設計支援 | I18: 11月 | J18: 45225 | K18: 齊藤
A19: 完了 | B19: 16 | C19: 内外装トリム設計部第３トリム設計室 | D19: 16112056 | F19: 11328 | G19: 設計支援 | I19: 12月 | J19: 45254 | K19: 齊藤
B20: 17 | C20: 内外装トリム設計部第３トリム設計室 | D20: 16112057 | F20: 11605 | G20: 設計支援 | I20: 1月 | J20: 45279 | K20: 齊藤
B21: 18 | C21: 内外装トリム設計部第３トリム設計室 | D21: 16112058 | F21: 11904 | G21: 設計支援 | I21: 2月 | J21: 45310 | K21: 齊藤
B22: 19 | C22: 内外装トリム設計部第３トリム設計室 | D22: 16112059 | F22: 12154 | G22: 設計支援 | I22: 3月 | J22: 45345 | K22: 齊藤
B23: 20 | C23: 内外装トリム設計部第３トリム設計室 | D23: 16112060 | F23: ITK12414 | G23: 設計支援 | I23: 4月 | J23: 45377 | K23: 齊藤
B24: 21 | C24: 内外装トリム設計部第３トリム設計室 | D24: 16112061 | F24: ITK12747 | G24: 設計支援 | I24: 5月 | J24: 45407 | K24: 齊藤
B25: 22 | C25: 内外装トリム設計部第３トリム設計室 | D25: 16112062 | F25: ITK12999 | G25: 設計支援 | I25: 6月 | J25: 45435 | K25: 齊藤
B26: 23 | C26: 内外装トリム設計部第３トリム設計室 | D26: 16112063 | F26: TBN-24-003 | G26: 設計標準化業務 | I26: 6月 | J26: 24/5/28 | K26: 齊藤
B27: 24 | C27: 内外装トリム設計部第３トリム設計室 | D27: 16112064 | F27: ITK13033 | G27: 400D | I27: 6月 | J27: 24/5/31 | K27: 齊藤
B28: 25 | C28: 内外装トリム設計部第３トリム設計室 | D28: 16112065 | F28: TBN-24-004 | G28: 設計標準化業務 | I28: 7月 | J28: 24/6/17 | K28: 齊藤
B29: 26 | C29: 内外装トリム設計部第３トリム設計室 | D29: 16112066 | F29: 13295 | G29: 設計支援 | I29: 7月 | J29: 45464 | K29: 齊藤
B30: 27 | C30: 内外装トリム設計部第３トリム設計室 | D30: 16112067 | F30: 13311 | G30: 400D | I30: 7月 | J30: 45470 | K30: 齊藤
B31: 28 | C31: 内外装トリム設計部第３トリム設計室 | D31: 16112068 | F31: 13578 | G31: 設計支援 | I31: 8月 | J31: '24/7/18 | K31: 齊藤
B32: 29 | C32: 内外装トリム設計部第３トリム設計室 | D32: 16112069 | F32: 13580 | G32: 400D | I32: 8月 | J32: '24/7/18 | K32: 齊藤
B33: 30 | C33: 内外装トリム設計部第３トリム設計室 | D33: 16112070 | F33: TBN-24-008 | G33: 設計標準化業務 | I33: 8月 | J33: '24/7/22 | K33: 齊藤
B34: 31 | C34: 内外装トリム設計部第３トリム設計室 | D34: 16112071 | F34: 13797 | G34: 190D | I34: 8月 | J34: '24/8/8 | K34: 齊藤
B35: 32 | C35: 内外装トリム設計部第３トリム設計室 | D35: 16112072 | F35: 13828 | G35: 400D | I35: 9月 | J35: '24/8/23 | K35: 齊藤
B36: 33 | C36: 内外装トリム設計部第３トリム設計室 | D36: 16112073 | F36: 13829 | G36: 設計支援 | I36: 9月 | J36: '24/8/23 | K36: 齊藤
B37: 34 | C37: 内外装トリム設計部第３トリム設計室 | D37: 16112074 | F37: TBN-24-008 | G37: 設計標準化業務 | I37: 9月 | J37: '24/8/23 | K37: 齊藤
B38: 35 | C38: 内外装トリム設計部第３トリム設計室 | D38: 16112075 | F38: 13904 | G38: 190D | I38: 9月 | J38: '24/9/6 | K38: 久目形
B39: 36 | C39: 内外装トリム設計部第３トリム設計室 | D39: 16112076 | F39: TBN-24-013 | G39: 設計標準化業務 | I39: 10月 | J39: '24/9/20 | K39: 久目形
B40: 37 | C40: 内外装トリム設計部第３トリム設計室 | D40: 16112077 | F40: 14115 | G40: 400D | I40: 10月 | J40: '24/9/20 | K40: 久目形
B41: 38 | C41: 内外装トリム設計部第３トリム設計室 | D41: 16112078 | F41: 14121 | G41: 設計支援 | I41: 10月 | J41: '24/9/20 | K41: 久目形
B42: 39 | C42: 内外装トリム設計部第３トリム設計室 | D42: 16112079 | F42: 14383 | G42: 設計支援 | I42: 11月 | J42: '24/10/23 | K42: 久目形
B43: 40 | C43: 内外装トリム設計部第３トリム設計室 | D43: 16112080 | F43: 14380 | G43: 400D | I43: 11月 | J43: '24/10/23 | K43: 久目形
B44: 41 | C44: 内外装トリム設計部第３トリム設計室 | D44: 16112081 | F44: TBN-24-015 | G44: 設計標準化業務 | I44: 11月 | J44: '24/10/23 | K44: 久目形
B45: 42 | C45: 内外装トリム設計部第３トリム設計室 | D45: 16112082 | F45: 14454 | G45: 650D 内装設計 | I45: 11月 | J45: '24/11/12 | K45: 久目形
B46: 43 | C46: 内外装トリム設計部第３トリム設計室 | D46: 16112083 | F46: TBN-24-019 | G46: 設計標準化業務 | I46: 12月 | J46: '24/11/18 | K46: 久目形
B47: 44 | C47: 内外装トリム設計部第３トリム設計室 | D47: 16112084 | F47: 14611 | G47: 設計支援 | I47: 12月 | J47: '24/11/26 | K47: 久目形
B48: 45 | C48: 内外装トリム設計部第３トリム設計室 | D48: 16112085 | F48: 14610 | G48: 400D | I48: 12月 | J48: '24/11/26 | K48: 久目形
B49: 46 | C49: 内外装トリム設計部第３トリム設計室 | D49: 16112086 | F49: 14770 | G49: 650D 内装設計 | I49: 12月 | J49: '24/12/4 | K49: 久目形
B50: 47 | C50: 内外装トリム設計部第３トリム設計室 | D50: 16112087 | F50: 14925 | G50: 設計支援 | I50: 1月 | J50: 2024/12/24 | K50: 久目形
B51: 48 | C51: 内外装トリム設計部第３トリム設計室 | D51: 16112088 | F51: 14904 | G51: 650D 内装設計 | I51: 1月 | J51: 2024/12/24 | K51: 久目形
B52: 49 | C52: 内外装トリム設計部第３トリム設計室 | D52: 16112089 | F52: TBN-24-021 | G52: 設計標準化業務 | I52: 1月 | J52: 2025/1/9 | K52: 久目形
B53: 50 | C53: 内外装トリム設計部第３トリム設計室 | D53: 16112090 | F53: TBN-24-023 | G53: 設計標準化業務 | I53: 2月 | J53: 2025/1/22 | K53: 久目形
B54: 51 | C54: 内外装トリム設計部第３トリム設計室 | D54: 16112091 | F54: 15145 | G54: 設計支援 | I54: 2月 | J54: 202/2/29 | K54: 久目形
B55: 52 | C55: 内外装トリム設計部第３トリム設計室 | D55: 16112092 | F55: 15144 | G55: 650D 内装設計 | I55: 2月 | J55: 202/2/29 | K55: 久目形
B56: 53 | C56: 内外装トリム設計部第３トリム設計室 | D56: 16112093 | F56: TBN-24-025 | G56: 設計標準化業務 | I56: 3月 | J56: 2025/2/18 | K56: 久目形
B57: 54 | C57: 内外装トリム設計部第３トリム設計室 | D57: 16112094 | F57: 15373 | G57: 設計支援 | I57: 3月 | J57: 2025/2/19 | K57: 久目形
B58: 55 | C58: 内外装トリム設計部第３トリム設計室 | D58: 16112095 | F58: 15372 | G58: 650D 内装設計 | I58: 3月 | J58: 2025/2/19 | K58: 久目形
B59: 56 | C59: 内外装トリム設計部第３トリム設計室 | D59: 16112096 | F59: TBN-24-028 | G59: 設計標準化業務 | I59: 4月 | J59: 2025/3/25 | K59: 久目形
B60: 57 | C60: 内外装トリム設計部 | D60: 16112097 | G60: QTRトリム設計 | I60: 4月 | J60: 45743 | K60: 丸山
B61: 58 | C61: 内外装トリム設計部第３トリム設計室 | D61: 16112098 | F61: ITK15582 | G61: 設計支援 | I61: 4月 | J61: 45743 | K61: 丸山
B62: 59 | C62: 内外装トリム設計部第３トリム設計室 | D62: 16112099 | F62: ITK15586 | G62: 650D 内装設計 | I62: 4月 | J62: 45743 | K62: 丸山
B63: 60 | C63: 内外装トリム設計部第３トリム設計室 | D63: 16112100 | F63: TBN-25-003 | G63: 設計標準化業務 | I63: 5月 | J63: 45763 | K63: 丸山
B64: 61 | C64: 内外装トリム設計部第３トリム設計室 | D64: 16112101 | F64: 15941 | G64: 650D 内装設計 | I64: 5月 | J64: 45769 | K64: 丸山
B65: 62 | C65: 内外装トリム設計部標準化推進室 | D65: 16112102 | F65: 15942 | G65: 設計支援 | I65: 5月 | J65: 45769 | K65: 丸山
B66: 63 | C66: 内外装トリム設計部標準化推進室 | D66: 16112103 | F66: TBN-25-005 | G66: 設計標準化業務 | I66: 6月 | J66: 45792 | K66: 丸山
B67: 64 | C67: 内外装トリム設計部第３トリム設計室 | D67: 16112104 | F67: 16225 | G67: 650D 内装設計 | I67: 6月 | J67: 45799 | K67: 丸山
B68: 65 | C68: 内外装トリム設計部第３トリム設計室 | D68: 16112105 | F68: 16226 | G68: 450D 内装設計 | I68: 6月 | J68: 45799 | K68: 丸山
B69: 66 | C69: 内外装トリム設計部標準化推進室 | D69: 16112106 | F69: 16209 | G69: 設計支援 | I69: 6月 | J69: 45799 | K69: 丸山
B70: 67 | C70: 内外装トリム設計部標準化推進室 | D70: 16112107 | F70: TBN-25-008 | G70: 設計標準化業務 | I70: 7月 | J70: 45824 | K70: 久目形
B71: 68 | C71: 内外装トリム設計部第2トリム設計室 | D71: 16112108 | F71: 16517 | G71: 070D 開発PJT | I71: 7月 | J71: 45834 | K71: 久目形
B72: 69 | C72: 内外装トリム設計部標準化推進室 | D72: 16112109 | F72: 16508 | G72: 設計支援 | I72: 7月 | J72: 45834 | K72: 久目形
B73: 70 | C73: 内外装トリム設計部第３トリム設計室 | D73: 16112110 | F73: 16447 | G73: 450D 内装設計 | I73: 7月 | J73: 45834 | K73: 久目形
B74: 71 | C74: 内外装トリム設計部第３トリム設計室 | D74: 16112111 | F74: 16443 | G74: 650D 内装設計 | I74: 7月 | J74: 45834 | K74: 久目形
B75: 72 | C75: 内外装トリム設計部標準化推進室 | D75: 16112112 | F75: TBN-25-011 | G75: 設計標準化業務 | I75: 8月 | J75: 45855 | K75: 久目形
B76: 73 | C76: 内外装トリム設計部標準化推進室 | D76: 16112113 | F76: TBN-25-013 | G76: 設計標準化業務 | I76: 8月 | J76: 45855 | K76: 久目形
B77: 74 | C77: 内外装トリム設計部第2トリム設計室 | D77: 16112114 | F77: 16806 | G77: 070D 開発PJT | I77: 8月 | J77: 45861 | K77: 久目形
B78: 75 | C78: 内外装トリム設計部第３トリム設計室 | D78: 16112115 | F78: 16810 | G78: 設計支援 | I78: 8月 | J78: 45861 | K78: 久目形
B79: 76 | C79: 内外装トリム設計部第３トリム設計室 | D79: 16112116 | F79: 16815 | G79: 450D 内装設計 | I79: 8月 | J79: 45861 | K79: 久目形
B80: 77 | C80: 内外装トリム設計部第1トリム設計室 | D80: 16112117 | F80: 16822 | G80: 740D 内装設計 | I80: 8月 | J80: 45863 | K80: 久目形
B81: 78 | C81: 内外装トリム設計部標準化推進室 | D81: 16112118 | F81: TBN-25-015 | G81: 設計標準化業務 | I81: 9月 | J81: 45887 | K81: 久目形
B82: 79 | C82: 内外装トリム設計部標準化推進室 | D82: 16112119 | F82: TBN-25-016 | G82: 設計標準化業務 | I82: 9月 | J82: 45887 | K82: 久目形
B83: 80 | C83: 内外装トリム設計部第３トリム設計室 | D83: 16112120 | F83: 17063 | G83: 設計支援 | I83: 9月 | J83: 45889 | K83: 久目形
B84: 81 | C84: 内外装トリム設計部第３トリム設計室 | D84: 16112121 | F84: 17062 | G84: 450D 内装設計 | I84: 9月 | J84: 45889 | K84: 久目形
B85: 82 | C85: 内外装トリム設計部第2トリム設計室 | D85: 16112122 | F85: 17064 | G85: 070D 開発PJT | I85: 9月 | J85: 45894 | K85: 久目形
B86: 83 | C86: 内外装トリム設計部第１トリム設計室 | D86: 16112123 | F86: 17084 | G86: 740D 内装設計 | I86: 9月 | J86: 45894 | K86: 久目形
B87: 84 | C87: 内外装トリム設計部標準化推進室 | D87: 16112124 | F87: TBN-25-018 | G87: 設計標準化業務 | I87: 10月 | J87: 45918 | K87: 久目形
B88: 85 | C88: 内外装トリム設計部第３トリム設計室 | D88: 16112125 | F88: 17345 | G88: 設計支援 | I88: 10月 | J88: 45924 | K88: 久目形
B89: 86 | C89: 内外装トリム設計部第３トリム設計室 | D89: 16112126 | F89: 17346 | G89: 450D 内装設計 | I89: 10月 | J89: 45924 | K89: 久目形
B90: 87 | C90: 内外装トリム設計部第2トリム設計室 | D90: 16112127 | F90: 17375 | G90: 070D 開発PJT | I90: 10月 | J90: 45924 | K90: 久目形
B91: 88 | C91: 内外装トリム設計部第１トリム設計室 | D91: 16112128 | F91: 17376 | G91: 740D 内装設計 | I91: 10月 | J91: 45924 | K91: 久目形
B92: 89 | C92: 内外装トリム設計部標準化推進室 | D92: 16112129 | F92: TBN-25-021 | G92: 設計標準化業務 | I92: 11月 | J92: 45952 | K92: 久目形
B93: 90 | C93: 内外装トリム設計部第３トリム設計室 | D93: 16112130 | F93: 17669 | G93: 設計支援 | I93: 11月 | J93: 45952 | K93: 久目形
B94: 91 | C94: 内外装トリム設計部第３トリム設計室 | D94: 16112131 | F94: 17668 | G94: 450D 内装設計 | I94: 11月 | J94: 45952 | K94: 久目形
B95: 92 | C95: 内外装トリム設計部第2トリム設計室 | D95: 16112132 | F95: 17667 | G95: 070D 開発PJT | I95: 11月 | J95: 45952 | K95: 久目形
B96: 93 | C96: 内外装トリム設計部第１トリム設計室 | D96: 16112133 | F96: 17655 | G96: 740D 内装設計 | I96: 11月 | J96: 45952 | K96: 久目形
B97: 94 | C97: 内外装トリム設計部標準化推進室 | D97: 16112134 | F97: TBN-25-024 | G97: 設計標準化業務 | I97: 12月 | J97: 45975 | K97: 久目形
B98: 95 | C98: 内外装トリム設計部第１トリム設計室 | D98: 16112135 | F98: 17959 | G98: 740D 内装設計 | I98: 12月
B99: 96 | C99: 内外装トリム設計部第３トリム設計室 | D99: 16112136 | F99: 17978 | G99: 設計支援 | I99: 12月
B100: 97 | C100: 内外装トリム設計部第2トリム設計室 | D100: 16112137 | F100: 17963 | G100: 070D 開発PJT | I100: 12月
...

Sheet 内外装先行開発部
A1: 2024年 | C1: エンジニアリングサービス部 見積書・請求書発行管理台帳 | H1: 見積書(税抜金額)
A2: 企業名： | C2: トヨタ紡織(株)
A3: タスク | B3: No | C3: 部署名 | D3: 見積/請求番号 | E3: 発注番号 | F3: 業務計画書No | G3: 案件名 | H3: 見積金額 | I3: 見積月 | J3: 発行日 | K3: 発行者 | L3: 備考
A4: 完了 | B4: 1 | C4: 内外装先行開発部照明開発室 | D4: 16115009 | F4: 9163 | G4: 280Dイルミ | I4: 4月 | J4: 45021 | K4: 鈴木
A5: 完了 | B5: 2 | C5: 内外装先行開発部照明開発室 | D5: 16115010 | F5: 9554 | G5: 280Dイルミ | I5: 5月 | J5: 45062 | K5: 鈴木
A6: 完了 | B6: 3 | C6: 内外装先行開発部照明開発室 | D6: 16115011 | F6: 9629 | G6: 280Dイルミ | I6: 6月 | J6: 45078 | K6: 鈴木
A7: 完了 | B7: 4 | C7: 内外装先行開発部照明開発室 | D7: 16115012 | F7: 9959 | G7: 280Dイルミ | I7: 7月 | J7: 45119 | K7: 鈴木
A8: 完了 | B8: 5 | C8: 内外装先行開発部照明開発室 | D8: 16115013 | F8: 10231 | G8: 280Dイルミ | I8: 8月 | J8: 45148 | K8: 鈴木
A9: 完了 | B9: 6 | C9: 内外装先行開発部照明開発室 | D9: 16115014 | F9: 10482 | G9: 280Dイルミ | I9: 9月 | J9: 45167 | K9: 鈴木
A10: 完了 | B10: 7 | C10: 内外装先行開発部照明開発室 | D10: 16115015 | F10: 10853 | G10: 280Dイルミ | I10: 10月 | J10: 45198 | K10: 齊藤
A11: 完了 | B11: 8 | C11: 内外装先行開発部照明開発室 | D11: 16115016 | F11: 11092 | G11: 280Dイルミ | I11: 11月 | J11: 45236 | K11: 齊藤
A12: 完了 | B12: 9 | C12: 内外装先行開発部照明開発室 | D12: 16115017 | F12: ITK11380 | G12: 280Dイルミ | I12: 12月 | J12: 45275 | K12: 齊藤
B13: 10 | C13: 内外装先行開発部照明開発室 | D13: 16115018 | F13: ITK11372 | G13: 650Dイルミ | I13: 12月 | J13: 45278 | K13: 齊藤
B14: 11 | C14: 内外装先行開発部照明開発室 | D14: 16115019 | F14: 11693 | G14: 280Dイルミ | I14: 1月 | J14: 45287 | K14: 齊藤
B15: 12 | C15: 内外装先行開発部照明開発室 | D15: 16115020 | F15: 11698 | G15: 650Dイルミ | I15: 1月 | J15: 45287 | K15: 齊藤
B16: 13 | C16: 内外装先行開発部照明開発室 | D16: 16115021 | F16: 11930 | G16: 650Dイルミ | I16: 2月 | J16: 45323 | K16: 齊藤
B17: 14 | C17: 内外装先行開発部照明開発室 | D17: 16115022 | F17: 12190 | G17: 650Dイルミ | I17: 3月 | J17: 45349 | K17: 齊藤
B18: 15 | C18: 内外装先行開発部照明開発室 | D18: 16115023 | F18: ITK12758 | G18: 650Dイルミ | I18: 5月 | J18: 45407 | K18: 齊藤
B19: 16 | C19: ドアトリム設計部照明設計室 | D19: 16115024 | F19: ITK12846 | G19: 650Dイルミ | I19: 6月 | J19: 45432 | K19: 齊藤
B20: 17 | C20: ドアトリム設計部照明設計室 | D20: 16115025 | F20: 13272 | G20: 650Dイルミ | I20: 7-8月 | J20: 45470 | K20: 齊藤
B21: 18 | C21: ドアトリム設計部照明設計室 | D21: 16115026 | F21: 13767 | G21: 650Dイルミ | I21: 9月 | J21: '24/8/21 | K21: 齊藤
B22: 19 | C22: ドアトリム設計部照明設計室 | D22: 16115027 | F22: 14031 | G22: 650Dイルミ | I22: 10月 | J22: '24/9/20 | K22: 久目形
B23: 20 | C23: ドアトリム設計部照明設計室 | D23: 16115028 | F23: 14309 | G23: 650Dイルミ | I23: 11月 | J23: '24/10/23 | K23: 久目形
B24: 21 | C24: ドアトリム設計部照明設計室 | D24: 16115029 | F24: 14480 | G24: 650Dイルミ | I24: 12月 | J24: '24/11/26 | K24: 久目形
B25: 22 | C25: ドアトリム設計部照明設計室 | D25: 16115030 | F25: 14760 | G25: 650Dイルミ | I25: 1月 | J25: 45645 | K25: 久目形
B26: 23 | C26: ドアトリム設計部照明設計室 | D26: 16115031 | F26: 15103 | G26: 650Dイルミ | I26: 2月 | J26: 202/2/29 | K26: 久目形
B27: 24 | C27: ドアトリム設計部照明設計室 | D27: 16115032 | F27: 15224 | G27: 650Dイルミ | I27: 3月 | J27: 2025/2/19 | K27: 久目形
B28: 25 | C28: ドアトリム設計部照明設計室 | D28: 16115033 | F28: ITK15502 | G28: 650Dイルミ | I28: 4月 | J28: 45743 | K28: 丸山
B29: 26 | D29: 16115034
B30: 27 | D30: 16115035
B31: 28 | D31: 16115036
B32: 29 | D32: 16115037
B33: 30 | D33: 16115038
B34: 31 | D34: 16115039
B35: 32 | D35: 16115040
B36: 33 | D36: 16115041
B37: 34 | D37: 16115042
B38: 35 | D38: 16115043
B39: 36 | D39: 16115044
B40: 37 | D40: 16115045
... B50: 47 | D50: 16115055

Sheet 内外装実験部
A1: 2024年 | C1: エンジニアリングサービス部 見積書・請求書発行管理台帳 | H1: 見積書(税抜金額)
A2: 企業名： | C2: トヨタ紡織(株)
A3: タスク | B3: No | C3: 部署名 | D3: 見積/請求番号 | E3: 発注番号 | F3: 業務計画書No | G3: 案件名 | H3: 見積金額 | I3: 見積月 | J3: 発行日 | K3: 発行者 | L3: 備考
B4: 1 | C4: 内外装事業本部 内外装実験部 | D4: 16111001 | G4: CAE用物性データ変換 | I4: 1月 | J4: 45308 | K4: 齊藤
B5: 2 | C5: 内外装事業本部 内外装実験部 | D5: 16111002 | G5: CAE用物性データ変換 | I5: 3月 | J5: 45342 | K5: 齊藤
B6: 3 | D6: 16111003
B7: 4 | D7: 16111004
B8: 5 | D8: 16111005
B9: 6 | D9: 16111006
B10: 7 | D10: 16111007
B11: 8 | D11: 16111008
B12: 9 | D12: 16111009
B13: 10 | D13: 16111010
B14: 11 | D14: 16111011
B15: 12 | D15: 16111012
B16: 13 | D16: 16111013
B17: 14 | D17: 16111014
... B50: 47 | D50: 16111047

Sheet SH→設計品質改善室
A1: 2024年 | C1: エンジニアリングサービス部 見積書・請求書発行管理台帳 | H1: 見積書(税抜金額)
A2: 企業名： | C2: トヨタ紡織(株)
A3: タスク | B3: No | C3: 部署名 | D3: 見積/請求番号 | E3: 発注番号 | F3: 業務計画書No | G3: 案件名 | H3: 見積金額 | I3: 見積月 | J3: 発行日 | K3: 発行者 | L3: 備考
A4: 完了 | B4: 1 | C4: シートホーム推進部 | D4: 16120016 | E4: SQ2021-0062 | F4: - | G4: 品質監査業務支援 | I4: 1月 | J4: 44903 | K4: 鈴木
A5: 完了 | B5: 2 | C5: シートホーム推進部 | D5: 16120017 | E5: SQ2021-0061 | F5: - | G5: 設計品質改善会 | I5: 1月 | J5: 44903 | K5: 鈴木
A6: 完了 | B6: 3 | C6: シートホーム推進部 | D6: 16120018 | E6: SQ2021-0067 | F6: - | G6: 品質監査業務支援 | I6: 2月 | J6: 44937 | K6: 鈴木
A7: 完了 | B7: 4 | C7: シートホーム推進部 | D7: 16120019 | E7: SQ2021-0066 | F7: - | G7: 設計品質改善会 | I7: 2月 | J7: 44937 | K7: 鈴木
A8: 完了 | B8: 5 | C8: シートホーム推進部 | D8: 16120020 | F8: - | G8: 品質監査業務支援 | I8: 3月 | J8: 44966 | K8: 鈴木
A9: 完了 | B9: 6 | C9: シートホーム推進部 | D9: 16120021 | F9: - | G9: 設計品質改善会 | I9: 3月 | J9: 44966 | K9: 鈴木
A10: 完了 | B10: 7 | C10: シートホーム推進部 | D10: 16120022 | F10: - | G10: 品質監査業務支援 | I10: 4月 | J10: 44999 | K10: 鈴木
A11: 完了 | B11: 8 | C11: シートホーム推進部 | D11: 16120023 | F11: - | G11: 設計品質改善会 | I11: 4月 | J11: 44999 | K11: 鈴木
A12: 完了 | B12: 9 | C12: シートホーム推進部 | D12: 16120024 | F12: - | G12: 品質監査業務支援 | I12: 5月 | J12: 45023 | K12: 鈴木
A13: 完了 | B13: 10 | C13: シートホーム推進部 | D13: 16120025 | F13: - | G13: 設計品質改善会 | I13: 5月 | J13: 45023 | K13: 鈴木
A14: 完了 | B14: 11 | C14: シートホーム推進部 | D14: 16120026 | F14: - | G14: 品質監査業務支援 | I14: 6月 | J14: 45063 | K14: 鈴木
A15: 完了 | B15: 12 | C15: シートホーム推進部 | D15: 16120027 | F15: - | G15: 設計品質改善会 | I15: 6月 | J15: 45063 | K15: 鈴木
A16: 完了 | B16: 13 | C16: シートホーム推進部 | D16: 16120028 | F16: - | G16: 品質監査業務支援 | I16: 7月 | J16: 45085 | K16: 鈴木
A17: 完了 | B17: 14 | C17: シートホーム推進部 | D17: 16120029 | F17: - | G17: 設計品質改善会 | I17: 7月 | J17: 45085 | K17: 鈴木
A18: 完了 | B18: 15 | C18: シートホーム推進部 | D18: 16120030 | F18: - | G18: 品質監査業務支援 | I18: 8月 | J18: 45112 | K18: 鈴木
A19: 完了 | B19: 16 | C19: シートホーム推進部 | D19: 16120031 | F19: - | G19: 設計品質改善会 | I19: 8月 | J19: 45112 | K19: 鈴木
... A27: 見積着手 | B27: 24 | C27: シートホーム推進部 | D27: 16120039 | F27: - | G27: 設計品質改善会 | I27: 12月 | J27: 45243 | K27: 齊藤
B28: 25 | C28: シートホーム推進部 | D28: 16120040 | F28: - | G28: 品質監査業務支援 | I28: 1月 | J28: 45276 | K28: 齊藤
B29: 26 | C29: シートホーム推進部 | D29: 16120041 | F29: - | G29: 設計品質改善会の運営のサポート | I29: 1月 | J29: 45276 | K29: 齊藤
B30: 27 | C30: シートホーム推進部 | D30: 16120042 | F30: - | G30: 品質監査業務支援 | I30: 2月 | J30: 45309 | K30: 齊藤
B31: 28 | C31: シートホーム推進部 | D31: 16120043 | F31: - | G31: 設計品質改善会 | I31: 2月 | J31: 45309 | K31: 齊藤
B32: 29 | C32: シートホーム推進部 | D32: 16120044 | F32: - | G32: 品質監査業務支援 | I32: 3月 | J32: 45328 | K32: 齊藤
B33: 30 | C33: シートホーム推進部 | D33: 16120045 | F33: - | G33: 設計品質改善会 | I33: 3月 | J33: 45328 | K33: 齊藤
B34: 31 | C34: シートホーム推進部 | D34: 16120046 | F34: - | G34: 品質監査業務支援 | I34: 4月 | J34: 45364 | K34: 齊藤
B35: 32 | C35: シートホーム推進部 | D35: 16120047 | F35: - | G35: 設計品質改善会 | I35: 4月 | J35: 45364 | K35: 齊藤
B36: 33 | C36: 設計品質改善室 | D36: 16120048 | F36: - | G36: 品質監査業務支援 | I36: 5月 | J36: 45390 | K36: 齊藤
B37: 34 | C37: 設計品質改善室 | D37: 16120049 | F37: - | G37: 設計品質改善会 | I37: 5月 | J37: 45390 | K37: 齊藤
B38: 35 | C38: 設計品質改善室 | D38: 16120050 | F38: - | G38: 品質監査業務支援 | I38: 6月 | J38: 45422 | K38: 齊藤
B39: 36 | C39: 設計品質改善室 | D39: 16120051 | F39: - | G39: 設計品質改善会 | I39: 6月 | J39: 45422 | K39: 齊藤
... B55: 52 | C55: 設計品質改善室 | D55: 16120067 | F55: - | G55: 設計品質改善会 | I55: 2月 | J55: 45672 | K55: 久目形
B56: 53 | C56: 設計品質改善室 | D56: 16120068 | F56: - | G56: 品質監査業務支援（内外装） | I56: 2月 | J56: 202/2/29 | K56: 久目形
B57: 54 | C57: 設計品質改善室 | D57: 16120069 | F57: - | G57: 品質監査業務支援 | I57: 3月 | J57: 45699 | K57: 久目形
B58: 55 | C58: 設計品質改善室 | D58: 16120070 | F58: - | G58: 設計品質改善会 | I58: 3月 | J58: 45699 | K58: 久目形
B59: 56 | C59: 設計品質改善室 | D59: 16120071 | F59: - | G59: 品質監査業務支援 | I59: 4月 | J59: 45735 | K59: 久目形
B60: 57 | C60: 設計品質改善室 | D60: 16120072 | F60: - | G60: 設計品質改善会 | I60: 4月 | J60: 45735 | K60: 久目形
B61: 58 | C61: 設計品質改善室 | D61: 16120073 | F61: - | G61: 品質監査業務支援（内外装） | I61: 4月 | J61: 45735 | K61: 久目形
B62: 59 | C62: 設計品質改善室 | D62: 16120074 | F62: - | G62: 品質監査業務支援 | I62: 5月 | J62: 45761 | K62: 丸山
B63: 60 | C63: 設計品質改善室 | D63: 16120075 | F63: - | G63: 設計品質改善会 | I63: 5月 | J63: 45761 | K63: 丸山
B64: 61 | C64: 設計品質改善室 | D64: 16120076 | F64: - | G64: 品質監査業務支援（内外装） | I64: 5月 | J64: 45761 | K64: 丸山
B65: 62 | C65: 設計品質改善室 | D65: 16120077 | F65: - | G65: 品質監査業務支援 | I65: 6月 | J65: 45790 | K65: 丸山
B66: 63 | C66: 設計品質改善室 | D66: 16120078 | F66: - | G66: 設計品質改善会 | I66: 6月 | J66: 45790 | K66: 丸山
B67: 64 | C67: 設計品質改善室 | D67: 16120079 | F67: - | G67: 品質監査業務支援（内外装） | I67: 6月 | J67: 45790 | K67: 丸山
B68: 65 | C68: 設計品質改善室 | D68: 16120080 | F68: - | G68: 品質監査業務支援 | I68: 7月 | J68: 45817 | K68: 久目形
... B73: 70 | C73: 設計品質改善室 | D73: 16120085 | F73: - | G73: 品質監査業務支援（内外装） | I73: 8月 | J73: 45835 | K73: 久目形
B74: 71 | C74: 設計品質改善室 | D74: 16120086 | F74: - | G74: 品質監査業務支援（内外装） | I74: 9月 | J74: 25/8/6 | K74: 久目形
B75: 72 | C75: 設計品質改善室 | D75: 16120087 | F75: - | G75: 品質監査業務支援 | I75: 9月 | J75: 25/8/18 | K75: 久目形
B76: 73 | C76: 設計品質改善室 | D76: 16120088 | F76: - | G76: 設計品質改善会 | I76: 9月 | J76: 25/8/18 | K76: 久目形
B77: 74 | C77: 設計品質改善室 | D77: 16120089 | F77: - | G77: 品質監査業務支援 | I77: 9月 | J77: 25/8/18 | K77: 久目形
B78: 75 | C78: 設計品質改善室 | D78: 16120090 | F78: - | G78: 設計品質改善会 | I78: 9月 | J78: 25/8/18 | K78: 久目形
B79: 76 | C79: 設計品質改善室 | D79: 16120091 | F79: - | G79: 品質監査業務支援（内外装） | I79: 10月 | J79: ’25/9/8 | K79: 久目形
B80: 77 | C80: 設計品質改善室 | D80: 16120092 | F80: - | G80: 品質監査業務支援 | I80: 10月 | J80: ’25/9/8 | K80: 久目形
B81: 78 | C81: 設計品質改善室 | D81: 16120093 | F81: - | G81: 設計品質改善会運営サポート | I81: 10月 | J81: ’25/9/8 | K81: 久目形 | L81: 設計品質改善会⇒設計品質改善会運営サポートに名前変更
B82: 79 | C82: 設計品質改善室 | D82: 16120094 | F82: - | G82: 品質監査業務支援（内外装） | I82: 11月 | J82: ’25/10/6 | K82: 久目形
B83: 80 | C83: 設計品質改善室 | D83: 16120095 | F83: - | G83: 品質監査業務支援 | I83: 11月 | J83: ’25/10/6 | K83: 久目形
B84: 81 | C84: 設計品質改善室 | D84: 16120096 | F84: - | G84: 設計品質改善会運営サポート | I84: 11月 | J84: ’25/10/6 | K84: 久目形
B85: 82 | C85: 設計品質改善室 | D85: 16120097 | F85: - | G85: 品質監査業務支援 | I85: 12月 | J85: ’25/11/10 | K85: 久目形
B86: 83 | C86: 設計品質改善室 | D86: 16120098 | F86: - | G86: 設計品質改善会運営サポート | I86: 12月 | J86: ’25/11/10 | K86: 久目形
B87: 84 | C87: 設計品質改善室 | D87: 16120099 | F87: - | G87: 品質監査業務支援（内外装） | I87: 12月 | J87: ’25/11/14 | K87: 久目形
B88: 85 | C88: 設計品質改善室 | D88: 16120100 | F88: - | G88: 品質監査業務支援 | I88: 1月 | J88: 45996 | K88: 久目形
B89: 86 | C89: 設計品質改善室 | D89: 16120101 | F89: - | G89: 設計品質改善会運営サポート | I89: 1月 | J89: 45996 | K89: 久目形
B90: 87 | C90: 設計品質改善室 | D90: 16120102 | F90: - | G90: 品質監査業務支援（内外装） | I90: 1月 | J90: 45996 | K90: 久目形
B91: 88 | C91: 設計品質改善室 | D91: 16120103 | F91: -
B92: 89 | C92: 設計品質改善室 | D92: 16120104 | F92: -
B93: 90 | C93: 設計品質改善室 | D93: 16120105
B94: 91 | C94: 設計品質改善室 | D94: 16120106
D95: 16120107
D96: 16120108
D97: 16120109
D98: 16120110

Sheet 技管
A1: 2024年 | C1: エンジニアリングサービス部 見積書・請求書発行管理台帳 | H1: 見積書(税抜金額)
A2: 企業名： | C2: トヨタ紡織(株)
A3: タスク | B3: No | C3: 部署名 | D3: 見積/請求番号 | E3: 発注番号 | F3: 業務計画書No | G3: 案件名 | H3: 見積金額 | I3: 見積月 | J3: 発行日 | K3: 発行者 | L3: 備考
A4: 完了 | B4: 1 | C4: 技術管理部 | D4: 16124001 | E4: SQ2021-0062 | F4: - | G4: 単価改定 | I4: 1月 | J4: 45651 | K4: 久目形
B5: 2 | D5: 16124002
B6: 3 | D6: 16124003
B7: 4 | D7: 16124004
B8: 5 | D8: 16124005
B9: 6 | D9: 16124006
B10: 7 | D10: 16124007
B11: 8 | D11: 16124008
B12: 9 | D12: 16124009
B13: 10 | D13: 16124010
B14: 11 | D14: 16124011
B15: 12 | D15: 16124012
B16: 13 | D16: 16124013
... B70: 67 | D70: 16120082

Sheet デザイン部
A1: 2024年 | C1: エンジニアリングサービス部 見積書・請求書発行管理台帳 | H1: 見積書(税抜金額)
A2: 企業名： | C2: トヨタ紡織(株)
A3: タスク | B3: No | C3: 部署名 | D3: 見積/請求番号 | E3: 発注番号 | F3: 業務計画書No | G3: 案件名 | H3: 見積金額 | I3: 見積月 | J3: 発行日 | K3: 発行者 | L3: 備考
B4: 1 | C4: デザイン部 | D4: 16125001 | E4: SQ2021-0062 | F4: - | G4: デザインデータ | I4: 1月 | J4: 45679 | K4: 久目形 | L4: ブレンダ
B5: 2 | C5: デザイン部 | D5: 16125002 | G5: デザインデータ | I5: 2月 | J5: 45679 | K5: 久目形 | L5: スケッチ
B6: 3 | C6: デザイン部 | D6: 16125003 | G6: デザインデータ | I6: 2月 | J6: 45700 | K6: 久目形 | L6: スケッチ
B7: 4 | C7: デザイン部 | D7: 16125004 | G7: コンセプトデザインモデル開発 | J7: 45867 | K7: 久目形
B8: 5 | D8: 16125005 | F8: Phase1 | G8: コンセプトデザインモデル開発 | J8: 45867 | K8: 久目形
B9: 6 | D9: 16125006 | F9: Phase2 | G9: コンセプトデザインモデル開発 | J9: 45867 | K9: 久目形
B10: 7 | D10: 16125007 | F10: Phase3 | G10: コンセプトデザインモデル開発 | J10: 45867 | K10: 久目形
B11: 8 | D11: 16125008 | F11: Phase4 | G11: コンセプトデザインモデル開発 | J11: 45867 | K11: 久目形
B12: 9 | C12: デザイン部 | D12: 16125009 | F12: Phase1 | G12: コンセプトデザインモデル開発_金額見直し | I12: 10月 | J12: 25/10/23 | K12: 齊藤
B13: 10 | C13: デザイン部 | D13: 16125010 | F13: Phase2 | G13: コンセプトデザインモデル開発_金額見直し | I13: 10月 | J13: 25/10/23 | K13: 齊藤
B14: 11 | C14: デザイン部 | D14: 16125011 | F14: Phase3 | G14: コンセプトデザインモデル開発_金額見直し | I14: 10月 | J14: 25/10/23 | K14: 齊藤
B15: 12 | C15: デザイン部 | D15: 16125012 | F15: Phase4 | G15: コンセプトデザインモデル開発_金額見直し | I15: 10月 | J15: 25/10/23 | K15: 齊藤
B16: 13 | C16: デザイン部 | D16: 16125013 | F16: Phase5 | G16: コンセプトデザインモデル開発_金額見直し | I16: 10月 | J16: 25/10/23 | K16: 齊藤
B17: 14 | C17: デザイン部 | D17: 16125014 | F17: 集約版 | G17: コンセプトデザインモデル開発_金額見直し | I17: 10月 | J17: 25/10/23 | K17: 齊藤
B18: 15 | D18: 16125015
B19: 16 | D19: 16125016
B20: 17 | D20: 16125017
B21: 18 | D21: 16125018
B22: 19 | D22: 16125019
B23: 20 | D23: 16125020
B24: 21 | D24: 16125021
B25: 22 | D25: 16125022
B26: 23 | D26: 16125023
B27: 24 | D27: 16125024
B55: 52 | D55: 16120067
B56: 53 | D56: 16120068
... B70: 67 | D70: 16120082

Sheet 空間ビジョニアリング部
A1: 2024年 | C1: エンジニアリングサービス部 見積書・請求書発行管理台帳 | H1: 見積書(税抜金額)
A2: 企業名： | C2: トヨタ紡織(株)
A3: タスク | B3: No | C3: 部署名 | D3: 見積/請求番号 | E3: 発注番号 | F3: 業務計画書No | G3: 案件名 | H3: 見積金額 | I3: 見積月 | J3: 発行日 | K3: 発行者 | L3: 備考
B4: 1 | C4: 空間ビジョニアリング部 | D4: 16126001 | E4: SQ2021-0062 | F4: 15266 | G4: POD 図面作成 | I4: ３月 | J4: 45720 | K4: 久目形
B5: 2 | D5: 16126002
B6: 3 | D6: 16126003
B7: 4 | D7: 16126004
B8: 5 | D8: 16126005
B9: 6 | D9: 16126006
B10: 7 | D10: 16126007
B11: 8 | D11: 16126008
B12: 9 | D12: 16126009
B13: 10 | D13: 16126010
B14: 11 | D14: 16126011
B15: 12 | D15: 16126012
B16: 13 | D16: 16126013
... B27: 24 | D27: 16126024
D28: 16126025
B55: 52 | D55: 16120067
B56: 53 | D56: 16120068
B57: 54 | D57: 16120069
B58: 55 | D58: 16120070
B59: 56 | D59: 16120071
B60: 57 | D60: 16120072
B61: 58 | D61: 16120073
B62: 59 | D62: 16120074
B63: 60 | D63: 16120075
B64: 61 | D64: 16120076
B65: 62 | D65: 16120077
B66: 63 | D66: 16120078
... B70: 67 | D70: 16120082

Sheet シート計画部　SAT推進室
A1: 2024年 | C1: エンジニアリングサービス部 見積書・請求書発行管理台帳 | H1: 見積書(税抜金額)
A2: 企業名： | C2: トヨタ紡織(株)
A3: タスク | B3: No | C3: 部署名 | D3: 見積/請求番号 | E3: 発注番号 | F3: 業務計画書No | G3: 案件名 | H3: 見積金額 | I3: 見積月 | J3: 発行日 | K3: 発行者 | L3: 備考
B4: 1 | C4: シート計画部 SAT推進室 | D4: 16127001 | E4: SQ2021-0062 | F4: 16732 | G4: 900D | I4: 8月 | J4: ’25/7/21 | K4: 久目形
B5: 2 | C5: シート計画部 SAT推進室 | D5: 16127002 | F5: 16885 | G5: 900D | I5: 9月 | J5: 45889 | K5: 久目形
B6: 3 | C6: シート計画部 SAT推進室 | D6: 16127003 | F6: 17187 | G6: 900D | I6: 10月 | J6: 45916 | K6: 久目形
B7: 4 | C7: シート計画部 SAT推進室 | D7: 16127004 | F7: 17491 | G7: 800D | I7: 11月 | J7: 45946 | K7: 久目形 | L7: no.3の業務名変更
B8: 5 | C8: シート計画部 SAT推進室 | D8: 16127005 | F8: 17851 | G8: 800D | I8: 12月 | J8: 45975 | K8: 久目形
B9: 6 | C9: シート計画部 SAT推進室 | D9: 16127006 | F9: 18142 | G9: 800D | I9: １月 | J9: 46008 | K9: 久目形
B10: 7 | D10: 16127007
B11: 8 | D11: 16127008
B12: 9 | D12: 16127009
B13: 10 | D13: 16127010
B14: 11 | D14: 16127011
B15: 12 | D15: 16127012
B16: 13 | D16: 16127013
B17: 14 | D17: 16127014
B18: 15 | D18: 16127015
B19: 16 | D19: 16127016
B20: 17 | D20: 16127017
B21: 18 | D21: 16127018
... B27: 24 | D27: 16127024
D28: 16127025
B55: 52 | D55: 16120067
B56: 53 | D56: 16120068
B57: 54 | D57: 16120069
B58: 55 | D58: 16120070
B59: 56 | D59: 16120071
B60: 57 | D60: 16120072
B61: 58 | D61: 16120073
B62: 59 | D62: 16120074
B63: 60 | D63: 16120075
B64: 61 | D64: 16120076
B65: 62 | D65: 16120077
B66: 63 | D66: 16120078
... B70: 67 | D70: 16120082

Sheet TBEU
A1: 2024年 | C1: エンジニアリングサービス部 見積書・請求書発行管理台帳 | H1: 見積書(税抜金額)
A2: 企業名： | C2: トヨタ紡織欧州
A3: タスク | B3: No | C3: 部署名 | D3: 見積/請求番号 | E3: 発注番号 | F3: 業務計画書No | G3: 案件名 | H3: 見積金額 | I3: 見積月 | J3: 発行日 | K3: 発行者 | L3: 備考
B4: 1 | C4: トヨタ紡織欧州 | D4: 16123001 | E4: SQ2021-0062 | F4: - | G4: FR被せシート開発 | H4: 5579600 | I4: 9月 | J4: 45188 | K4: 齊藤
B5: 2 | C5: トヨタ紡織欧州 | D5: 16123002 | F5: - | G5: シートモック制作・設計 | I5: 2月 | J5: 44964 | K5: 齊藤
B6: 3 | D6: 16123003
B7: 4 | D7: 16123004
B8: 5 | D8: 16123005
B9: 6 | D9: 16123006
B10: 7 | D10: 16123007
B11: 8 | D11: 16123008
B12: 9 | D12: 16123009
B13: 10 | D13: 16123010
B14: 11 | D14: 16123011
B15: 12 | D15: 16123012
B16: 13 | D16: 16123013
B17: 14 | D17: 16123014
... B27: 24 | D27: 16123024

Sheet 内外装部品センター
A1: 2023年 | C1: エンジニアリングサービス部 見積書・請求書発行管理台帳 | H1: 見積書(税抜金額)
A2: 企業名： | C2: トヨタ紡織(株)
A3: タスク | B3: No | C3: 部署名 | D3: 見積/請求番号 | E3: 発注番号 | F3: 業務計画書No | G3: 案件名 | H3: 見積金額 | I3: 見積月 | J3: 発行日 | K3: 発行者 | L3: 備考
A4: 完了 | B4: 1 | C4: 内外装部品センター | D4: 16318002 | F4: - | G4: 亀甲リブガイド作成 | H4: 320000 | I4: 12ｰ1月 | J4: ? | K4: 安居
A5: 完了 | B5: 2 | C5: 内外装部品センター | D5: 16122003 | F5: - | G5: 亀甲リブガイド作成 | H5: 488000 | I5: 2-3月 | J5: 44965 | K5: 安居
D6: 16122004

Sheet 注文書(外注・物品購入)
A1: 2024年 | C1: エンジニアリングサービス部 発注書発行管理台帳 | H1: 44935
A3: タスク | B3: No | C3: 注文書番号 | D3: 拠点名 | E3: 依頼者 | F3: 注文先 | G3: 発行日 | H3: 見積書番号
B4: 1
B5: 2
B6: 3
B7: 4
B8: 5
B9: 6
B10: 7
B11: 8
B12: 9
B13: 10

Sheet 委託プロジェクトコード
B1: エンジニアリングサービス部 プロジェクトコード
H2: 45401
C3: 見積書/請求書 | H3: 備考
B4: 企業名 | C4: 企業コード | D4: 委託通称名 | E4: 部署名 | F4: 部署コード | G4: 最終番号
B5: 小島プレス工業(株) | C5: 05 | D5: - | E5: - | F5: 101
B6: トヨタ自動車(株) | C6: 10 | D6: IT ｽﾏｰﾄｼﾃｨ | E6: DX開発推進部ｻｰﾋﾞｽPFｸﾞﾙｰﾌﾟ | F6: 101 | G6: 10101002 | H6: 2021年4月よりｴﾝｼﾞﾆｱﾘﾝｸﾞﾋﾞｼﾞﾈｽ開発部へ移管
D7: IT TLION | E7: DX開発推進部商品企画ﾌﾟﾛｾｽ開発ｸﾞﾙｰﾌﾟ | F7: 102 | G7: 10102004 | H7: 2021年6月末にて終了
D8: 法規認証 | E8: 法規認証部企画室ラベル・VINｸﾞﾙｰﾌﾟ | F8: 103
B9: トヨタ車体(株) | C9: 13 | D9: 内装 | E9: 内装設計部内装設計室 | F9: 101 | G9: 13101002 | H9: 2021年4月初旬にて終了
D10: シート | E10: 内装設計部ｼｰﾄ設計室 | F10: 102 | G10: 13102001 | H10: 2021年4月末にて終了
B11: 豊田合成(株) | C11: 14 | D11: - | E11: - | F11: 101
B12: トヨタ紡織(株) | C12: 16 | E12: 第1ｼｰﾄ設計部 | F12: 100
E13: 第1ｼｰﾄ設計部第13ｼｰﾄ設計室 | F13: 101
D14: 設計 | E14: Frｼｰﾄ骨格設計部 | F14: 102
D15: 品質 | E15: Frｼｰﾄ骨格設計部 | F15: 103 | G15: 16103005 | H15: 部署コード『102』へ統合
E16: Rrｼｰﾄ骨格設計部 | F16: 104
E17: 新興国ｼｰﾄ設計室 | F17: 105 | G17: 16105146 | H17: 2022年4月よりｸﾞﾛｰﾊﾞﾙｼｰﾄ設計部へ移管
E18: 第2ｼｰﾄ設計部 | F18: 106 | G18: 16106002
E19: 第3ｼｰﾄ設計部 | F19: 107
E20: 第1ｼｰﾄ設計部第12ｼｰﾄ設計室 | F20: 108
E21: ｼｰﾄｽﾄﾗﾃﾞｼﾞｰｸｵﾘﾃｨ部品質改善室 | F21: 109 | G21: 16109031 | H21: 2022年5月よりｼｰﾄﾎｰﾑ推進部へ移管
E22: ｼｰﾄｽﾄﾗﾃﾞｼﾞｰｸｵﾘﾃｨ部第2ｼｰﾄ品質改善室 | F22: 110 | G22: 16110005 | H22: 2022年5月よりｼｰﾄﾎｰﾑ推進部へ移管
E23: 内外装実験部 | F23: 111
E24: 内外装ﾄﾘﾑ設計部 | F24: 112
E25: 第1ｼｰﾄ設計部第11ｼｰﾄ設計室 | F25: 113 | G25: 16113001
E26: ｼｰﾄ実験部 | F26: 114
E27: 内外装先行開発部 | F27: 115
E28: ﾄﾞｱﾄﾘﾑ設計部 | F28: 116
E29: ｼｰﾄ機能品設計部 | F29: 117
E30: ACT | F30: 118
E31: ｸﾞﾛｰﾊﾞﾙｼｰﾄ設計室 | F31: 119
E32: ｼｰﾄﾎｰﾑ推進部 | F32: 120
E33: ｼｰﾄ部品開発部 | F33: 121 | G33: 16121002
E34: 内外装部品ｾﾝﾀｰ | F34: 122
E35: 第4ｼｰﾄ設計部 | F35: 123
E36: 技管部 | F36: 124 | G36: 16124001
E37: デザイン部 | F37: 125 | G37: 16125001
E38: 空間ビジョニアリング部 | F38: 126
E39: シート計画部 SAT推進室 ２G | F39: 127
B40: 三井E&Sシステム技研(株) | C40: 19 | D40: - | E40: 製造事業本部業務管理ｸﾞﾙｰﾌﾟ | F40: 101
B41: IPGオートモーティブ(株) | C41: 50 | D41: - | E41: - | F41: 101 | G41: 50101004 | H41: 2021年9月よりｴﾝｼﾞﾆｱﾘﾝｸﾞﾋﾞｼﾞﾈｽ開発部へ移管 →終了
B42: (株)SUBARU | C42: 51 | E42: ﾎﾞﾃﾞｨ設計部 | F42: 000
B43: サイバネットSMBE(株) | C43: 53 | D43: - | E43: - | F43: 101 | H43: 2021年1月より派遣契約へ変更
B44: 日産自動車(株) | C44: 54 | D44: PT | E44: ﾊﾟﾜｰﾄﾚｲﾝEV先進技術開発部 次世代ﾊﾟﾜｰﾄﾚｲﾝEVﾕﾆｯﾄ開発ｸﾞﾙｰﾌﾟ | F44: 101 | G44: 54101026 | H44: 2021年9月よりｴﾝｼﾞﾆｱﾘﾝｸﾞﾋﾞｼﾞﾈｽ開発部へ移管 →事業企画部へ
D45: HMI | E45: ｻｰﾋﾞｽｻﾎﾟｰﾄ調達部 | F45: 102 | G45: 54102003
B46: 本田技研工業(株) | C46: 58 | D46: - | E46: - | F46: 101 | H46: 2021年9月よりｴﾝｼﾞﾆｱﾘﾝｸﾞﾋﾞｼﾞﾈｽ開発部へ移管 →2023年1月よりR&D部とEB部統合
B47: 大丸工業(株) | C47: 66 | D47: NTC PT | E47: 自動車部開発･試作ﾁｰﾑ | F47: 111 | G47: 54111010 | H47: 2021年9月よりｴﾝｼﾞﾆｱﾘﾝｸﾞﾋﾞｼﾞﾈｽ開発部へ移管 →事業企画部へ
B48: (株)アイシン・デジタルエンジニアリング | C48: 59 | E48: ﾃﾞｼﾞﾀﾙ技術部 | F48: 101 | H48: 2023年1月よりR＆DとEB部統合
B49: ビューテック(株) | C49: 69 | E49: 技術ｾﾝﾀｰ 製品開発室 設計ｸﾞﾙｰﾌﾟ | F49: 101 | H49: 2023年1月よりR＆DとEB部統合
B50: 泰東工業(株) | C50: 70 | E50: 設計課 | F50: 101 | H50: 2023年1月よりR＆DとEB部統合
B51: (株)オーツ―・パートナーズ | C51: 71 | F51: 101 | H51: 2023年1月よりR＆DとEB部統合

Sheet 支払い時期に関して
B1: 外注・物品購入に対する支払い時期に関して
F3: 44433 | G3: 作成
B5: １．支払い日
C6: 毎月 5日、15日、20日、25日、月末日
C7: ※休日/祝日の場合は、その前日が支払日となる
C9: 備考(10日に支払いされない理由)
C10: 基本、15日、25日、末日の3日が支払い日
C11: 5日、20日は役員への支払いがあるため、ついでに支払って頂けるとのこと
B13: ２．請求書必着日
C14: 稼働5日前
C16: 【例】2021年9月の場合
C17: ・5日(日)休日のため、3日(金)支払い | D17: → 8月30日(月)必着
C18: ・15日(水)支払い | D18: → 9日(木)必着
C19: ・20日(月)祝日のため、17日(金)支払い | D19: → 13日(月)必着
C20: ・25日(土)休日のため、24日(金)支払い | D20: → 20日(月)必着
C21: ・30日(木)支払い | D21: → 24日(金)必着
B23: ３．上記支払日以外で支払って頂きたい場合
C24: 至急支払い稟議申請を行う

Sheet 採番ルール
B1: エンジニアリングサービス部 採番ルール | G1: 44411 | H1: 更新 | I1: ※４訂正、５追加
G2: 44277 | H2: 更新 | I2: ※４追加
G3: 44216 | H3: 現在
B5: １．見積書番号と請求書番号は同じ番号とする
C6: トヨタ紡織の場合
C7: 企業コード | D7: 部署コード | E7: 連番
C8: １６ | D8: １０１ | E8: ００１
C9: ※企業コードは管理部確認
C11: 見積書NO. | D11: 16101001
C12: 請求書NO. | D12: 16101001
B14: ２．見積書1件につき請求書を複数件発行する場合は、-1,2,3…をふる
C15: 見積書NO. | D15: 16101002
C16: 3月請求書NO. | D16: 16101002-1
C17: 6月請求書NO. | D17: 16101002-2
B19: ３．出張経費の請求書を発行する場合は-Sをふる
C20: 見積書NO. | D20: 16101003
C21: 請求書NO. | D21: 16101003
C22: 請求書NO. | D22: 16101003-S
B24: ４．注文書を発行する場合は下記の通りとする
C25: 日産PTの場合
C26: 企業コード | D26: 部署コード | E26: 期 | F26: 連番
C27: ５４ | D27: １ | E27: ２３ | F27: ００１
C29: 注文書NO. | D29: 54123001
B31: ４．注文書番号と稟議書番号は同じ番号とする
C32: 稟議書NO. | D32: 2089
C33: 注文書NO. | D33: 2089
B35: ５．稟議書1件につき注文書を複数件発行する場合は、-1,2,3…をふる
C36: 稟議書NO. | D36: 2090
C37: 注文書NO. | D37: 2090-1
C38: 注文書NO. | D38: 2090-2

Sheet タスク
B2: タスク
B3: 見積！
B4: 見積着手 | C4: 確認中
B5: 見積完了
B6: 進行中
B7: 請求着手 | C7: 開始待ち
B8: 未着手
B9: 完了 | C9: 入金待ち
B10: 中止
B11: 保留
B12: 客先待ち
B13: 移管

Sheet 確認用
C1: 月TB
B2: =Fr骨格!B3 -> No | C2: =Fr骨格!C3 -> 部署名 | D2: =Fr骨格!D3 -> 見積/請求番号 | E2: =Fr骨格!E3 -> 発注番号 | F2: =Fr骨格!F3 -> 業務計画書No | G2: =Fr骨格!G3 -> 案件名 | H2: =Fr骨格!H3 -> 見積金額 | I2: =Fr骨格!I3 -> 見積月 | ... K2: =Fr骨格!K3 -> 発行者
B3: ='A12'!B23 -> 20
B4: =Fr骨格!B28 -> 25
B5: =Fr骨格!B29 -> 26
B6: =Fr骨格!B30 -> 27
B7: =Rr骨格!B26 -> 23
B8: =Rr骨格!B27 -> 24
B9: =Rr骨格!B28 -> 25
B10: =#REF! -> #REF!
B11: =NT!B18 -> 15
B12: =ACT!B14 -> 11
B13: =GS!B87 -> 84
B14: =GS!B88 -> 85
B15: =GS!B89 -> 86
B16: =GS!B90 -> 87
B17: =GS!B91 -> 88
B18: =GS!B92 -> 89
B19: =GS!B93 -> 90
